Workbook
Name SimNao: Metas!$Q$2:$Q$3

Sheet Metas
A1: ID_Area | B1: Área | C1: Tema | D1: ID_Meta | E1: Descrição da Meta | F1: Status da Meta | G1: % Avanço | H1: Data Inicio | I1: Data Fim | J1: Duração | K1: ID_Responsavel | L1: Responsável | M1: Empresa | N1: Observação de Acompanhamento | O1: Concluí em 2025?
A2: =IFERROR(INDEX(Tabela2[ID_Area], MATCH(B2,Tabela2[Area], 0)), "Não encontrado") -> 1004 | B2: Licenciamento & Regulatório | C2: Licenciamento | D2: =ROW(D2) +98 -> 100 | E2: Atender a Lei SNUC/SEUC e Lei de FAUNA dentro dos prazos estabelecidos pelos órgãos reguladores | F2: =IF(G2=1,"Concluído", IF(TODAY()>I2,"Atrasado", IF(AND(G2=0,TODAY()<I2),"Não iniciado", "Em Andamento"))) -> Atrasado | G2: {=SUMPRODUCT( (Atividades!$E$2:$E$598=Metas!E2) * (Atividades!$O$2:$O$598=Metas!L2), Atividades!$I$2:$I$598, Atividades!$J$2:$J$598 ) / SUMPRODUCT( (Atividades!$E$2:$E$598=Metas!E2) * (Atividades!$O$2:$O$598=Metas!L2), Atividades!$J$2:$J$598 )} -> 0.96842828 | H2: 45658 | I2: 46008 | J2: =I2-H2 -> 350 | K2: =IFERROR(INDEX(Tabela3[ID_Responsavel], MATCH(L2,Tabela3[[Responsáveis ]], 0)), "Não encontrado") -> 25 | L2: Thiago Viana | M2: SVPM | N2: Pendência da SEMAD. Dentro das ações de responsabilidade GMA, tudo foi cumprido conforme proposto para 2025. Continuidade 2026 conforme aditivo TCCA e Aditivos contratuai | O2: Não | Q2: Sim
A3: =IFERROR(INDEX(Tabela2[ID_Area], MATCH(B3,Tabela2[Area], 0)), "Não encontrado") -> 1004 | B3: Licenciamento & Regulatório | C3: Licenciamento | D3: =ROW(D3) +98 -> 101 | E3: Concluir o processo de solicitação de aditivo ao Termo de Compromisso Ambiental do SNUC/SEUC do processo de complementação das estruturas licenciadas_Thiago | F3: =IF(G3=1,"Concluído", IF(TODAY()>I3,"Atrasado", IF(AND(G3=0,TODAY()<I3),"Não iniciado", "Em Andamento"))) -> Concluído | G3: {=SUMPRODUCT( (Atividades!$E$2:$E$598=Metas!E3) * (Atividades!$O$2:$O$598=Metas!L3), Atividades!$I$2:$I$598, Atividades!$J$2:$J$598 ) / SUMPRODUCT( (Atividades!$E$2:$E$598=Metas!E3) * (Atividades!$O$2:$O$598=Metas!L3), Atividades!$J$2:$J$598 )} -> 1 | H3: 45658 | I3: 45933 | J3: =I3-H3 -> 275 | K3: =IFERROR(INDEX(Tabela3[ID_Responsavel], MATCH(L3,Tabela3[[Responsáveis ]], 0)), "Não encontrado") -> 25 | L3: Thiago Viana | M3: SVPM | Q3: Não
A4: =IFERROR(INDEX(Tabela2[ID_Area], MATCH(B4,Tabela2[Area], 0)), "Não encontrado") -> 1004 | B4: Licenciamento & Regulatório | C4: SGA | D4: =ROW(D4) +98 -> 102 | E4: Desenvolver e implementar estratégia para implantação da SGA ISO 14001 | F4: =IF(G4=1,"Concluído", IF(TODAY()>I4,"Atrasado", IF(AND(G4=0,TODAY()<I4),"Não iniciado", "Em Andamento"))) -> Atrasado | G4: {=SUMPRODUCT( (Atividades!$E$2:$E$598=Metas!E4) * (Atividades!$O$2:$O$598=Metas!L4), Atividades!$I$2:$I$598, Atividades!$J$2:$J$598 ) / SUMPRODUCT( (Atividades!$E$2:$E$598=Metas!E4) * (Atividades!$O$2:$O$598=Metas!L4), Atividades!$J$2:$J$598 )} -> 0.78294885 | H4: 45717 | I4: 45960 | J4: =I4-H4 -> 243 | K4: =IFERROR(INDEX(Tabela3[ID_Responsavel], MATCH(L4,Tabela3[[Responsáveis ]], 0)), "Não encontrado") -> 25 | L4: Thiago Viana | M4: SVPM | N4: Continuidade em 2026. Itens do Manual SGA e Aspectos e Impactos com base na nova estrutura e planejamento integrado da Gerência. Alinhado com Gestor a prorrogação da meta, devido foco em outros temas prioritários (RDA e Licenciamentos) | O4: Não
A5: =IFERROR(INDEX(Tabela2[ID_Area], MATCH(B5,Tabela2[Area], 0)), "Não encontrado") -> 1004 | B5: Licenciamento & Regulatório | C5: Licenciamento | D5: =ROW(D5) +98 -> 103 | E5: Cumprir plano de licenciamento (ASV, Heap Leaching, renovação, integração)_Thiago | F5: =IF(G5=1,"Concluído", IF(TODAY()>I5,"Atrasado", IF(AND(G5=0,TODAY()<I5),"Não iniciado", "Em Andamento"))) -> Concluído | G5: {=SUMPRODUCT( (Atividades!$E$2:$E$598=Metas!E5) * (Atividades!$O$2:$O$598=Metas!L5), Atividades!$I$2:$I$598, Atividades!$J$2:$J$598 ) / SUMPRODUCT( (Atividades!$E$2:$E$598=Metas!E5) * (Atividades!$O$2:$O$598=Metas!L5), Atividades!$J$2:$J$598 )} -> 1 | H5: 45659 | I5: 46004 | J5: =I5-H5 -> 345 | K5: =IFERROR(INDEX(Tabela3[ID_Responsavel], MATCH(L5,Tabela3[[Responsáveis ]], 0)), "Não encontrado") -> 25 | L5: Thiago Viana | M5: SVPM
A6: =IFERROR(INDEX(Tabela2[ID_Area], MATCH(B6,Tabela2[Area], 0)), "Não encontrado") -> 1004 | B6: Licenciamento & Regulatório | C6: Licenciamento | D6: =ROW(D6) +98 -> 104 | E6: Desenvolver Masterplan de Licenciamento Ambiental da SVPM_Thiago | F6: =IF(G6=1,"Concluído", IF(TODAY()>I6,"Atrasado", IF(AND(G6=0,TODAY()<I6),"Não iniciado", "Em Andamento"))) -> Concluído | G6: {=SUMPRODUCT( (Atividades!$E$2:$E$598=Metas!E6) * (Atividades!$O$2:$O$598=Metas!L6), Atividades!$I$2:$I$598, Atividades!$J$2:$J$598 ) / SUMPRODUCT( (Atividades!$E$2:$E$598=Metas!E6) * (Atividades!$O$2:$O$598=Metas!L6), Atividades!$J$2:$J$598 )} -> 1 | H6: 45901 | I6: 46006 | J6: =I6-H6 -> 105 | K6: =IFERROR(INDEX(Tabela3[ID_Responsavel], MATCH(L6,Tabela3[[Responsáveis ]], 0)), "Não encontrado") -> 25 | L6: Thiago Viana | M6: SVPM
A7: =IFERROR(INDEX(Tabela2[ID_Area], MATCH(B7,Tabela2[Area], 0)), "Não encontrado") -> 1004 | B7: Licenciamento & Regulatório | C7: SGA | D7: =ROW(D7) +98 -> 105 | E7: Implementar sistema de requisitos legais ambientais | F7: =IF(G7=1,"Concluído", IF(TODAY()>I7,"Atrasado", IF(AND(G7=0,TODAY()<I7),"Não iniciado", "Em Andamento"))) -> Concluído | G7: {=SUMPRODUCT( (Atividades!$E$2:$E$598=Metas!E7) * (Atividades!$O$2:$O$598=Metas!L7), Atividades!$I$2:$I$598, Atividades!$J$2:$J$598 ) / SUMPRODUCT( (Atividades!$E$2:$E$598=Metas!E7) * (Atividades!$O$2:$O$598=Metas!L7), Atividades!$J$2:$J$598 )} -> 1 | H7: 45658 | I7: 45901 | J7: =I7-H7 -> 243 | K7: =IFERROR(INDEX(Tabela3[ID_Responsavel], MATCH(L7,Tabela3[[Responsáveis ]], 0)), "Não encontrado") -> 3 | L7: Anna Laura | M7: SESI
A8: =IFERROR(INDEX(Tabela2[ID_Area], MATCH(B8,Tabela2[Area], 0)), "Não encontrado") -> 1004 | B8: Licenciamento & Regulatório | C8: SGA | D8: =ROW(D8) +98 -> 106 | E8: Realizar gap analysis da ISO14001 nas áreas | F8: =IF(G8=1,"Concluído", IF(TODAY()>I8,"Atrasado", IF(AND(G8=0,TODAY()<I8),"Não iniciado", "Em Andamento"))) -> Concluído | G8: {=SUMPRODUCT( (Atividades!$E$2:$E$598=Metas!E8) * (Atividades!$O$2:$O$598=Metas!L8), Atividades!$I$2:$I$598, Atividades!$J$2:$J$598 ) / SUMPRODUCT( (Atividades!$E$2:$E$598=Metas!E8) * (Atividades!$O$2:$O$598=Metas!L8), Atividades!$J$2:$J$598 )} -> 1 | H8: 45677 | I8: 46021 | J8: =I8-H8 -> 344 | K8: =IFERROR(INDEX(Tabela3[ID_Responsavel], MATCH(L8,Tabela3[[Responsáveis ]], 0)), "Não encontrado") -> 3 | L8: Anna Laura | M8: SESI
A9: =IFERROR(INDEX(Tabela2[ID_Area], MATCH(B9,Tabela2[Area], 0)), "Não encontrado") -> 1004 | B9: Licenciamento & Regulatório | C9: Regulatório | D9: =ROW(D9) +98 -> 107 | E9: Estruturação da BASE DE DADOS e plano de atendimento aos itens regulatórios Fundiários, Minerários e Passivos Ambientais das propriedades_AnnaLaura | F9: =IF(G9=1,"Concluído", IF(TODAY()>I9,"Atrasado", IF(AND(G9=0,TODAY()<I9),"Não iniciado", "Em Andamento"))) -> Concluído | G9: {=SUMPRODUCT( (Atividades!$E$2:$E$598=Metas!E9) * (Atividades!$O$2:$O$598=Metas!L9), Atividades!$I$2:$I$598, Atividades!$J$2:$J$598 ) / SUMPRODUCT( (Atividades!$E$2:$E$598=Metas!E9) * (Atividades!$O$2:$O$598=Metas!L9), Atividades!$J$2:$J$598 )} -> 1 | H9: 45677 | I9: 46021 | J9: =I9-H9 -> 344 | K9: =IFERROR(INDEX(Tabela3[ID_Responsavel], MATCH(L9,Tabela3[[Responsáveis ]], 0)), "Não encontrado") -> 3 | L9: Anna Laura | M9: SESI | O9: Sim
A10: =IFERROR(INDEX(Tabela2[ID_Area], MATCH(B10,Tabela2[Area], 0)), "Não encontrado") -> 1004 | B10: Licenciamento & Regulatório | C10: Licenciamento | D10: =ROW(D10) +98 -> 108 | E10: Concluir o processo de solicitação de aditivo ao Termo de Compromisso Ambiental do SNUC/SEUC do processo de complementação das estruturas licenciadas_AnnaLaura | F10: =IF(G10=1,"Concluído", IF(TODAY()>I10,"Atrasado", IF(AND(G10=0,TODAY()<I10),"Não iniciado", "Em Andamento"))) -> Concluído | G10: {=SUMPRODUCT( (Atividades!$E$2:$E$598=Metas!E10) * (Atividades!$O$2:$O$598=Metas!L10), Atividades!$I$2:$I$598, Atividades!$J$2:$J$598 ) / SUMPRODUCT( (Atividades!$E$2:$E$598=Metas!E10) * (Atividades!$O$2:$O$598=Metas!L10), Atividades!$J$2:$J$598 )} -> 1 | H10: 45659 | I10: 46004 | J10: =I10-H10 -> 345 | K10: =IFERROR(INDEX(Tabela3[ID_Responsavel], MATCH(L10,Tabela3[[Responsáveis ]], 0)), "Não encontrado") -> 3 | L10: Anna Laura | M10: SESI
A11: =IFERROR(INDEX(Tabela2[ID_Area], MATCH(B11,Tabela2[Area], 0)), "Não encontrado") -> 1004 | B11: Licenciamento & Regulatório | C11: Licenciamento | D11: =ROW(D11) +98 -> 109 | E11: Acompanhar o processo de Renovação da Licença de Instalação pelo sistema SGA junto a SEMAD | F11: =IF(G11=1,"Concluído", IF(TODAY()>I11,"Atrasado", IF(AND(G11=0,TODAY()<I11),"Não iniciado", "Em Andamento"))) -> Concluído | G11: {=SUMPRODUCT( (Atividades!$E$2:$E$598=Metas!E11) * (Atividades!$O$2:$O$598=Metas!L11), Atividades!$I$2:$I$598, Atividades!$J$2:$J$598 ) / SUMPRODUCT( (Atividades!$E$2:$E$598=Metas!E11) * (Atividades!$O$2:$O$598=Metas!L11), Atividades!$J$2:$J$598 )} -> 1 | H11: 45659 | I11: 46021 | J11: =I11-H11 -> 362 | K11: =IFERROR(INDEX(Tabela3[ID_Responsavel], MATCH(L11,Tabela3[[Responsáveis ]], 0)), "Não encontrado") -> 3 | L11: Anna Laura | M11: SESI
A12: =IFERROR(INDEX(Tabela2[ID_Area], MATCH(B12,Tabela2[Area], 0)), "Não encontrado") -> 1004 | B12: Licenciamento & Regulatório | C12: Licenciamento | D12: =ROW(D12) +98 -> 110 | E12: Cumprir plano de licenciamento (ASV, Heap Leaching, renovação, integração)_Nadrielle | F12: =IF(G12=1,"Concluído", IF(TODAY()>I12,"Atrasado", IF(AND(G12=0,TODAY()<I12),"Não iniciado", "Em Andamento"))) -> Concluído | G12: {=SUMPRODUCT( (Atividades!$E$2:$E$598=Metas!E12) * (Atividades!$O$2:$O$598=Metas!L12), Atividades!$I$2:$I$598, Atividades!$J$2:$J$598 ) / SUMPRODUCT( (Atividades!$E$2:$E$598=Metas!E12) * (Atividades!$O$2:$O$598=Metas!L12), Atividades!$J$2:$J$598 )} -> 1 | H12: 45658 | I12: 46022 | J12: =I12-H12 -> 364 | K12: =IFERROR(INDEX(Tabela3[ID_Responsavel], MATCH(L12,Tabela3[[Responsáveis ]], 0)), "Não encontrado") -> 20 | L12: Nadrielle | M12: SVPM | O12: Sim
A13: =IFERROR(INDEX(Tabela2[ID_Area], MATCH(B13,Tabela2[Area], 0)), "Não encontrado") -> 1004 | B13: Licenciamento & Regulatório | C13: Gestão de Custo | D13: =ROW(D13) +98 -> 111 | E13: Propor revisão de contratos vigentes buscando reduzir custos | F13: =IF(G13=1,"Concluído", IF(TODAY()>I13,"Atrasado", IF(AND(G13=0,TODAY()<I13),"Não iniciado", "Em Andamento"))) -> Atrasado | G13: {=SUMPRODUCT( (Atividades!$E$2:$E$598=Metas!E13) * (Atividades!$O$2:$O$598=Metas!L13), Atividades!$I$2:$I$598, Atividades!$J$2:$J$598 ) / SUMPRODUCT( (Atividades!$E$2:$E$598=Metas!E13) * (Atividades!$O$2:$O$598=Metas!L13), Atividades!$J$2:$J$598 )} -> 0.3105042 | H13: 45663 | I13: 45991 | J13: =I13-H13 -> 328 | K13: =IFERROR(INDEX(Tabela3[ID_Responsavel], MATCH(L13,Tabela3[[Responsáveis ]], 0)), "Não encontrado") -> 20 | L13: Nadrielle | M13: SVPM | O13: Não
A14: =IFERROR(INDEX(Tabela2[ID_Area], MATCH(B14,Tabela2[Area], 0)), "Não encontrado") -> 1004 | B14: Licenciamento & Regulatório | C14: Publicações científicas | D14: =ROW(D14) +98 -> 112 | E14: Desenvolver Masterplan de Licenciamento Ambiental da SVPM_Nadrielle | F14: =IF(G14=1,"Concluído", IF(TODAY()>I14,"Atrasado", IF(AND(G14=0,TODAY()<I14),"Não iniciado", "Em Andamento"))) -> Concluído | G14: {=SUMPRODUCT( (Atividades!$E$2:$E$598=Metas!E14) * (Atividades!$O$2:$O$598=Metas!L14), Atividades!$I$2:$I$598, Atividades!$J$2:$J$598 ) / SUMPRODUCT( (Atividades!$E$2:$E$598=Metas!E14) * (Atividades!$O$2:$O$598=Metas!L14), Atividades!$J$2:$J$598 )} -> 1 | H14: 45663 | I14: 45960 | J14: =I14-H14 -> 297 | K14: =IFERROR(INDEX(Tabela3[ID_Responsavel], MATCH(L14,Tabela3[[Responsáveis ]], 0)), "Não encontrado") -> 20 | L14: Nadrielle | M14: SVPM | O14: Sim
A15: =IFERROR(INDEX(Tabela2[ID_Area], MATCH(B15,Tabela2[Area], 0)), "Não encontrado") -> 1004 | B15: Licenciamento & Regulatório | C15: SGA | D15: =ROW(D15) +98 -> 113 | E15: Estruturar BASE de DADOS geoespaciais (GMA)_Nadrielle | F15: =IF(G15=1,"Concluído", IF(TODAY()>I15,"Atrasado", IF(AND(G15=0,TODAY()<I15),"Não iniciado", "Em Andamento"))) -> Concluído | G15: {=SUMPRODUCT( (Atividades!$E$2:$E$598=Metas!E15) * (Atividades!$O$2:$O$598=Metas!L15), Atividades!$I$2:$I$598, Atividades!$J$2:$J$598 ) / SUMPRODUCT( (Atividades!$E$2:$E$598=Metas!E15) * (Atividades!$O$2:$O$598=Metas!L15), Atividades!$J$2:$J$598 )} -> 1 | H15: 45717 | I15: 45960 | J15: =I15-H15 -> 243 | K15: =IFERROR(INDEX(Tabela3[ID_Responsavel], MATCH(L15,Tabela3[[Responsáveis ]], 0)), "Não encontrado") -> 20 | L15: Nadrielle | M15: SVPM | O15: Sim
A16: =IFERROR(INDEX(Tabela2[ID_Area], MATCH(B16,Tabela2[Area], 0)), "Não encontrado") -> 1004 | B16: Licenciamento & Regulatório | C16: Licenciamento | D16: =ROW(D16) +98 -> 114 | E16: Atender a Lei SNUC/SEUC e Lei de FAUNA dentro dos prazos estabelecidos pelos órgãos reguladores_Nadrielle | F16: =IF(G16=1,"Concluído", IF(TODAY()>I16,"Atrasado", IF(AND(G16=0,TODAY()<I16),"Não iniciado", "Em Andamento"))) -> Atrasado | G16: {=SUMPRODUCT( (Atividades!$E$2:$E$598=Metas!E16) * (Atividades!$O$2:$O$598=Metas!L16), Atividades!$I$2:$I$598, Atividades!$J$2:$J$598 ) / SUMPRODUCT( (Atividades!$E$2:$E$598=Metas!E16) * (Atividades!$O$2:$O$598=Metas!L16), Atividades!$J$2:$J$598 )} -> 0.96842828 | H16: 45658 | I16: 46008 | J16: =I16-H16 -> 350 | K16: =IFERROR(INDEX(Tabela3[ID_Responsavel], MATCH(L16,Tabela3[[Responsáveis ]], 0)), "Não encontrado") -> 20 | L16: Nadrielle | M16: SVPM | O16: Sim
A17: =IFERROR(INDEX(Tabela2[ID_Area], MATCH(B17,Tabela2[Area], 0)), "Não encontrado") -> 1004 | B17: Licenciamento & Regulatório | C17: Regulatório | D17: =ROW(D17) +98 -> 115 | E17: Estruturação da BASE DE DADOS e plano de atendimento aos itens regulatórios Fundiários, Minerários e Passivos Ambientais das propriedades_Nadrielle | F17: =IF(G17=1,"Concluído", IF(TODAY()>I17,"Atrasado", IF(AND(G17=0,TODAY()<I17),"Não iniciado", "Em Andamento"))) -> Concluído | G17: {=SUMPRODUCT( (Atividades!$E$2:$E$598=Metas!E17) * (Atividades!$O$2:$O$598=Metas!L17), Atividades!$I$2:$I$598, Atividades!$J$2:$J$598 ) / SUMPRODUCT( (Atividades!$E$2:$E$598=Metas!E17) * (Atividades!$O$2:$O$598=Metas!L17), Atividades!$J$2:$J$598 )} -> 1 | H17: 45748 | I17: 45991 | J17: =I17-H17 -> 243 | K17: =IFERROR(INDEX(Tabela3[ID_Responsavel], MATCH(L17,Tabela3[[Responsáveis ]], 0)), "Não encontrado") -> 20 | L17: Nadrielle | M17: SVPM | O17: Sim
A18: =IFERROR(INDEX(Tabela2[ID_Area], MATCH(B18,Tabela2[Area], 0)), "Não encontrado") -> 1004 | B18: Licenciamento & Regulatório | C18: SGA | D18: =ROW(D18) +98 -> 116 | E18: Elaborar Procedimento de Aspectos e Impactos Ambientais e Executar Piloto em 01 Área | F18: =IF(G18=1,"Concluído", IF(TODAY()>I18,"Atrasado", IF(AND(G18=0,TODAY()<I18),"Não iniciado", "Em Andamento"))) -> Atrasado | G18: {=SUMPRODUCT( (Atividades!$E$2:$E$598=Metas!E18) * (Atividades!$O$2:$O$598=Metas!L18), Atividades!$I$2:$I$598, Atividades!$J$2:$J$598 ) / SUMPRODUCT( (Atividades!$E$2:$E$598=Metas!E18) * (Atividades!$O$2:$O$598=Metas!L18), Atividades!$J$2:$J$598 )} -> 0.1744186 | H18: 45931 | I18: 46013 | J18: =I18-H18 -> 82 | K18: =IFERROR(INDEX(Tabela3[ID_Responsavel], MATCH(L18,Tabela3[[Responsáveis ]], 0)), "Não encontrado") -> 24 | L18: Thayna | M18: BIOTA | N18: Continuidade em 2026 | O18: Não
A19: =IFERROR(INDEX(Tabela2[ID_Area], MATCH(B19,Tabela2[Area], 0)), "Não encontrado") -> 1004 | B19: Licenciamento & Regulatório | C19: SGA | D19: =ROW(D19) +98 -> 117 | E19: Executar e consolidar sistemática de atualização e consolidação das informações para elaboração RDA 2026/2025_Thayna | F19: =IF(G19=1,"Concluído", IF(TODAY()>I19,"Atrasado", IF(AND(G19=0,TODAY()<I19),"Não iniciado", "Em Andamento"))) -> Concluído | G19: {=SUMPRODUCT( (Atividades!$E$2:$E$598=Metas!E19) * (Atividades!$O$2:$O$598=Metas!L19), Atividades!$I$2:$I$598, Atividades!$J$2:$J$598 ) / SUMPRODUCT( (Atividades!$E$2:$E$598=Metas!E19) * (Atividades!$O$2:$O$598=Metas!L19), Atividades!$J$2:$J$598 )} -> 1 | H19: 45748 | I19: 46013 | J19: =I19-H19 -> 265 | K19: =IFERROR(INDEX(Tabela3[ID_Responsavel], MATCH(L19,Tabela3[[Responsáveis ]], 0)), "Não encontrado") -> 24 | L19: Thayna | M19: BIOTA | O19: Sim
A20: =IFERROR(INDEX(Tabela2[ID_Area], MATCH(B20,Tabela2[Area], 0)), "Não encontrado") -> 1004 | B20: Licenciamento & Regulatório | C20: Regulatório | D20: =ROW(D20) +98 -> 118 | E20: Estruturação da BASE DE DADOS e plano de atendimento aos itens regulatórios Fundiários, Minerários e Passivos Ambientais das propriedades_Thayna | F20: =IF(G20=1,"Concluído", IF(TODAY()>I20,"Atrasado", IF(AND(G20=0,TODAY()<I20),"Não iniciado", "Em Andamento"))) -> Concluído | G20: {=SUMPRODUCT( (Atividades!$E$2:$E$598=Metas!E20) * (Atividades!$O$2:$O$598=Metas!L20), Atividades!$I$2:$I$598, Atividades!$J$2:$J$598 ) / SUMPRODUCT( (Atividades!$E$2:$E$598=Metas!E20) * (Atividades!$O$2:$O$598=Metas!L20), Atividades!$J$2:$J$598 )} -> 1 | H20: 45748 | I20: 45991 | J20: =I20-H20 -> 243 | K20: =IFERROR(INDEX(Tabela3[ID_Responsavel], MATCH(L20,Tabela3[[Responsáveis ]], 0)), "Não encontrado") -> 24 | L20: Thayna | M20: BIOTA | O20: Sim
A21: =IFERROR(INDEX(Tabela2[ID_Area], MATCH(B21,Tabela2[Area], 0)), "Não encontrado") -> 1004 | B21: Licenciamento & Regulatório | C21: Licenciamento | D21: =ROW(D21) +98 -> 119 | E21: Diligenciar no acompanhamento das solicitações de exclusões de condicionantes | F21: =IF(G21=1,"Concluído", IF(TODAY()>I21,"Atrasado", IF(AND(G21=0,TODAY()<I21),"Não iniciado", "Em Andamento"))) -> Concluído | G21: {=SUMPRODUCT( (Atividades!$E$2:$E$598=Metas!E21) * (Atividades!$O$2:$O$598=Metas!L21), Atividades!$I$2:$I$598, Atividades!$J$2:$J$598 ) / SUMPRODUCT( (Atividades!$E$2:$E$598=Metas!E21) * (Atividades!$O$2:$O$598=Metas!L21), Atividades!$J$2:$J$598 )} -> 1 | H21: 45670 | I21: 45716 | J21: =I21-H21 -> 46 | K21: =IFERROR(INDEX(Tabela3[ID_Responsavel], MATCH(L21,Tabela3[[Responsáveis ]], 0)), "Não encontrado") -> 24 | L21: Thayna | M21: BIOTA
A22: =IFERROR(INDEX(Tabela2[ID_Area], MATCH(B22,Tabela2[Area], 0)), "Não encontrado") -> 1004 | B22: Licenciamento & Regulatório | C22: SGA | D22: =ROW(D22) +98 -> 120 | E22: Desenvolver Manual do SGA | F22: =IF(G22=1,"Concluído", IF(TODAY()>I22,"Atrasado", IF(AND(G22=0,TODAY()<I22),"Não iniciado", "Em Andamento"))) -> Atrasado | G22: {=SUMPRODUCT( (Atividades!$E$2:$E$598=Metas!E22) * (Atividades!$O$2:$O$598=Metas!L22), Atividades!$I$2:$I$598, Atividades!$J$2:$J$598 ) / SUMPRODUCT( (Atividades!$E$2:$E$598=Metas!E22) * (Atividades!$O$2:$O$598=Metas!L22), Atividades!$J$2:$J$598 )} -> 0.525 | H22: 45748 | I22: 45961 | J22: =I22-H22 -> 213 | K22: =IFERROR(INDEX(Tabela3[ID_Responsavel], MATCH(L22,Tabela3[[Responsáveis ]], 0)), "Não encontrado") -> 24 | L22: Thayna | M22: BIOTA | N22: Continuidade em 2026 | O22: Não
A23: =IFERROR(INDEX(Tabela2[ID_Area], MATCH(B23,Tabela2[Area], 0)), "Não encontrado") -> 1000 | B23: Meio Ambiente - Gerencial | C23: P&D | D23: =ROW(D23) +98 -> 121 | E23: SULFATO DE AMÔNIO - Continuidade dos Estudos de Avaliação de Impactos e Ganhos Potenciais com inclusão do reagente S.A. | F23: =IF(G23=1,"Concluído", IF(TODAY()>I23,"Atrasado", IF(AND(G23=0,TODAY()<I23),"Não iniciado", "Em Andamento"))) -> Concluído | G23: {=SUMPRODUCT( (Atividades!$E$2:$E$598=Metas!E23) * (Atividades!$O$2:$O$598=Metas!L23), Atividades!$I$2:$I$598, Atividades!$J$2:$J$598 ) / SUMPRODUCT( (Atividades!$E$2:$E$598=Metas!E23) * (Atividades!$O$2:$O$598=Metas!L23), Atividades!$J$2:$J$598 )} -> 1 | H23: =Atividades!K38 -> 45658 | I23: 46376 | J23: =I23-H23 -> 718 | K23: =IFERROR(INDEX(Tabela3[ID_Responsavel], MATCH(L23,Tabela3[[Responsáveis ]], 0)), "Não encontrado") -> 7 | L23: Edimar Dias | M23: SVPM
A24: =IFERROR(INDEX(Tabela2[ID_Area], MATCH(B24,Tabela2[Area], 0)), "Não encontrado") -> 1000 | B24: Meio Ambiente - Gerencial | C24: P&D | D24: =ROW(D24) +98 -> 122 | E24: TRATABILIDADE EFLUENTES E REJEITOS - Continuidade dos Estudos de Tratabilidade de Efluentes (Salinidade ). | F24: =IF(G24=1,"Concluído", IF(TODAY()>I24,"Atrasado", IF(AND(G24=0,TODAY()<I24),"Não iniciado", "Em Andamento"))) -> Concluído | G24: {=SUMPRODUCT( (Atividades!$E$2:$E$598=Metas!E24) * (Atividades!$O$2:$O$598=Metas!L24), Atividades!$I$2:$I$598, Atividades!$J$2:$J$598 ) / SUMPRODUCT( (Atividades!$E$2:$E$598=Metas!E24) * (Atividades!$O$2:$O$598=Metas!L24), Atividades!$J$2:$J$598 )} -> 1 | H24: =Atividades!K45 -> 45658 | I24: 46091 | J24: =I24-H24 -> 433 | K24: =IFERROR(INDEX(Tabela3[ID_Responsavel], MATCH(L24,Tabela3[[Responsáveis ]], 0)), "Não encontrado") -> 7 | L24: Edimar Dias | M24: SVPM
A25: =IFERROR(INDEX(Tabela2[ID_Area], MATCH(B25,Tabela2[Area], 0)), "Não encontrado") -> 1000 | B25: Meio Ambiente - Gerencial | C25: Regulatório | D25: =ROW(D25) +98 -> 123 | E25: REGULARIZAÇÃO CAR - Atualização das informações e adequação das bases das propriedades inseridas na ADA SVPM conforme prioridade e disponibilidade de recurso. | F25: =IF(G25=1,"Concluído", IF(TODAY()>I25,"Atrasado", IF(AND(G25=0,TODAY()<I25),"Não iniciado", "Em Andamento"))) -> Concluído | G25: {=SUMPRODUCT( (Atividades!$E$2:$E$598=Metas!E25) * (Atividades!$O$2:$O$598=Metas!L25), Atividades!$I$2:$I$598, Atividades!$J$2:$J$598 ) / SUMPRODUCT( (Atividades!$E$2:$E$598=Metas!E25) * (Atividades!$O$2:$O$598=Metas!L25), Atividades!$J$2:$J$598 )} -> 1 | H25: 45847 | I25: 45969 | J25: =I25-H25 -> 122 | K25: =IFERROR(INDEX(Tabela3[ID_Responsavel], MATCH(L25,Tabela3[[Responsáveis ]], 0)), "Não encontrado") -> 7 | L25: Edimar Dias | M25: SESI
A26: =IFERROR(INDEX(Tabela2[ID_Area], MATCH(B26,Tabela2[Area], 0)), "Não encontrado") -> 1000 | B26: Meio Ambiente - Gerencial | C26: SGA | D26: =ROW(D26) +98 -> 124 | E26: Desenvolver e Implementar do Indice de Maturidade e regras socioambientais | F26: =IF(G26=1,"Concluído", IF(TODAY()>I26,"Atrasado", IF(AND(G26=0,TODAY()<I26),"Não iniciado", "Em Andamento"))) -> Concluído | G26: {=SUMPRODUCT( (Atividades!$E$2:$E$598=Metas!E26) * (Atividades!$O$2:$O$598=Metas!L26), Atividades!$I$2:$I$598, Atividades!$J$2:$J$598 ) / SUMPRODUCT( (Atividades!$E$2:$E$598=Metas!E26) * (Atividades!$O$2:$O$598=Metas!L26), Atividades!$J$2:$J$598 )} -> 1 | H26: =Atividades!K16 -> 45674 | I26: 45989 | J26: =I26-H26 -> 315 | K26: =IFERROR(INDEX(Tabela3[ID_Responsavel], MATCH(L26,Tabela3[[Responsáveis ]], 0)), "Não encontrado") -> 7 | L26: Edimar Dias | M26: SESI
A27: =IFERROR(INDEX(Tabela2[ID_Area], MATCH(B27,Tabela2[Area], 0)), "Não encontrado") -> 1000 | B27: Meio Ambiente - Gerencial | C27: Regulatório | D27: =ROW(D27) +98 -> 125 | E27: Atualizar base de APP (Vereda, Nascente e cursos hídricos) das propriedades. | F27: =IF(G27=1,"Concluído", IF(TODAY()>I27,"Atrasado", IF(AND(G27=0,TODAY()<I27),"Não iniciado", "Em Andamento"))) -> Concluído | G27: {=SUMPRODUCT( (Atividades!$E$2:$E$598=Metas!E27) * (Atividades!$O$2:$O$598=Metas!L27), Atividades!$I$2:$I$598, Atividades!$J$2:$J$598 ) / SUMPRODUCT( (Atividades!$E$2:$E$598=Metas!E27) * (Atividades!$O$2:$O$598=Metas!L27), Atividades!$J$2:$J$598 )} -> 1 | H27: =Atividades!K2 -> 45660 | I27: 45989 | J27: =I27-H27 -> 329 | K27: =IFERROR(INDEX(Tabela3[ID_Responsavel], MATCH(L27,Tabela3[[Responsáveis ]], 0)), "Não encontrado") -> 7 | L27: Edimar Dias | M27: SESI
A28: =IFERROR(INDEX(Tabela2[ID_Area], MATCH(B28,Tabela2[Area], 0)), "Não encontrado") -> 1000 | B28: Meio Ambiente - Gerencial | C28: Projeto | D28: =ROW(D28) +98 -> 126 | E28: Rehabilitation Projects Phase II | F28: =IF(G28=1,"Concluído", IF(TODAY()>I28,"Atrasado", IF(AND(G28=0,TODAY()<I28),"Não iniciado", "Em Andamento"))) -> Concluído | G28: {=SUMPRODUCT( (Atividades!$E$2:$E$598=Metas!E28) * (Atividades!$O$2:$O$598=Metas!L28), Atividades!$I$2:$I$598, Atividades!$J$2:$J$598 ) / SUMPRODUCT( (Atividades!$E$2:$E$598=Metas!E28) * (Atividades!$O$2:$O$598=Metas!L28), Atividades!$J$2:$J$598 )} -> 1 | H28: 45663 | I28: 46010 | J28: =I28-H28 -> 347 | K28: =IFERROR(INDEX(Tabela3[ID_Responsavel], MATCH(L28,Tabela3[[Responsáveis ]], 0)), "Não encontrado") -> 7 | L28: Edimar Dias | M28: SESI
A29: =IFERROR(INDEX(Tabela2[ID_Area], MATCH(B29,Tabela2[Area], 0)), "Não encontrado") -> 1000 | B29: Meio Ambiente - Gerencial | C29: Projeto | D29: =ROW(D29) +98 -> 127 | E29: Elaborar Book ambiental dos projetos Flow Sheat | F29: =IF(G29=1,"Concluído", IF(TODAY()>I29,"Atrasado", IF(AND(G29=0,TODAY()<I29),"Não iniciado", "Em Andamento"))) -> Atrasado | G29: {=SUMPRODUCT( (Atividades!$E$2:$E$598=Metas!E29) * (Atividades!$O$2:$O$598=Metas!L29), Atividades!$I$2:$I$598, Atividades!$J$2:$J$598 ) / SUMPRODUCT( (Atividades!$E$2:$E$598=Metas!E29) * (Atividades!$O$2:$O$598=Metas!L29), Atividades!$J$2:$J$598 )} -> 0.0045072273 | H29: 45677 | I29: 46010 | J29: =I29-H29 -> 333 | K29: =IFERROR(INDEX(Tabela3[ID_Responsavel], MATCH(L29,Tabela3[[Responsáveis ]], 0)), "Não encontrado") -> 7 | L29: Edimar Dias | M29: SESI
A30: =IFERROR(INDEX(Tabela2[ID_Area], MATCH(B30,Tabela2[Area], 0)), "Não encontrado") -> 1000 | B30: Meio Ambiente - Gerencial | C30: Projeto | D30: =ROW(D30) +98 -> 128 | E30: Elaborar Book ambiental do Heap Laeth | F30: =IF(G30=1,"Concluído", IF(TODAY()>I30,"Atrasado", IF(AND(G30=0,TODAY()<I30),"Não iniciado", "Em Andamento"))) -> Atrasado | G30: {=SUMPRODUCT( (Atividades!$E$2:$E$598=Metas!E30) * (Atividades!$O$2:$O$598=Metas!L30), Atividades!$I$2:$I$598, Atividades!$J$2:$J$598 ) / SUMPRODUCT( (Atividades!$E$2:$E$598=Metas!E30) * (Atividades!$O$2:$O$598=Metas!L30), Atividades!$J$2:$J$598 )} -> 0.68946648 | H30: 45677 | I30: 46010 | J30: =I30-H30 -> 333 | K30: =IFERROR(INDEX(Tabela3[ID_Responsavel], MATCH(L30,Tabela3[[Responsáveis ]], 0)), "Não encontrado") -> 7 | L30: Edimar Dias | M30: SESI
A31: =IFERROR(INDEX(Tabela2[ID_Area], MATCH(B31,Tabela2[Area], 0)), "Não encontrado") -> 1001 | B31: Meio Ambiente - Operação | C31: Planos Diretores | D31: =ROW(D31) +98 -> 129 | E31: Elaborar o Plano Diretor de PRAD do empreendimento, estabelecendo diretrizes e ações para o gerenciamento de águas superficiais, controle de processos erosivos, aplicação de técnicas de bioengenharia e revegetação de taludes nas áreas da SVPM. | F31: =IF(G31=1,"Concluído", IF(TODAY()>I31,"Atrasado", IF(AND(G31=0,TODAY()<I31),"Não iniciado", "Em Andamento"))) -> Atrasado | G31: {=SUMPRODUCT( (Atividades!$E$2:$E$598=Metas!E31) * (Atividades!$O$2:$O$598=Metas!L31), Atividades!$I$2:$I$598, Atividades!$J$2:$J$598 ) / SUMPRODUCT( (Atividades!$E$2:$E$598=Metas!E31) * (Atividades!$O$2:$O$598=Metas!L31), Atividades!$J$2:$J$598 )} -> 0.93043478 | H31: 45659 | I31: 46022 | J31: =I31-H31 -> 363 | K31: =IFERROR(INDEX(Tabela3[ID_Responsavel], MATCH(L31,Tabela3[[Responsáveis ]], 0)), "Não encontrado") -> 1 | L31: Alan Boni | M31: SVPM | N31: Alinhado com a Gerencia que a meta será concluída no início de 2026 com a realização do workshop e treinamento das equipes operacionais | O31: Não
A32: =IFERROR(INDEX(Tabela2[ID_Area], MATCH(B32,Tabela2[Area], 0)), "Não encontrado") -> 1001 | B32: Meio Ambiente - Operação | C32: PRAD | D32: =ROW(D32) +98 -> 130 | E32: Desenvolvimento de protocolo de monitoramento para conclusão de áreas de PRAD da Serra Verde | F32: =IF(G32=1,"Concluído", IF(TODAY()>I32,"Atrasado", IF(AND(G32=0,TODAY()<I32),"Não iniciado", "Em Andamento"))) -> Concluído | G32: {=SUMPRODUCT( (Atividades!$E$2:$E$598=Metas!E32) * (Atividades!$O$2:$O$598=Metas!L32), Atividades!$I$2:$I$598, Atividades!$J$2:$J$598 ) / SUMPRODUCT( (Atividades!$E$2:$E$598=Metas!E32) * (Atividades!$O$2:$O$598=Metas!L32), Atividades!$J$2:$J$598 )} -> 1 | H32: 45659 | I32: 45960 | J32: =I32-H32 -> 301 | K32: =IFERROR(INDEX(Tabela3[ID_Responsavel], MATCH(L32,Tabela3[[Responsáveis ]], 0)), "Não encontrado") -> 1 | L32: Alan Boni | M32: SVPM | O32: Sim
A33: =IFERROR(INDEX(Tabela2[ID_Area], MATCH(B33,Tabela2[Area], 0)), "Não encontrado") -> 1001 | B33: Meio Ambiente - Operação | C33: Planos Diretores | D33: =ROW(D33) +98 -> 131 | E33: Elaborar o Plano Diretor de Controles Ambientais do empreendimento | F33: =IF(G33=1,"Concluído", IF(TODAY()>I33,"Atrasado", IF(AND(G33=0,TODAY()<I33),"Não iniciado", "Em Andamento"))) -> Atrasado | G33: {=SUMPRODUCT( (Atividades!$E$2:$E$598=Metas!E33) * (Atividades!$O$2:$O$598=Metas!L33), Atividades!$I$2:$I$598, Atividades!$J$2:$J$598 ) / SUMPRODUCT( (Atividades!$E$2:$E$598=Metas!E33) * (Atividades!$O$2:$O$598=Metas!L33), Atividades!$J$2:$J$598 )} -> 0.82913907 | H33: 45659 | I33: 46003 | J33: =I33-H33 -> 344 | K33: =IFERROR(INDEX(Tabela3[ID_Responsavel], MATCH(L33,Tabela3[[Responsáveis ]], 0)), "Não encontrado") -> 1 | L33: Alan Boni | M33: SVPM | N33: Alinhado com a Gerencia que a meta será concluída no início de 2026 com a realização do workshop e treinamento das equipes operacionais | O33: Não
A34: =IFERROR(INDEX(Tabela2[ID_Area], MATCH(B34,Tabela2[Area], 0)), "Não encontrado") -> 1001 | B34: Meio Ambiente - Operação | C34: SGA | D34: =ROW(D34) +98 -> 132 | E34: Desenvolver e Implementar do Indice de Maturidade e regras socioambientais. | F34: =IF(G34=1,"Concluído", IF(TODAY()>I34,"Atrasado", IF(AND(G34=0,TODAY()<I34),"Não iniciado", "Em Andamento"))) -> Atrasado | G34: {=SUMPRODUCT( (Atividades!$E$2:$E$598=Metas!E34) * (Atividades!$O$2:$O$598=Metas!L34), Atividades!$I$2:$I$598, Atividades!$J$2:$J$598 ) / SUMPRODUCT( (Atividades!$E$2:$E$598=Metas!E34) * (Atividades!$O$2:$O$598=Metas!L34), Atividades!$J$2:$J$598 )} -> 0.39322581 | H34: 45674 | I34: 46022 | J34: =I34-H34 -> 348 | K34: =IFERROR(INDEX(Tabela3[ID_Responsavel], MATCH(L34,Tabela3[[Responsáveis ]], 0)), "Não encontrado") -> 1 | L34: Alan Boni | M34: SVPM | N34: Início em 2026. | O34: Não
A35: =IFERROR(INDEX(Tabela2[ID_Area], MATCH(B35,Tabela2[Area], 0)), "Não encontrado") -> 1001 | B35: Meio Ambiente - Operação | C35: P&D | D35: =ROW(D35) +98 -> 133 | E35: Desenvolvimento de experimentos com técnicas de recuperação de áreas degradadas. | F35: =IF(G35=1,"Concluído", IF(TODAY()>I35,"Atrasado", IF(AND(G35=0,TODAY()<I35),"Não iniciado", "Em Andamento"))) -> Atrasado | G35: {=SUMPRODUCT( (Atividades!$E$2:$E$598=Metas!E35) * (Atividades!$O$2:$O$598=Metas!L35), Atividades!$I$2:$I$598, Atividades!$J$2:$J$598 ) / SUMPRODUCT( (Atividades!$E$2:$E$598=Metas!E35) * (Atividades!$O$2:$O$598=Metas!L35), Atividades!$J$2:$J$598 )} -> 0.15137615 | H35: 45660 | I35: 45960 | J35: =I35-H35 -> 300 | K35: =IFERROR(INDEX(Tabela3[ID_Responsavel], MATCH(L35,Tabela3[[Responsáveis ]], 0)), "Não encontrado") -> 13 | L35: Leovigildo | M35: SESI | N35: A meta é dependente da aquisição dos insumos do PRAD e Bioengenharia. Serão entregues à SVPM somente em janeiro de 2026. | O35: Não
A36: =IFERROR(INDEX(Tabela2[ID_Area], MATCH(B36,Tabela2[Area], 0)), "Não encontrado") -> 1002 | B36: Meio Biótico | C36: PRAD | D36: =ROW(D36) +98 -> 134 | E36: Desenvolver trabalho técnico florestal com base na implantação e resultados iniciais do PRAD Piloto. | F36: =IF(G36=1,"Concluído", IF(TODAY()>I36,"Atrasado", IF(AND(G36=0,TODAY()<I36),"Não iniciado", "Em Andamento"))) -> Concluído | G36: {=SUMPRODUCT( (Atividades!$E$2:$E$598=Metas!E36) * (Atividades!$O$2:$O$598=Metas!L36), Atividades!$I$2:$I$598, Atividades!$J$2:$J$598 ) / SUMPRODUCT( (Atividades!$E$2:$E$598=Metas!E36) * (Atividades!$O$2:$O$598=Metas!L36), Atividades!$J$2:$J$598 )} -> 1 | H36: 45660 | I36: 46021 | J36: =I36-H36 -> 361 | K36: =IFERROR(INDEX(Tabela3[ID_Responsavel], MATCH(L36,Tabela3[[Responsáveis ]], 0)), "Não encontrado") -> 13 | L36: Leovigildo | M36: SESI | N36: Exceto a submissão do trabalho em periódico científico, todas as outras etapas foram finalizadas. No entanto, a submissão depende ainda da aprovação da Relações Institucionais e Responsabilidade Social Responsabilidade Social Corporativa. | O36: Sim
A37: =IFERROR(INDEX(Tabela2[ID_Area], MATCH(B37,Tabela2[Area], 0)), "Não encontrado") -> 1001 | B37: Meio Ambiente - Operação | C37: Planos Diretores | D37: =ROW(D37) +98 -> 135 | E37: De acordo com as premissas do Plano diretor de PRAD, firmar parcerias com instituições de pesquisa / pesquisadores autônomos para estudos aprofundados relacionados a estratégias para recuperação do cerrado. | F37: =IF(G37=1,"Concluído", IF(TODAY()>I37,"Atrasado", IF(AND(G37=0,TODAY()<I37),"Não iniciado", "Em Andamento"))) -> Atrasado | G37: {=SUMPRODUCT( (Atividades!$E$2:$E$598=Metas!E37) * (Atividades!$O$2:$O$598=Metas!L37), Atividades!$I$2:$I$598, Atividades!$J$2:$J$598 ) / SUMPRODUCT( (Atividades!$E$2:$E$598=Metas!E37) * (Atividades!$O$2:$O$598=Metas!L37), Atividades!$J$2:$J$598 )} -> 0.74642127 | H37: 45672 | I37: 45961 | J37: =I37-H37 -> 289 | K37: =IFERROR(INDEX(Tabela3[ID_Responsavel], MATCH(L37,Tabela3[[Responsáveis ]], 0)), "Não encontrado") -> 13 | L37: Leovigildo | M37: SESI | N37: Dependente da aquisição dos insumos de PRAD e Bioengenharia, que só serão entregues à SVPM em janeiro de 2026. | O37: Não
A38: =IFERROR(INDEX(Tabela2[ID_Area], MATCH(B38,Tabela2[Area], 0)), "Não encontrado") -> 1002 | B38: Meio Biótico | C38: P&D | D38: =ROW(D38) +98 -> 136 | E38: Apresentar e testar novas soluções para controle de sedimentos do empreendimento. | F38: =IF(G38=1,"Concluído", IF(TODAY()>I38,"Atrasado", IF(AND(G38=0,TODAY()<I38),"Não iniciado", "Em Andamento"))) -> Atrasado | G38: {=SUMPRODUCT( (Atividades!$E$2:$E$598=Metas!E38) * (Atividades!$O$2:$O$598=Metas!L38), Atividades!$I$2:$I$598, Atividades!$J$2:$J$598 ) / SUMPRODUCT( (Atividades!$E$2:$E$598=Metas!E38) * (Atividades!$O$2:$O$598=Metas!L38), Atividades!$J$2:$J$598 )} -> 0.97839506 | H38: 45731 | I38: 46011 | J38: =I38-H38 -> 280 | K38: =IFERROR(INDEX(Tabela3[ID_Responsavel], MATCH(L38,Tabela3[[Responsáveis ]], 0)), "Não encontrado") -> 13 | L38: Leovigildo | M38: SESI | N38: Impantadas duas soluções reaproveitando lonas de filtragem: 01 para a proteção de taludes e controle de plantas daninhas por solarização no PRAD Piloto; 01 como construção de paliçadas para a retenção de sedimentos na Cava Sul. | O38: Não
A39: =IFERROR(INDEX(Tabela2[ID_Area], MATCH(B39,Tabela2[Area], 0)), "Não encontrado") -> 1001 | B39: Meio Ambiente - Operação | C39: Controle Ambiental | D39: =ROW(D39) +98 -> 137 | E39: Implementar o Plano Diretor de Controles Ambientais (PDCA) do empreendimento. | F39: =IF(G39=1,"Concluído", IF(TODAY()>I39,"Atrasado", IF(AND(G39=0,TODAY()<I39),"Não iniciado", "Em Andamento"))) -> Atrasado | G39: {=SUMPRODUCT( (Atividades!$E$2:$E$598=Metas!E39) * (Atividades!$O$2:$O$598=Metas!L39), Atividades!$I$2:$I$598, Atividades!$J$2:$J$598 ) / SUMPRODUCT( (Atividades!$E$2:$E$598=Metas!E39) * (Atividades!$O$2:$O$598=Metas!L39), Atividades!$J$2:$J$598 )} -> 0.64950166 | H39: 45659 | I39: 46022 | J39: =I39-H39 -> 363 | K39: =IFERROR(INDEX(Tabela3[ID_Responsavel], MATCH(L39,Tabela3[[Responsáveis ]], 0)), "Não encontrado") -> 22 | L39: Pedro Duque | M39: SVPM | N39: Alinhado com a Gerencia que a meta será concluída no início de 2026 com a realização do workshop e treinamento das equipes operacionais | O39: Não
A40: =IFERROR(INDEX(Tabela2[ID_Area], MATCH(B40,Tabela2[Area], 0)), "Não encontrado") -> 1001 | B40: Meio Ambiente - Operação | C40: Controle Ambiental | D40: =ROW(D40) +98 -> 138 | E40: Determinar as principais bacias de drenagem natural da ADA SVPM e suas contribuições pluviais, para determinar a origem dos impactos de turbidez das bacias. | F40: =IF(G40=1,"Concluído", IF(TODAY()>I40,"Atrasado", IF(AND(G40=0,TODAY()<I40),"Não iniciado", "Em Andamento"))) -> Concluído | G40: {=SUMPRODUCT( (Atividades!$E$2:$E$598=Metas!E40) * (Atividades!$O$2:$O$598=Metas!L40), Atividades!$I$2:$I$598, Atividades!$J$2:$J$598 ) / SUMPRODUCT( (Atividades!$E$2:$E$598=Metas!E40) * (Atividades!$O$2:$O$598=Metas!L40), Atividades!$J$2:$J$598 )} -> 1 | H40: 45659 | I40: 46022 | J40: =I40-H40 -> 363 | K40: =IFERROR(INDEX(Tabela3[ID_Responsavel], MATCH(L40,Tabela3[[Responsáveis ]], 0)), "Não encontrado") -> 22 | L40: Pedro Duque | M40: SVPM | O40: Sim
A41: =IFERROR(INDEX(Tabela2[ID_Area], MATCH(B41,Tabela2[Area], 0)), "Não encontrado") -> 1001 | B41: Meio Ambiente - Operação | C41: P&D | D41: =ROW(D41) +98 -> 139 | E41: Apresentar e testar novas soluções para proteção de taludes a erosão | F41: =IF(G41=1,"Concluído", IF(TODAY()>I41,"Atrasado", IF(AND(G41=0,TODAY()<I41),"Não iniciado", "Em Andamento"))) -> Concluído | G41: {=SUMPRODUCT( (Atividades!$E$2:$E$598=Metas!E41) * (Atividades!$O$2:$O$598=Metas!L41), Atividades!$I$2:$I$598, Atividades!$J$2:$J$598 ) / SUMPRODUCT( (Atividades!$E$2:$E$598=Metas!E41) * (Atividades!$O$2:$O$598=Metas!L41), Atividades!$J$2:$J$598 )} -> 1 | H41: 45659 | I41: 46021 | J41: =I41-H41 -> 362 | K41: =IFERROR(INDEX(Tabela3[ID_Responsavel], MATCH(L41,Tabela3[[Responsáveis ]], 0)), "Não encontrado") -> 22 | L41: Pedro Duque | M41: SVPM | O41: Sim
A42: =IFERROR(INDEX(Tabela2[ID_Area], MATCH(B42,Tabela2[Area], 0)), "Não encontrado") -> 1001 | B42: Meio Ambiente - Operação | C42: P&D | D42: =ROW(D42) +98 -> 140 | E42: Propor nova metodologia para controle de material particulado em vias não pavimentadas | F42: =IF(G42=1,"Concluído", IF(TODAY()>I42,"Atrasado", IF(AND(G42=0,TODAY()<I42),"Não iniciado", "Em Andamento"))) -> Concluído | G42: {=SUMPRODUCT( (Atividades!$E$2:$E$598=Metas!E42) * (Atividades!$O$2:$O$598=Metas!L42), Atividades!$I$2:$I$598, Atividades!$J$2:$J$598 ) / SUMPRODUCT( (Atividades!$E$2:$E$598=Metas!E42) * (Atividades!$O$2:$O$598=Metas!L42), Atividades!$J$2:$J$598 )} -> 1 | H42: 45839 | I42: 46021 | J42: =I42-H42 -> 182 | K42: =IFERROR(INDEX(Tabela3[ID_Responsavel], MATCH(L42,Tabela3[[Responsáveis ]], 0)), "Não encontrado") -> 22 | L42: Pedro Duque | M42: SVPM | O42: Sim
A43: =IFERROR(INDEX(Tabela2[ID_Area], MATCH(B43,Tabela2[Area], 0)), "Não encontrado") -> 1003 | B43: Meio Físico | C43: SGA | D43: =ROW(D43) +98 -> 141 | E43: Revisão dos documentos PGRS / PGRSS / PGRCCD | F43: =IF(G43=1,"Concluído", IF(TODAY()>I43,"Atrasado", IF(AND(G43=0,TODAY()<I43),"Não iniciado", "Em Andamento"))) -> Concluído | G43: {=SUMPRODUCT( (Atividades!$E$2:$E$598=Metas!E43) * (Atividades!$O$2:$O$598=Metas!L43), Atividades!$I$2:$I$598, Atividades!$J$2:$J$598 ) / SUMPRODUCT( (Atividades!$E$2:$E$598=Metas!E43) * (Atividades!$O$2:$O$598=Metas!L43), Atividades!$J$2:$J$598 )} -> 1 | H43: 45659 | I43: 45994 | J43: =I43-H43 -> 335 | K43: =IFERROR(INDEX(Tabela3[ID_Responsavel], MATCH(L43,Tabela3[[Responsáveis ]], 0)), "Não encontrado") -> 8 | L43: Geovanna Freitas | M43: SVPM
A44: =IFERROR(INDEX(Tabela2[ID_Area], MATCH(B44,Tabela2[Area], 0)), "Não encontrado") -> 1003 | B44: Meio Físico | C44: SGA | D44: =ROW(D44) +98 -> 142 | E44: Implementação PGRS / PGRSS / PGRCCD | F44: =IF(G44=1,"Concluído", IF(TODAY()>I44,"Atrasado", IF(AND(G44=0,TODAY()<I44),"Não iniciado", "Em Andamento"))) -> Concluído | G44: {=SUMPRODUCT( (Atividades!$E$2:$E$598=Metas!E44) * (Atividades!$O$2:$O$598=Metas!L44), Atividades!$I$2:$I$598, Atividades!$J$2:$J$598 ) / SUMPRODUCT( (Atividades!$E$2:$E$598=Metas!E44) * (Atividades!$O$2:$O$598=Metas!L44), Atividades!$J$2:$J$598 )} -> 1 | H44: 45659 | I44: 46021 | J44: =I44-H44 -> 362 | K44: =IFERROR(INDEX(Tabela3[ID_Responsavel], MATCH(L44,Tabela3[[Responsáveis ]], 0)), "Não encontrado") -> 8 | L44: Geovanna Freitas | M44: SVPM
A45: =IFERROR(INDEX(Tabela2[ID_Area], MATCH(B45,Tabela2[Area], 0)), "Não encontrado") -> 1003 | B45: Meio Físico | C45: SGA | D45: =ROW(D45) +98 -> 143 | E45: Implementação Programa de Gerenciamento de Resíduos Sólidos | F45: =IF(G45=1,"Concluído", IF(TODAY()>I45,"Atrasado", IF(AND(G45=0,TODAY()<I45),"Não iniciado", "Em Andamento"))) -> Concluído | G45: {=SUMPRODUCT( (Atividades!$E$2:$E$598=Metas!E45) * (Atividades!$O$2:$O$598=Metas!L45), Atividades!$I$2:$I$598, Atividades!$J$2:$J$598 ) / SUMPRODUCT( (Atividades!$E$2:$E$598=Metas!E45) * (Atividades!$O$2:$O$598=Metas!L45), Atividades!$J$2:$J$598 )} -> 1 | H45: 45677 | I45: 46021 | J45: =I45-H45 -> 344 | K45: =IFERROR(INDEX(Tabela3[ID_Responsavel], MATCH(L45,Tabela3[[Responsáveis ]], 0)), "Não encontrado") -> 8 | L45: Geovanna Freitas | M45: SVPM
A46: =IFERROR(INDEX(Tabela2[ID_Area], MATCH(B46,Tabela2[Area], 0)), "Não encontrado") -> 1003 | B46: Meio Físico | C46: SGA | D46: =ROW(D46) +98 -> 144 | E46: GAP Analysis para Adequação do atendimento à NBR 10.004 | F46: =IF(G46=1,"Concluído", IF(TODAY()>I46,"Atrasado", IF(AND(G46=0,TODAY()<I46),"Não iniciado", "Em Andamento"))) -> Concluído | G46: {=SUMPRODUCT( (Atividades!$E$2:$E$598=Metas!E46) * (Atividades!$O$2:$O$598=Metas!L46), Atividades!$I$2:$I$598, Atividades!$J$2:$J$598 ) / SUMPRODUCT( (Atividades!$E$2:$E$598=Metas!E46) * (Atividades!$O$2:$O$598=Metas!L46), Atividades!$J$2:$J$598 )} -> 1 | H46: 45700 | I46: 46021 | J46: =I46-H46 -> 321 | K46: =IFERROR(INDEX(Tabela3[ID_Responsavel], MATCH(L46,Tabela3[[Responsáveis ]], 0)), "Não encontrado") -> 8 | L46: Geovanna Freitas | M46: SVPM
A47: =IFERROR(INDEX(Tabela2[ID_Area], MATCH(B47,Tabela2[Area], 0)), "Não encontrado") -> 1003 | B47: Meio Físico | C47: SGA | D47: =ROW(D47) +98 -> 145 | E47: Plano Diretor de Resíduos Sólidos | F47: =IF(G47=1,"Concluído", IF(TODAY()>I47,"Atrasado", IF(AND(G47=0,TODAY()<I47),"Não iniciado", "Em Andamento"))) -> Concluído | G47: {=SUMPRODUCT( (Atividades!$E$2:$E$598=Metas!E47) * (Atividades!$O$2:$O$598=Metas!L47), Atividades!$I$2:$I$598, Atividades!$J$2:$J$598 ) / SUMPRODUCT( (Atividades!$E$2:$E$598=Metas!E47) * (Atividades!$O$2:$O$598=Metas!L47), Atividades!$J$2:$J$598 )} -> 1 | H47: 45659 | I47: 46022 | J47: =I47-H47 -> 363 | K47: =IFERROR(INDEX(Tabela3[ID_Responsavel], MATCH(L47,Tabela3[[Responsáveis ]], 0)), "Não encontrado") -> 8 | L47: Geovanna Freitas | M47: SVPM
A48: =IFERROR(INDEX(Tabela2[ID_Area], MATCH(B48,Tabela2[Area], 0)), "Não encontrado") -> 1001 | B48: Meio Ambiente - Operação | C48: Plano de Atendimento a Emergência | D48: =ROW(D48) +98 -> 146 | E48: Revisão do PAE, PGR e PAE Rodoviário integrando atualizando e revisão riscos e atividades do empreendimento. | F48: =IF(G48=1,"Concluído", IF(TODAY()>I48,"Atrasado", IF(AND(G48=0,TODAY()<I48),"Não iniciado", "Em Andamento"))) -> Concluído | G48: {=SUMPRODUCT( (Atividades!$E$2:$E$598=Metas!E48) * (Atividades!$O$2:$O$598=Metas!L48), Atividades!$I$2:$I$598, Atividades!$J$2:$J$598 ) / SUMPRODUCT( (Atividades!$E$2:$E$598=Metas!E48) * (Atividades!$O$2:$O$598=Metas!L48), Atividades!$J$2:$J$598 )} -> 1 | H48: 45663 | I48: 45967 | J48: =I48-H48 -> 304 | K48: =IFERROR(INDEX(Tabela3[ID_Responsavel], MATCH(L48,Tabela3[[Responsáveis ]], 0)), "Não encontrado") -> 26 | L48: Thulio Souza | M48: BIOTA | O48: Sim
A49: =IFERROR(INDEX(Tabela2[ID_Area], MATCH(B49,Tabela2[Area], 0)), "Não encontrado") -> 1001 | B49: Meio Ambiente - Operação | C49: Plano de Atendimento a Emergência | D49: =ROW(D49) +98 -> 147 | E49: Criar Procedimento do PAE e PGR (Unificado Ambiente e Segurança). | F49: =IF(G49=1,"Concluído", IF(TODAY()>I49,"Atrasado", IF(AND(G49=0,TODAY()<I49),"Não iniciado", "Em Andamento"))) -> Concluído | G49: {=SUMPRODUCT( (Atividades!$E$2:$E$598=Metas!E49) * (Atividades!$O$2:$O$598=Metas!L49), Atividades!$I$2:$I$598, Atividades!$J$2:$J$598 ) / SUMPRODUCT( (Atividades!$E$2:$E$598=Metas!E49) * (Atividades!$O$2:$O$598=Metas!L49), Atividades!$J$2:$J$598 )} -> 1 | H49: 45663 | I49: 45967 | J49: =I49-H49 -> 304 | K49: =IFERROR(INDEX(Tabela3[ID_Responsavel], MATCH(L49,Tabela3[[Responsáveis ]], 0)), "Não encontrado") -> 26 | L49: Thulio Souza | M49: BIOTA | O49: Sim
A50: =IFERROR(INDEX(Tabela2[ID_Area], MATCH(B50,Tabela2[Area], 0)), "Não encontrado") -> 1001 | B50: Meio Ambiente - Operação | C50: SGA | D50: =ROW(D50) +98 -> 148 | E50: Aperfeiçoar sistema de gestão ambiental da área de Meio Ambiente Operação. | F50: =IF(G50=1,"Concluído", IF(TODAY()>I50,"Atrasado", IF(AND(G50=0,TODAY()<I50),"Não iniciado", "Em Andamento"))) -> Concluído | G50: {=SUMPRODUCT( (Atividades!$E$2:$E$598=Metas!E50) * (Atividades!$O$2:$O$598=Metas!L50), Atividades!$I$2:$I$598, Atividades!$J$2:$J$598 ) / SUMPRODUCT( (Atividades!$E$2:$E$598=Metas!E50) * (Atividades!$O$2:$O$598=Metas!L50), Atividades!$J$2:$J$598 )} -> 1 | H50: 45658 | I50: 45967 | J50: =I50-H50 -> 309 | K50: =IFERROR(INDEX(Tabela3[ID_Responsavel], MATCH(L50,Tabela3[[Responsáveis ]], 0)), "Não encontrado") -> 26 | L50: Thulio Souza | M50: BIOTA | O50: Sim
A51: =IFERROR(INDEX(Tabela2[ID_Area], MATCH(B51,Tabela2[Area], 0)), "Não encontrado") -> 1001 | B51: Meio Ambiente - Operação | C51: P&D | D51: =ROW(D51) +98 -> 149 | E51: Implementar experimentos com técnicas de recuperação de áreas degradadas. | F51: =IF(G51=1,"Concluído", IF(TODAY()>I51,"Atrasado", IF(AND(G51=0,TODAY()<I51),"Não iniciado", "Em Andamento"))) -> Atrasado | G51: {=SUMPRODUCT( (Atividades!$E$2:$E$598=Metas!E51) * (Atividades!$O$2:$O$598=Metas!L51), Atividades!$I$2:$I$598, Atividades!$J$2:$J$598 ) / SUMPRODUCT( (Atividades!$E$2:$E$598=Metas!E51) * (Atividades!$O$2:$O$598=Metas!L51), Atividades!$J$2:$J$598 )} -> 0.30666667 | H51: 45670 | I51: 45929 | J51: =I51-H51 -> 259 | K51: =IFERROR(INDEX(Tabela3[ID_Responsavel], MATCH(L51,Tabela3[[Responsáveis ]], 0)), "Não encontrado") -> 23 | L51: Ricardo Sobrinho | M51: BIOTA
A52: =IFERROR(INDEX(Tabela2[ID_Area], MATCH(B52,Tabela2[Area], 0)), "Não encontrado") -> 1001 | B52: Meio Ambiente - Operação | C52: P&D | D52: =ROW(D52) +98 -> 150 | E52: Implantar novas soluções para controle de sedimentos do empreendimento. | F52: =IF(G52=1,"Concluído", IF(TODAY()>I52,"Atrasado", IF(AND(G52=0,TODAY()<I52),"Não iniciado", "Em Andamento"))) -> Atrasado | G52: {=SUMPRODUCT( (Atividades!$E$2:$E$598=Metas!E52) * (Atividades!$O$2:$O$598=Metas!L52), Atividades!$I$2:$I$598, Atividades!$J$2:$J$598 ) / SUMPRODUCT( (Atividades!$E$2:$E$598=Metas!E52) * (Atividades!$O$2:$O$598=Metas!L52), Atividades!$J$2:$J$598 )} -> 0.35699374 | H52: 45659 | I52: 46011 | J52: =I52-H52 -> 352 | K52: =IFERROR(INDEX(Tabela3[ID_Responsavel], MATCH(L52,Tabela3[[Responsáveis ]], 0)), "Não encontrado") -> 23 | L52: Ricardo Sobrinho | M52: BIOTA
A53: =IFERROR(INDEX(Tabela2[ID_Area], MATCH(B53,Tabela2[Area], 0)), "Não encontrado") -> 1000 | B53: Meio Ambiente - Gerencial | C53: P&D | D53: =ROW(D53) +98 -> 151 | E53: Apoio no Desenvolvimento e Implementação do Indice de Maturidade e regras socioambientais | F53: =IF(G53=1,"Concluído", IF(TODAY()>I53,"Atrasado", IF(AND(G53=0,TODAY()<I53),"Não iniciado", "Em Andamento"))) -> Atrasado | G53: {=SUMPRODUCT( (Atividades!$E$2:$E$598=Metas!E53) * (Atividades!$O$2:$O$598=Metas!L53), Atividades!$I$2:$I$598, Atividades!$J$2:$J$598 ) / SUMPRODUCT( (Atividades!$E$2:$E$598=Metas!E53) * (Atividades!$O$2:$O$598=Metas!L53), Atividades!$J$2:$J$598 )} -> 0.98041734 | H53: 45670 | I53: 45981 | J53: =I53-H53 -> 311 | K53: =IFERROR(INDEX(Tabela3[ID_Responsavel], MATCH(L53,Tabela3[[Responsáveis ]], 0)), "Não encontrado") -> 14 | L53: Lucas Vilela | M53: SESI
A54: =IFERROR(INDEX(Tabela2[ID_Area], MATCH(B54,Tabela2[Area], 0)), "Não encontrado") -> 1000 | B54: Meio Ambiente - Gerencial | C54: P&D | D54: =ROW(D54) +98 -> 152 | E54: Estruturar sistemas de informações de dados de SGA ambientais e geoespaciais (presente/futuro). | F54: =IF(G54=1,"Concluído", IF(TODAY()>I54,"Atrasado", IF(AND(G54=0,TODAY()<I54),"Não iniciado", "Em Andamento"))) -> Atrasado | G54: {=SUMPRODUCT( (Atividades!$E$2:$E$598=Metas!E54) * (Atividades!$O$2:$O$598=Metas!L54), Atividades!$I$2:$I$598, Atividades!$J$2:$J$598 ) / SUMPRODUCT( (Atividades!$E$2:$E$598=Metas!E54) * (Atividades!$O$2:$O$598=Metas!L54), Atividades!$J$2:$J$598 )} -> 0.60452586 | H54: 45659 | I54: 46011 | J54: =I54-H54 -> 352 | K54: =IFERROR(INDEX(Tabela3[ID_Responsavel], MATCH(L54,Tabela3[[Responsáveis ]], 0)), "Não encontrado") -> 14 | L54: Lucas Vilela | M54: SESI
A55: =IFERROR(INDEX(Tabela2[ID_Area], MATCH(B55,Tabela2[Area], 0)), "Não encontrado") -> 1001 | B55: Meio Ambiente - Operação | C55: P&D | D55: =ROW(D55) +98 -> 153 | E55: Avaliação e mapeamento de impacto de soluções salinas no solo, flora e água | F55: =IF(G55=1,"Concluído", IF(TODAY()>I55,"Atrasado", IF(AND(G55=0,TODAY()<I55),"Não iniciado", "Em Andamento"))) -> Atrasado | G55: {=SUMPRODUCT( (Atividades!$E$2:$E$598=Metas!E55) * (Atividades!$O$2:$O$598=Metas!L55), Atividades!$I$2:$I$598, Atividades!$J$2:$J$598 ) / SUMPRODUCT( (Atividades!$E$2:$E$598=Metas!E55) * (Atividades!$O$2:$O$598=Metas!L55), Atividades!$J$2:$J$598 )} -> 0.96 | H55: 45858 | I55: 46021 | J55: =I55-H55 -> 163 | K55: =IFERROR(INDEX(Tabela3[ID_Responsavel], MATCH(L55,Tabela3[[Responsáveis ]], 0)), "Não encontrado") -> 26 | L55: Thulio Souza | M55: BIOTA | O55: Não
A56: =IFERROR(INDEX(Tabela2[ID_Area], MATCH(B56,Tabela2[Area], 0)), "Não encontrado") -> 1001 | B56: Meio Ambiente - Operação | C56: P&D | D56: =ROW(D56) +98 -> 154 | E56: Implantar soluções técnicas para controles controle da vazamento de óleo na planta e na mina. | F56: =IF(G56=1,"Concluído", IF(TODAY()>I56,"Atrasado", IF(AND(G56=0,TODAY()<I56),"Não iniciado", "Em Andamento"))) -> Concluído | G56: {=SUMPRODUCT( (Atividades!$E$2:$E$598=Metas!E56) * (Atividades!$O$2:$O$598=Metas!L56), Atividades!$I$2:$I$598, Atividades!$J$2:$J$598 ) / SUMPRODUCT( (Atividades!$E$2:$E$598=Metas!E56) * (Atividades!$O$2:$O$598=Metas!L56), Atividades!$J$2:$J$598 )} -> 1 | H56: 45659 | I56: 46021 | J56: =I56-H56 -> 362 | K56: =IFERROR(INDEX(Tabela3[ID_Responsavel], MATCH(L56,Tabela3[[Responsáveis ]], 0)), "Não encontrado") -> 17 | L56: Matheus | M56: BIOTA | O56: Sim
A57: =IFERROR(INDEX(Tabela2[ID_Area], MATCH(B57,Tabela2[Area], 0)), "Não encontrado") -> 1001 | B57: Meio Ambiente - Operação | C57: Controle Ambiental | D57: =ROW(D57) +98 -> 155 | E57: Determinar as principais bacias de drenagem natural da ADA SVPM e suas contribuições pluviais, para determinar a origem dos impactos de turbidez das bacias_Matheus | F57: =IF(G57=1,"Concluído", IF(TODAY()>I57,"Atrasado", IF(AND(G57=0,TODAY()<I57),"Não iniciado", "Em Andamento"))) -> Concluído | G57: {=SUMPRODUCT( (Atividades!$E$2:$E$598=Metas!E57) * (Atividades!$O$2:$O$598=Metas!L57), Atividades!$I$2:$I$598, Atividades!$J$2:$J$598 ) / SUMPRODUCT( (Atividades!$E$2:$E$598=Metas!E57) * (Atividades!$O$2:$O$598=Metas!L57), Atividades!$J$2:$J$598 )} -> 1 | H57: 45659 | I57: 45819 | J57: =I57-H57 -> 160 | K57: =IFERROR(INDEX(Tabela3[ID_Responsavel], MATCH(L57,Tabela3[[Responsáveis ]], 0)), "Não encontrado") -> 17 | L57: Matheus | M57: BIOTA | O57: Sim
A58: =IFERROR(INDEX(Tabela2[ID_Area], MATCH(B58,Tabela2[Area], 0)), "Não encontrado") -> 1001 | B58: Meio Ambiente - Operação | C58: P&D | D58: =ROW(D58) +98 -> 156 | E58: Implantar soluções técnicas para controles controle da vazamento de óleo na planta e na mina.. | F58: =IF(G58=1,"Concluído", IF(TODAY()>I58,"Atrasado", IF(AND(G58=0,TODAY()<I58),"Não iniciado", "Em Andamento"))) -> Atrasado | G58: {=SUMPRODUCT( (Atividades!$E$2:$E$598=Metas!E58) * (Atividades!$O$2:$O$598=Metas!L58), Atividades!$I$2:$I$598, Atividades!$J$2:$J$598 ) / SUMPRODUCT( (Atividades!$E$2:$E$598=Metas!E58) * (Atividades!$O$2:$O$598=Metas!L58), Atividades!$J$2:$J$598 )} -> 0.76138148 | H58: 45659 | I58: 46021 | J58: =I58-H58 -> 362 | K58: =IFERROR(INDEX(Tabela3[ID_Responsavel], MATCH(L58,Tabela3[[Responsáveis ]], 0)), "Não encontrado") -> 10 | L58: Guilherme Monteiro | M58: BIOTA | N58: Aguardando chegada da amostra para teste operacional | O58: Não
A59: =IFERROR(INDEX(Tabela2[ID_Area], MATCH(B59,Tabela2[Area], 0)), "Não encontrado") -> 1001 | B59: Meio Ambiente - Operação | C59: P&D | D59: =ROW(D59) +98 -> 157 | E59: Apresentar e testar novas soluções para proteção de taludes a erosão_GuilhermeMonteiro | F59: =IF(G59=1,"Concluído", IF(TODAY()>I59,"Atrasado", IF(AND(G59=0,TODAY()<I59),"Não iniciado", "Em Andamento"))) -> Concluído | G59: {=SUMPRODUCT( (Atividades!$E$2:$E$598=Metas!E59) * (Atividades!$O$2:$O$598=Metas!L59), Atividades!$I$2:$I$598, Atividades!$J$2:$J$598 ) / SUMPRODUCT( (Atividades!$E$2:$E$598=Metas!E59) * (Atividades!$O$2:$O$598=Metas!L59), Atividades!$J$2:$J$598 )} -> 1 | H59: 45659 | I59: 46021 | J59: =I59-H59 -> 362 | K59: =IFERROR(INDEX(Tabela3[ID_Responsavel], MATCH(L59,Tabela3[[Responsáveis ]], 0)), "Não encontrado") -> 10 | L59: Guilherme Monteiro | M59: BIOTA | O59: Sim
A60: =IFERROR(INDEX(Tabela2[ID_Area], MATCH(B60,Tabela2[Area], 0)), "Não encontrado") -> 1002 | B60: Meio Biótico | C60: P&D | D60: =ROW(D60) +98 -> 158 | E60: Desenvolver plano estratégico de suprimentos sustentável de material genético (mudas, sementes, composto orgânico...) do Cerrado | F60: =IF(G60=1,"Concluído", IF(TODAY()>I60,"Atrasado", IF(AND(G60=0,TODAY()<I60),"Não iniciado", "Em Andamento"))) -> Concluído | G60: {=SUMPRODUCT( (Atividades!$E$2:$E$598=Metas!E60) * (Atividades!$O$2:$O$598=Metas!L60), Atividades!$I$2:$I$598, Atividades!$J$2:$J$598 ) / SUMPRODUCT( (Atividades!$E$2:$E$598=Metas!E60) * (Atividades!$O$2:$O$598=Metas!L60), Atividades!$J$2:$J$598 )} -> 1 | H60: 45660 | I60: 46018 | J60: =I60-H60 -> 358 | K60: =IFERROR(INDEX(Tabela3[ID_Responsavel], MATCH(L60,Tabela3[[Responsáveis ]], 0)), "Não encontrado") -> 13 | L60: Leovigildo | M60: SVPM | N60: Plano de Seleção e Mapeamento de Matrizes Florestais, Plano de Coleta e Beneficiamento de Sementes Florestais, Plano de Estruturação do Viveiro Florestal | O60: Sim
A61: =IFERROR(INDEX(Tabela2[ID_Area], MATCH(B61,Tabela2[Area], 0)), "Não encontrado") -> 1002 | B61: Meio Biótico | C61: Operação | D61: =ROW(D61) +98 -> 159 | E61: Instalar e operar Meliponário SVPM, confeccionando relatório final anual evidenciando os trabalhalhos realizados. | F61: =IF(G61=1,"Concluído", IF(TODAY()>I61,"Atrasado", IF(AND(G61=0,TODAY()<I61),"Não iniciado", "Em Andamento"))) -> Concluído | G61: {=SUMPRODUCT( (Atividades!$E$2:$E$598=Metas!E61) * (Atividades!$O$2:$O$598=Metas!L61), Atividades!$I$2:$I$598, Atividades!$J$2:$J$598 ) / SUMPRODUCT( (Atividades!$E$2:$E$598=Metas!E61) * (Atividades!$O$2:$O$598=Metas!L61), Atividades!$J$2:$J$598 )} -> 1 | H61: 45658 | I61: 46021 | J61: =I61-H61 -> 363 | K61: =IFERROR(INDEX(Tabela3[ID_Responsavel], MATCH(L61,Tabela3[[Responsáveis ]], 0)), "Não encontrado") -> 2 | L61: Allikison | M61: BIOTA | O61: Sim
A62: =IFERROR(INDEX(Tabela2[ID_Area], MATCH(B62,Tabela2[Area], 0)), "Não encontrado") -> 1002 | B62: Meio Biótico | C62: Planos Diretores | D62: =ROW(D62) +98 -> 160 | E62: Desenvolver estudos utilizando DNA Ambiental (eDNA) | F62: =IF(G62=1,"Concluído", IF(TODAY()>I62,"Atrasado", IF(AND(G62=0,TODAY()<I62),"Não iniciado", "Em Andamento"))) -> Concluído | G62: {=SUMPRODUCT( (Atividades!$E$2:$E$598=Metas!E62) * (Atividades!$O$2:$O$598=Metas!L62), Atividades!$I$2:$I$598, Atividades!$J$2:$J$598 ) / SUMPRODUCT( (Atividades!$E$2:$E$598=Metas!E62) * (Atividades!$O$2:$O$598=Metas!L62), Atividades!$J$2:$J$598 )} -> 1 | H62: 45670 | I62: 46021 | J62: =I62-H62 -> 351 | K62: =IFERROR(INDEX(Tabela3[ID_Responsavel], MATCH(L62,Tabela3[[Responsáveis ]], 0)), "Não encontrado") -> 4 | L62: Cyro | M62: BIOTA | O62: Sim
A63: =IFERROR(INDEX(Tabela2[ID_Area], MATCH(B63,Tabela2[Area], 0)), "Não encontrado") -> 1002 | B63: Meio Biótico | C63: Monitoramento Ambiental | D63: =ROW(D63) +98 -> 161 | E63: Desenvolver e implantar metodologias de monitoramento de fauna nas áreas de PRAD. | F63: =IF(G63=1,"Concluído", IF(TODAY()>I63,"Atrasado", IF(AND(G63=0,TODAY()<I63),"Não iniciado", "Em Andamento"))) -> Concluído | G63: {=SUMPRODUCT( (Atividades!$E$2:$E$598=Metas!E63) * (Atividades!$O$2:$O$598=Metas!L63), Atividades!$I$2:$I$598, Atividades!$J$2:$J$598 ) / SUMPRODUCT( (Atividades!$E$2:$E$598=Metas!E63) * (Atividades!$O$2:$O$598=Metas!L63), Atividades!$J$2:$J$598 )} -> 1 | H63: 45660 | I63: 46021 | J63: =I63-H63 -> 361 | K63: =IFERROR(INDEX(Tabela3[ID_Responsavel], MATCH(L63,Tabela3[[Responsáveis ]], 0)), "Não encontrado") -> 4 | L63: Cyro | M63: BIOTA | O63: Sim
A64: =IFERROR(INDEX(Tabela2[ID_Area], MATCH(B64,Tabela2[Area], 0)), "Não encontrado") -> 1002 | B64: Meio Biótico | C64: Monitoramento Ambiental | D64: =ROW(D64) +98 -> 162 | E64: Desenvolver procedimento e implantar metodologias de monitoramento dos impactos do Sal na Fauna local. | F64: =IF(G64=1,"Concluído", IF(TODAY()>I64,"Atrasado", IF(AND(G64=0,TODAY()<I64),"Não iniciado", "Em Andamento"))) -> Concluído | G64: {=SUMPRODUCT( (Atividades!$E$2:$E$598=Metas!E64) * (Atividades!$O$2:$O$598=Metas!L64), Atividades!$I$2:$I$598, Atividades!$J$2:$J$598 ) / SUMPRODUCT( (Atividades!$E$2:$E$598=Metas!E64) * (Atividades!$O$2:$O$598=Metas!L64), Atividades!$J$2:$J$598 )} -> 1 | H64: 45717 | I64: 46021 | J64: =I64-H64 -> 304 | K64: =IFERROR(INDEX(Tabela3[ID_Responsavel], MATCH(L64,Tabela3[[Responsáveis ]], 0)), "Não encontrado") -> 4 | L64: Cyro | M64: BIOTA | O64: Sim
A65: =IFERROR(INDEX(Tabela2[ID_Area], MATCH(B65,Tabela2[Area], 0)), "Não encontrado") -> 1002 | B65: Meio Biótico | C65: Estudos Ambientais | D65: =ROW(D65) +98 -> 163 | E65: Confeccionar acervo de fauna para educação ambiental (coleção própria) | F65: =IF(G65=1,"Concluído", IF(TODAY()>I65,"Atrasado", IF(AND(G65=0,TODAY()<I65),"Não iniciado", "Em Andamento"))) -> Concluído | G65: {=SUMPRODUCT( (Atividades!$E$2:$E$598=Metas!E65) * (Atividades!$O$2:$O$598=Metas!L65), Atividades!$I$2:$I$598, Atividades!$J$2:$J$598 ) / SUMPRODUCT( (Atividades!$E$2:$E$598=Metas!E65) * (Atividades!$O$2:$O$598=Metas!L65), Atividades!$J$2:$J$598 )} -> 1 | H65: 45688 | I65: 45751 | J65: =I65-H65 -> 63 | K65: =IFERROR(INDEX(Tabela3[ID_Responsavel], MATCH(L65,Tabela3[[Responsáveis ]], 0)), "Não encontrado") -> 4 | L65: Cyro | M65: BIOTA | O65: Sim
A66: =IFERROR(INDEX(Tabela2[ID_Area], MATCH(B66,Tabela2[Area], 0)), "Não encontrado") -> 1002 | B66: Meio Biótico | C66: Planos Diretores | D66: =ROW(D66) +98 -> 164 | E66: Firmar parcerias com instituições de pesquisa / pesquisadores autônomos para estudos aprofundados relacionados às espécies da fauna e flora locais. | F66: =IF(G66=1,"Concluído", IF(TODAY()>I66,"Atrasado", IF(AND(G66=0,TODAY()<I66),"Não iniciado", "Em Andamento"))) -> Concluído | G66: {=SUMPRODUCT( (Atividades!$E$2:$E$598=Metas!E66) * (Atividades!$O$2:$O$598=Metas!L66), Atividades!$I$2:$I$598, Atividades!$J$2:$J$598 ) / SUMPRODUCT( (Atividades!$E$2:$E$598=Metas!E66) * (Atividades!$O$2:$O$598=Metas!L66), Atividades!$J$2:$J$598 )} -> 1 | H66: 45670 | I66: 45940 | J66: =I66-H66 -> 270 | K66: =IFERROR(INDEX(Tabela3[ID_Responsavel], MATCH(L66,Tabela3[[Responsáveis ]], 0)), "Não encontrado") -> 6 | L66: Dyse | M66: BIOTA | N66: Foi firmada parceria com o pesquisador Zenilton, da Embrapa, e com um mantenedor de fauna. | O66: Sim
A67: =IFERROR(INDEX(Tabela2[ID_Area], MATCH(B67,Tabela2[Area], 0)), "Não encontrado") -> 1002 | B67: Meio Biótico | C67: Operação | D67: =ROW(D67) +98 -> 165 | E67: Garantir que a taxa de reabilitação e reintrodução dos animais recebidos e tratados com sucesso no CETRAS não fique abaixo de 95%. | F67: =IF(G67=1,"Concluído", IF(TODAY()>I67,"Atrasado", IF(AND(G67=0,TODAY()<I67),"Não iniciado", "Em Andamento"))) -> Concluído | G67: {=SUMPRODUCT( (Atividades!$E$2:$E$598=Metas!E67) * (Atividades!$O$2:$O$598=Metas!L67), Atividades!$I$2:$I$598, Atividades!$J$2:$J$598 ) / SUMPRODUCT( (Atividades!$E$2:$E$598=Metas!E67) * (Atividades!$O$2:$O$598=Metas!L67), Atividades!$J$2:$J$598 )} -> 1 | H67: 45658 | I67: 45998 | J67: =I67-H67 -> 340 | K67: =IFERROR(INDEX(Tabela3[ID_Responsavel], MATCH(L67,Tabela3[[Responsáveis ]], 0)), "Não encontrado") -> 6 | L67: Dyse | M67: BIOTA | N67: É uma meta contínua, já que está correlacionada à entrada de animais no CETRAS. Mesmo assim, considero concluída, pois todos os procedimentos estão sendo seguidos. | O67: Sim
A68: =IFERROR(INDEX(Tabela2[ID_Area], MATCH(B68,Tabela2[Area], 0)), "Não encontrado") -> 1002 | B68: Meio Biótico | C68: Monitoramento Ambiental | D68: =ROW(D68) +98 -> 166 | E68: Desenvolver estudo e executar monitoramento em pontos estratégicos de passagem de fauna | F68: =IF(G68=1,"Concluído", IF(TODAY()>I68,"Atrasado", IF(AND(G68=0,TODAY()<I68),"Não iniciado", "Em Andamento"))) -> Concluído | G68: {=SUMPRODUCT( (Atividades!$E$2:$E$598=Metas!E68) * (Atividades!$O$2:$O$598=Metas!L68), Atividades!$I$2:$I$598, Atividades!$J$2:$J$598 ) / SUMPRODUCT( (Atividades!$E$2:$E$598=Metas!E68) * (Atividades!$O$2:$O$598=Metas!L68), Atividades!$J$2:$J$598 )} -> 1 | H68: 45660 | I68: 46021 | J68: =I68-H68 -> 361 | K68: =IFERROR(INDEX(Tabela3[ID_Responsavel], MATCH(L68,Tabela3[[Responsáveis ]], 0)), "Não encontrado") -> 9 | L68: Gilmar | M68: BIOTA | O68: Sim
A69: =IFERROR(INDEX(Tabela2[ID_Area], MATCH(B69,Tabela2[Area], 0)), "Não encontrado") -> 1002 | B69: Meio Biótico | C69: Monitoramento Ambiental | D69: =ROW(D69) +98 -> 167 | E69: Garantir o plano de monitoramento de fauna e flora em campo. | F69: =IF(G69=1,"Concluído", IF(TODAY()>I69,"Atrasado", IF(AND(G69=0,TODAY()<I69),"Não iniciado", "Em Andamento"))) -> Concluído | G69: {=SUMPRODUCT( (Atividades!$E$2:$E$598=Metas!E69) * (Atividades!$O$2:$O$598=Metas!L69), Atividades!$I$2:$I$598, Atividades!$J$2:$J$598 ) / SUMPRODUCT( (Atividades!$E$2:$E$598=Metas!E69) * (Atividades!$O$2:$O$598=Metas!L69), Atividades!$J$2:$J$598 )} -> 1 | H69: 45660 | I69: 46022 | J69: =I69-H69 -> 362 | K69: =IFERROR(INDEX(Tabela3[ID_Responsavel], MATCH(L69,Tabela3[[Responsáveis ]], 0)), "Não encontrado") -> 9 | L69: Gilmar | M69: BIOTA | O69: Sim
A70: =IFERROR(INDEX(Tabela2[ID_Area], MATCH(B70,Tabela2[Area], 0)), "Não encontrado") -> 1001 | B70: Meio Ambiente - Operação | C70: P&D | D70: =ROW(D70) +98 -> 168 | E70: Executar o plano estratégico de suprimentos sustentável de material genético (mudas, sementes, composto orgânico...) do Cerrado | F70: =IF(G70=1,"Concluído", IF(TODAY()>I70,"Atrasado", IF(AND(G70=0,TODAY()<I70),"Não iniciado", "Em Andamento"))) -> #DIV/0! | G70: {=SUMPRODUCT( (Atividades!$E$2:$E$598=Metas!E70) * (Atividades!$O$2:$O$598=Metas!L70), Atividades!$I$2:$I$598, Atividades!$J$2:$J$598 ) / SUMPRODUCT( (Atividades!$E$2:$E$598=Metas!E70) * (Atividades!$O$2:$O$598=Metas!L70), Atividades!$J$2:$J$598 )} -> #DIV/0! | H70: 45660 | I70: 46021 | J70: =I70-H70 -> 361 | K70: =IFERROR(INDEX(Tabela3[ID_Responsavel], MATCH(L70,Tabela3[[Responsáveis ]], 0)), "Não encontrado") -> 19 | L70: Gleiciele | M70: CERRADÃO
A71: =IFERROR(INDEX(Tabela2[ID_Area], MATCH(B71,Tabela2[Area], 0)), "Não encontrado") -> 1003 | B71: Meio Físico | C71: Planos Diretores | D71: =ROW(D71) +98 -> 169 | E71: Estruturar o Plano Diretor de Águas do empreendimento, estabelecendo ações, indicadores e metas alinhados ao horizonte temporal de 2025 a 2030. | F71: =IF(G71=1,"Concluído", IF(TODAY()>I71,"Atrasado", IF(AND(G71=0,TODAY()<I71),"Não iniciado", "Em Andamento"))) -> Atrasado | G71: {=SUMPRODUCT( (Atividades!$E$2:$E$598=Metas!E71) * (Atividades!$O$2:$O$598=Metas!L71), Atividades!$I$2:$I$598, Atividades!$J$2:$J$598 ) / SUMPRODUCT( (Atividades!$E$2:$E$598=Metas!E71) * (Atividades!$O$2:$O$598=Metas!L71), Atividades!$J$2:$J$598 )} -> 0.96975628 | H71: 45658 | I71: 46022 | J71: =I71-H71 -> 364 | K71: =IFERROR(INDEX(Tabela3[ID_Responsavel], MATCH(L71,Tabela3[[Responsáveis ]], 0)), "Não encontrado") -> 21 | L71: Nelson Bolotari | M71: SVPM | O71: Não
A72: =IFERROR(INDEX(Tabela2[ID_Area], MATCH(B72,Tabela2[Area], 0)), "Não encontrado") -> 1003 | B72: Meio Físico | C72: Planos Diretores | D72: =ROW(D72) +98 -> 170 | E72: Implementar ações do Plano Diretor de Emissões Atmosféricas | F72: =IF(G72=1,"Concluído", IF(TODAY()>I72,"Atrasado", IF(AND(G72=0,TODAY()<I72),"Não iniciado", "Em Andamento"))) -> Concluído | G72: {=SUMPRODUCT( (Atividades!$E$2:$E$598=Metas!E72) * (Atividades!$O$2:$O$598=Metas!L72), Atividades!$I$2:$I$598, Atividades!$J$2:$J$598 ) / SUMPRODUCT( (Atividades!$E$2:$E$598=Metas!E72) * (Atividades!$O$2:$O$598=Metas!L72), Atividades!$J$2:$J$598 )} -> 1 | H72: 45658 | I72: 45960 | J72: =I72-H72 -> 302 | K72: =IFERROR(INDEX(Tabela3[ID_Responsavel], MATCH(L72,Tabela3[[Responsáveis ]], 0)), "Não encontrado") -> 21 | L72: Nelson Bolotari | M72: SVPM | O72: Sim
A73: =IFERROR(INDEX(Tabela2[ID_Area], MATCH(B73,Tabela2[Area], 0)), "Não encontrado") -> 1003 | B73: Meio Físico | C73: P&D | D73: =ROW(D73) +98 -> 171 | E73: Submeter ao menos um trabalho científico em evento/revista renomada | F73: =IF(G73=1,"Concluído", IF(TODAY()>I73,"Atrasado", IF(AND(G73=0,TODAY()<I73),"Não iniciado", "Em Andamento"))) -> Concluído | G73: {=SUMPRODUCT( (Atividades!$E$2:$E$598=Metas!E73) * (Atividades!$O$2:$O$598=Metas!L73), Atividades!$I$2:$I$598, Atividades!$J$2:$J$598 ) / SUMPRODUCT( (Atividades!$E$2:$E$598=Metas!E73) * (Atividades!$O$2:$O$598=Metas!L73), Atividades!$J$2:$J$598 )} -> 1 | H73: 45658 | I73: 45930 | J73: =I73-H73 -> 272 | K73: =IFERROR(INDEX(Tabela3[ID_Responsavel], MATCH(L73,Tabela3[[Responsáveis ]], 0)), "Não encontrado") -> 21 | L73: Nelson Bolotari | M73: SVPM | O73: Sim
A74: =IFERROR(INDEX(Tabela2[ID_Area], MATCH(B74,Tabela2[Area], 0)), "Não encontrado") -> 1003 | B74: Meio Físico | C74: P&D | D74: =ROW(D74) +98 -> 172 | E74: Desenvolver plano para o aproveitamento científico dos dados e informações do meio físico | F74: =IF(G74=1,"Concluído", IF(TODAY()>I74,"Atrasado", IF(AND(G74=0,TODAY()<I74),"Não iniciado", "Em Andamento"))) -> Concluído | G74: {=SUMPRODUCT( (Atividades!$E$2:$E$598=Metas!E74) * (Atividades!$O$2:$O$598=Metas!L74), Atividades!$I$2:$I$598, Atividades!$J$2:$J$598 ) / SUMPRODUCT( (Atividades!$E$2:$E$598=Metas!E74) * (Atividades!$O$2:$O$598=Metas!L74), Atividades!$J$2:$J$598 )} -> 1 | H74: 45658 | I74: 45746 | J74: =I74-H74 -> 88 | K74: =IFERROR(INDEX(Tabela3[ID_Responsavel], MATCH(L74,Tabela3[[Responsáveis ]], 0)), "Não encontrado") -> 21 | L74: Nelson Bolotari | M74: SVPM | O74: Sim
A75: =IFERROR(INDEX(Tabela2[ID_Area], MATCH(B75,Tabela2[Area], 0)), "Não encontrado") -> 1003 | B75: Meio Físico | C75: Planos Diretores | D75: =ROW(D75) +98 -> 173 | E75: Concluir e implantar Plano diretor de Resíduos | F75: =IF(G75=1,"Concluído", IF(TODAY()>I75,"Atrasado", IF(AND(G75=0,TODAY()<I75),"Não iniciado", "Em Andamento"))) -> Atrasado | G75: {=SUMPRODUCT( (Atividades!$E$2:$E$598=Metas!E75) * (Atividades!$O$2:$O$598=Metas!L75), Atividades!$I$2:$I$598, Atividades!$J$2:$J$598 ) / SUMPRODUCT( (Atividades!$E$2:$E$598=Metas!E75) * (Atividades!$O$2:$O$598=Metas!L75), Atividades!$J$2:$J$598 )} -> 0.86689655 | H75: 45658 | I75: 46022 | J75: =I75-H75 -> 364 | K75: =IFERROR(INDEX(Tabela3[ID_Responsavel], MATCH(L75,Tabela3[[Responsáveis ]], 0)), "Não encontrado") -> 21 | L75: Nelson Bolotari | M75: SVPM
A76: =IFERROR(INDEX(Tabela2[ID_Area], MATCH(B76,Tabela2[Area], 0)), "Não encontrado") -> 1003 | B76: Meio Físico | C76: P&D | D76: =ROW(D76) +98 -> 174 | E76: Definir estratégia para adequação da atualização da NBR 10004 (Ecotóxico) | F76: =IF(G76=1,"Concluído", IF(TODAY()>I76,"Atrasado", IF(AND(G76=0,TODAY()<I76),"Não iniciado", "Em Andamento"))) -> Concluído | G76: {=SUMPRODUCT( (Atividades!$E$2:$E$598=Metas!E76) * (Atividades!$O$2:$O$598=Metas!L76), Atividades!$I$2:$I$598, Atividades!$J$2:$J$598 ) / SUMPRODUCT( (Atividades!$E$2:$E$598=Metas!E76) * (Atividades!$O$2:$O$598=Metas!L76), Atividades!$J$2:$J$598 )} -> 1 | H76: 45658 | I76: 45807 | J76: =I76-H76 -> 149 | K76: =IFERROR(INDEX(Tabela3[ID_Responsavel], MATCH(L76,Tabela3[[Responsáveis ]], 0)), "Não encontrado") -> 21 | L76: Nelson Bolotari | M76: SVPM | O76: Sim
A77: =IFERROR(INDEX(Tabela2[ID_Area], MATCH(B77,Tabela2[Area], 0)), "Não encontrado") -> 1003 | B77: Meio Físico | C77: Planos Diretores | D77: =ROW(D77) +98 -> 175 | E77: Execução das atividades em campo em atendimento ao Plano Diretor de Emissões Atmosféricas (Testes com polímeros, otimização de rota de caminhão pipa, etc) | F77: =IF(G77=1,"Concluído", IF(TODAY()>I77,"Atrasado", IF(AND(G77=0,TODAY()<I77),"Não iniciado", "Em Andamento"))) -> Concluído | G77: {=SUMPRODUCT( (Atividades!$E$2:$E$598=Metas!E77) * (Atividades!$O$2:$O$598=Metas!L77), Atividades!$I$2:$I$598, Atividades!$J$2:$J$598 ) / SUMPRODUCT( (Atividades!$E$2:$E$598=Metas!E77) * (Atividades!$O$2:$O$598=Metas!L77), Atividades!$J$2:$J$598 )} -> 1 | H77: 45658 | I77: 45807 | J77: =I77-H77 -> 149 | K77: =IFERROR(INDEX(Tabela3[ID_Responsavel], MATCH(L77,Tabela3[[Responsáveis ]], 0)), "Não encontrado") -> 11 | L77: Jansley Rodart | M77: BIOTA | O77: Sim
A78: =IFERROR(INDEX(Tabela2[ID_Area], MATCH(B78,Tabela2[Area], 0)), "Não encontrado") -> 1003 | B78: Meio Físico | C78: Monitoramento Ambiental | D78: =ROW(D78) +98 -> 176 | E78: Implementar sistema de monitoramento online para acompanhar, em tempo real, a qualidade da água, utilizando tecnologias avançadas para garantir precisão e eficiência no processo. | F78: =IF(G78=1,"Concluído", IF(TODAY()>I78,"Atrasado", IF(AND(G78=0,TODAY()<I78),"Não iniciado", "Em Andamento"))) -> Concluído | G78: {=SUMPRODUCT( (Atividades!$E$2:$E$598=Metas!E78) * (Atividades!$O$2:$O$598=Metas!L78), Atividades!$I$2:$I$598, Atividades!$J$2:$J$598 ) / SUMPRODUCT( (Atividades!$E$2:$E$598=Metas!E78) * (Atividades!$O$2:$O$598=Metas!L78), Atividades!$J$2:$J$598 )} -> 1 | H78: 45658 | I78: 45746 | J78: =I78-H78 -> 88 | K78: =IFERROR(INDEX(Tabela3[ID_Responsavel], MATCH(L78,Tabela3[[Responsáveis ]], 0)), "Não encontrado") -> 11 | L78: Jansley Rodart | M78: BIOTA | O78: Sim
A79: =IFERROR(INDEX(Tabela2[ID_Area], MATCH(B79,Tabela2[Area], 0)), "Não encontrado") -> 1003 | B79: Meio Físico | C79: Monitoramento Ambiental | D79: =ROW(D79) +98 -> 177 | E79: Realizar levantamento dos pontos críticos de monitoramento ambiental - Qualidade da água superficial, subterrânea | F79: =IF(G79=1,"Concluído", IF(TODAY()>I79,"Atrasado", IF(AND(G79=0,TODAY()<I79),"Não iniciado", "Em Andamento"))) -> Concluído | G79: {=SUMPRODUCT( (Atividades!$E$2:$E$598=Metas!E79) * (Atividades!$O$2:$O$598=Metas!L79), Atividades!$I$2:$I$598, Atividades!$J$2:$J$598 ) / SUMPRODUCT( (Atividades!$E$2:$E$598=Metas!E79) * (Atividades!$O$2:$O$598=Metas!L79), Atividades!$J$2:$J$598 )} -> 1 | H79: 45658 | I79: 45716 | J79: =I79-H79 -> 58 | K79: =IFERROR(INDEX(Tabela3[ID_Responsavel], MATCH(L79,Tabela3[[Responsáveis ]], 0)), "Não encontrado") -> 11 | L79: Jansley Rodart | M79: BIOTA | O79: Sim
A80: =IFERROR(INDEX(Tabela2[ID_Area], MATCH(B80,Tabela2[Area], 0)), "Não encontrado") -> 1003 | B80: Meio Físico | C80: Monitoramento Ambiental | D80: =ROW(D80) +98 -> 178 | E80: Executar ações de melhoria dos pontos levantados nos pontos críticos de monitoramento ambiental - Qualidade da água superficial, subterranea | F80: =IF(G80=1,"Concluído", IF(TODAY()>I80,"Atrasado", IF(AND(G80=0,TODAY()<I80),"Não iniciado", "Em Andamento"))) -> Atrasado | G80: {=SUMPRODUCT( (Atividades!$E$2:$E$598=Metas!E80) * (Atividades!$O$2:$O$598=Metas!L80), Atividades!$I$2:$I$598, Atividades!$J$2:$J$598 ) / SUMPRODUCT( (Atividades!$E$2:$E$598=Metas!E80) * (Atividades!$O$2:$O$598=Metas!L80), Atividades!$J$2:$J$598 )} -> 0.32659574 | H80: 45716 | I80: 45930 | J80: =I80-H80 -> 214 | K80: =IFERROR(INDEX(Tabela3[ID_Responsavel], MATCH(L80,Tabela3[[Responsáveis ]], 0)), "Não encontrado") -> 11 | L80: Jansley Rodart | M80: BIOTA | O80: Não
A81: =IFERROR(INDEX(Tabela2[ID_Area], MATCH(B81,Tabela2[Area], 0)), "Não encontrado") -> 1003 | B81: Meio Físico | C81: Monitoramento Ambiental | D81: =ROW(D81) +98 -> 179 | E81: Implementar sistema de monitoramento online para acompanhar, em tempo real, a qualidade do ar, utilizando tecnologias avançadas para garantir precisão e eficiência no processo. | F81: =IF(G81=1,"Concluído", IF(TODAY()>I81,"Atrasado", IF(AND(G81=0,TODAY()<I81),"Não iniciado", "Em Andamento"))) -> Concluído | G81: {=SUMPRODUCT( (Atividades!$E$2:$E$598=Metas!E81) * (Atividades!$O$2:$O$598=Metas!L81), Atividades!$I$2:$I$598, Atividades!$J$2:$J$598 ) / SUMPRODUCT( (Atividades!$E$2:$E$598=Metas!E81) * (Atividades!$O$2:$O$598=Metas!L81), Atividades!$J$2:$J$598 )} -> 1 | H81: 45658 | I81: 45746 | J81: =I81-H81 -> 88 | K81: =IFERROR(INDEX(Tabela3[ID_Responsavel], MATCH(L81,Tabela3[[Responsáveis ]], 0)), "Não encontrado") -> 15 | L81: Luciano Marcelino | M81: BIOTA
A82: =IFERROR(INDEX(Tabela2[ID_Area], MATCH(B82,Tabela2[Area], 0)), "Não encontrado") -> 1003 | B82: Meio Físico | C82: Estudos Ambientais | D82: =ROW(D82) +98 -> 180 | E82: Realizar cadastramento de Sistemas de Drenagem e criar Fluxograma esquemático das contribuições dos SUMP's nos cursos hídricos | F82: =IF(G82=1,"Concluído", IF(TODAY()>I82,"Atrasado", IF(AND(G82=0,TODAY()<I82),"Não iniciado", "Em Andamento"))) -> Concluído | G82: {=SUMPRODUCT( (Atividades!$E$2:$E$598=Metas!E82) * (Atividades!$O$2:$O$598=Metas!L82), Atividades!$I$2:$I$598, Atividades!$J$2:$J$598 ) / SUMPRODUCT( (Atividades!$E$2:$E$598=Metas!E82) * (Atividades!$O$2:$O$598=Metas!L82), Atividades!$J$2:$J$598 )} -> 1 | H82: 45658 | I82: 45807 | J82: =I82-H82 -> 149 | K82: =IFERROR(INDEX(Tabela3[ID_Responsavel], MATCH(L82,Tabela3[[Responsáveis ]], 0)), "Não encontrado") -> 15 | L82: Luciano Marcelino | M82: BIOTA
A83: =IFERROR(INDEX(Tabela2[ID_Area], MATCH(B83,Tabela2[Area], 0)), "Não encontrado") -> 1003 | B83: Meio Físico | C83: Estudos Ambientais | D83: =ROW(D83) +98 -> 181 | E83: Realizar levantamento das informações para o PROVIAS (Mapeamento de asfalto, canaletas, guard rail, sinalizações, etc) | F83: =IF(G83=1,"Concluído", IF(TODAY()>I83,"Atrasado", IF(AND(G83=0,TODAY()<I83),"Não iniciado", "Em Andamento"))) -> Concluído | G83: {=SUMPRODUCT( (Atividades!$E$2:$E$598=Metas!E83) * (Atividades!$O$2:$O$598=Metas!L83), Atividades!$I$2:$I$598, Atividades!$J$2:$J$598 ) / SUMPRODUCT( (Atividades!$E$2:$E$598=Metas!E83) * (Atividades!$O$2:$O$598=Metas!L83), Atividades!$J$2:$J$598 )} -> 1 | H83: 45658 | I83: 46022 | J83: =I83-H83 -> 364 | K83: =IFERROR(INDEX(Tabela3[ID_Responsavel], MATCH(L83,Tabela3[[Responsáveis ]], 0)), "Não encontrado") -> 15 | L83: Luciano Marcelino | M83: BIOTA
A84: =IFERROR(INDEX(Tabela2[ID_Area], MATCH(B84,Tabela2[Area], 0)), "Não encontrado") -> 1003 | B84: Meio Físico | C84: P&D | D84: =ROW(D84) +98 -> 182 | E84: Escrever pelo menos um artigo científico para avaliação interna | F84: =IF(G84=1,"Concluído", IF(TODAY()>I84,"Atrasado", IF(AND(G84=0,TODAY()<I84),"Não iniciado", "Em Andamento"))) -> Concluído | G84: {=SUMPRODUCT( (Atividades!$E$2:$E$598=Metas!E84) * (Atividades!$O$2:$O$598=Metas!L84), Atividades!$I$2:$I$598, Atividades!$J$2:$J$598 ) / SUMPRODUCT( (Atividades!$E$2:$E$598=Metas!E84) * (Atividades!$O$2:$O$598=Metas!L84), Atividades!$J$2:$J$598 )} -> 1 | H84: 45658 | I84: 45777 | J84: =I84-H84 -> 119 | K84: =IFERROR(INDEX(Tabela3[ID_Responsavel], MATCH(L84,Tabela3[[Responsáveis ]], 0)), "Não encontrado") -> 16 | L84: Maryel Galvão | M84: BIOTA | O84: Sim
A85: =IFERROR(INDEX(Tabela2[ID_Area], MATCH(B85,Tabela2[Area], 0)), "Não encontrado") -> 1003 | B85: Meio Físico | C85: Estudos Ambientais | D85: =ROW(D85) +98 -> 183 | E85: Estruturar trabalho de campo com prioridades de atuação para execução do trabalho de cadastramento de Sistema de Drenagem e apresentar cronograma/planejamento de execução | F85: =IF(G85=1,"Concluído", IF(TODAY()>I85,"Atrasado", IF(AND(G85=0,TODAY()<I85),"Não iniciado", "Em Andamento"))) -> Concluído | G85: {=SUMPRODUCT( (Atividades!$E$2:$E$598=Metas!E85) * (Atividades!$O$2:$O$598=Metas!L85), Atividades!$I$2:$I$598, Atividades!$J$2:$J$598 ) / SUMPRODUCT( (Atividades!$E$2:$E$598=Metas!E85) * (Atividades!$O$2:$O$598=Metas!L85), Atividades!$J$2:$J$598 )} -> 1 | H85: 45658 | I85: 45777 | J85: =I85-H85 -> 119 | K85: =IFERROR(INDEX(Tabela3[ID_Responsavel], MATCH(L85,Tabela3[[Responsáveis ]], 0)), "Não encontrado") -> 16 | L85: Maryel Galvão | M85: BIOTA | O85: Sim
A86: =IFERROR(INDEX(Tabela2[ID_Area], MATCH(B86,Tabela2[Area], 0)), "Não encontrado") -> 1003 | B86: Meio Físico | C86: Planos Diretores | D86: =ROW(D86) +98 -> 184 | E86: Estruturar trabalho de campo com prioridades de atuação para execução das atividades do Plano Diretor de Emissões Atmosféricas apresentar cronograma/planejamento de execução | F86: =IF(G86=1,"Concluído", IF(TODAY()>I86,"Atrasado", IF(AND(G86=0,TODAY()<I86),"Não iniciado", "Em Andamento"))) -> Concluído | G86: {=SUMPRODUCT( (Atividades!$E$2:$E$598=Metas!E86) * (Atividades!$O$2:$O$598=Metas!L86), Atividades!$I$2:$I$598, Atividades!$J$2:$J$598 ) / SUMPRODUCT( (Atividades!$E$2:$E$598=Metas!E86) * (Atividades!$O$2:$O$598=Metas!L86), Atividades!$J$2:$J$598 )} -> 1 | H86: 45658 | I86: 45807 | J86: =I86-H86 -> 149 | K86: =IFERROR(INDEX(Tabela3[ID_Responsavel], MATCH(L86,Tabela3[[Responsáveis ]], 0)), "Não encontrado") -> 16 | L86: Maryel Galvão | M86: BIOTA | O86: Sim
A87: =IFERROR(INDEX(Tabela2[ID_Area], MATCH(B87,Tabela2[Area], 0)), "Não encontrado") -> 1003 | B87: Meio Físico | C87: Planos Diretores | D87: =ROW(D87) +98 -> 185 | E87: Implementar modelo de Governança de Gestão Hídrica | F87: =IF(G87=1,"Concluído", IF(TODAY()>I87,"Atrasado", IF(AND(G87=0,TODAY()<I87),"Não iniciado", "Em Andamento"))) -> Concluído | G87: {=SUMPRODUCT( (Atividades!$E$2:$E$598=Metas!E87) * (Atividades!$O$2:$O$598=Metas!L87), Atividades!$I$2:$I$598, Atividades!$J$2:$J$598 ) / SUMPRODUCT( (Atividades!$E$2:$E$598=Metas!E87) * (Atividades!$O$2:$O$598=Metas!L87), Atividades!$J$2:$J$598 )} -> 1 | H87: 45658 | I87: 45991 | J87: =I87-H87 -> 333 | K87: =IFERROR(INDEX(Tabela3[ID_Responsavel], MATCH(L87,Tabela3[[Responsáveis ]], 0)), "Não encontrado") -> 16 | L87: Maryel Galvão | M87: BIOTA | O87: Sim
A88: =IFERROR(INDEX(Tabela2[ID_Area], MATCH(B88,Tabela2[Area], 0)), "Não encontrado") -> 1003 | B88: Meio Físico | C88: Planos Diretores | D88: =ROW(D88) +98 -> 186 | E88: Realizar GAP Analysis e propor Plano de Trabalho para adequação ao atendimento da NBR 10.004 | F88: =IF(G88=1,"Concluído", IF(TODAY()>I88,"Atrasado", IF(AND(G88=0,TODAY()<I88),"Não iniciado", "Em Andamento"))) -> Concluído | G88: {=SUMPRODUCT( (Atividades!$E$2:$E$598=Metas!E88) * (Atividades!$O$2:$O$598=Metas!L88), Atividades!$I$2:$I$598, Atividades!$J$2:$J$598 ) / SUMPRODUCT( (Atividades!$E$2:$E$598=Metas!E88) * (Atividades!$O$2:$O$598=Metas!L88), Atividades!$J$2:$J$598 )} -> 1 | H88: 45658 | I88: 45731 | J88: =I88-H88 -> 73 | K88: =IFERROR(INDEX(Tabela3[ID_Responsavel], MATCH(L88,Tabela3[[Responsáveis ]], 0)), "Não encontrado") -> 16 | L88: Maryel Galvão | M88: BIOTA | O88: Sim
A89: =IFERROR(INDEX(Tabela2[ID_Area], MATCH(B89,Tabela2[Area], 0)), "Não encontrado") -> 1003 | B89: Meio Físico | C89: Monitoramento Ambiental | D89: =ROW(D89) +98 -> 187 | E89: Realizar acompanhamento e monitoramento de desempenho contínuo, reportando mensalmente relatório sobre a eficiência e a precisão do sistema em fornecer dados válidos e úteis dentro do período definido (monitoramento online de água) | F89: =IF(G89=1,"Concluído", IF(TODAY()>I89,"Atrasado", IF(AND(G89=0,TODAY()<I89),"Não iniciado", "Em Andamento"))) -> Concluído | G89: {=SUMPRODUCT( (Atividades!$E$2:$E$598=Metas!E89) * (Atividades!$O$2:$O$598=Metas!L89), Atividades!$I$2:$I$598, Atividades!$J$2:$J$598 ) / SUMPRODUCT( (Atividades!$E$2:$E$598=Metas!E89) * (Atividades!$O$2:$O$598=Metas!L89), Atividades!$J$2:$J$598 )} -> 1 | H89: 45658 | I89: 46022 | J89: =I89-H89 -> 364 | K89: =IFERROR(INDEX(Tabela3[ID_Responsavel], MATCH(L89,Tabela3[[Responsáveis ]], 0)), "Não encontrado") -> 11 | L89: Jansley Rodart | M89: BIOTA | O89: Sim
A90: =IFERROR(INDEX(Tabela2[ID_Area], MATCH(B90,Tabela2[Area], 0)), "Não encontrado") -> 1003 | B90: Meio Físico | C90: Monitoramento Ambiental | D90: =ROW(D90) +98 -> 188 | E90: Realizar acompanhamento e monitoramento de desempenho contínuo, reportando mensalmente, um relatório sobre a eficiência e a precisao do sistema em fornecer dados válidos e úteis dentro do período definido ( Monitoramento Online de Emissões) | F90: =IF(G90=1,"Concluído", IF(TODAY()>I90,"Atrasado", IF(AND(G90=0,TODAY()<I90),"Não iniciado", "Em Andamento"))) -> Concluído | G90: {=SUMPRODUCT( (Atividades!$E$2:$E$598=Metas!E90) * (Atividades!$O$2:$O$598=Metas!L90), Atividades!$I$2:$I$598, Atividades!$J$2:$J$598 ) / SUMPRODUCT( (Atividades!$E$2:$E$598=Metas!E90) * (Atividades!$O$2:$O$598=Metas!L90), Atividades!$J$2:$J$598 )} -> 1 | H90: 45658 | I90: 46022 | J90: =I90-H90 -> 364 | K90: =IFERROR(INDEX(Tabela3[ID_Responsavel], MATCH(L90,Tabela3[[Responsáveis ]], 0)), "Não encontrado") -> 15 | L90: Luciano Marcelino | M90: BIOTA
A91: =IFERROR(INDEX(Tabela2[ID_Area], MATCH(B91,Tabela2[Area], 0)), "Não encontrado") -> 1003 | B91: Meio Físico | C91: Planos Diretores | D91: =ROW(D91) +98 -> 189 | E91: Realizar acompanhamento mensal da evolução das ações do GAP ANALYSIS - Plano Diretor de Resíduos | F91: =IF(G91=1,"Concluído", IF(TODAY()>I91,"Atrasado", IF(AND(G91=0,TODAY()<I91),"Não iniciado", "Em Andamento"))) -> Concluído | G91: {=SUMPRODUCT( (Atividades!$E$2:$E$598=Metas!E91) * (Atividades!$O$2:$O$598=Metas!L91), Atividades!$I$2:$I$598, Atividades!$J$2:$J$598 ) / SUMPRODUCT( (Atividades!$E$2:$E$598=Metas!E91) * (Atividades!$O$2:$O$598=Metas!L91), Atividades!$J$2:$J$598 )} -> 1 | H91: 45658 | I91: 46022 | J91: =I91-H91 -> 364 | K91: =IFERROR(INDEX(Tabela3[ID_Responsavel], MATCH(L91,Tabela3[[Responsáveis ]], 0)), "Não encontrado") -> 8 | L91: Geovanna Freitas | M91: BIOTA
A92: =IFERROR(INDEX(Tabela2[ID_Area], MATCH(B92,Tabela2[Area], 0)), "Não encontrado") -> 1000 | B92: Meio Ambiente - Gerencial | C92: Projeto | D92: =ROW(D92) +98 -> 190 | E92: Realizar monitoramentos diários de Turbidez e Salinidade | F92: =IF(G92=1,"Concluído", IF(TODAY()>I92,"Atrasado", IF(AND(G92=0,TODAY()<I92),"Não iniciado", "Em Andamento"))) -> Concluído | G92: {=SUMPRODUCT( (Atividades!$E$2:$E$598=Metas!E92) * (Atividades!$O$2:$O$598=Metas!L92), Atividades!$I$2:$I$598, Atividades!$J$2:$J$598 ) / SUMPRODUCT( (Atividades!$E$2:$E$598=Metas!E92) * (Atividades!$O$2:$O$598=Metas!L92), Atividades!$J$2:$J$598 )} -> 1 | H92: 45658 | I92: 45993 | J92: =I92-H92 -> 335 | K92: =IFERROR(INDEX(Tabela3[ID_Responsavel], MATCH(L92,Tabela3[[Responsáveis ]], 0)), "Não encontrado") -> 5 | L92: Daniel | M92: BIOTA
A93: =IFERROR(INDEX(Tabela2[ID_Area], MATCH(B93,Tabela2[Area], 0)), "Não encontrado") -> 1000 | B93: Meio Ambiente - Gerencial | C93: Estudos Ambientais | D93: =ROW(D93) +98 -> 191 | E93: Apoiar a atualização da base de APP (Vereda, Nascente e cursos hídricos) das propriedades. | F93: =IF(G93=1,"Concluído", IF(TODAY()>I93,"Atrasado", IF(AND(G93=0,TODAY()<I93),"Não iniciado", "Em Andamento"))) -> Concluído | G93: {=SUMPRODUCT( (Atividades!$E$2:$E$598=Metas!E93) * (Atividades!$O$2:$O$598=Metas!L93), Atividades!$I$2:$I$598, Atividades!$J$2:$J$598 ) / SUMPRODUCT( (Atividades!$E$2:$E$598=Metas!E93) * (Atividades!$O$2:$O$598=Metas!L93), Atividades!$J$2:$J$598 )} -> 1 | H93: 45659 | I93: 45994 | J93: =I93-H93 -> 335 | K93: =IFERROR(INDEX(Tabela3[ID_Responsavel], MATCH(L93,Tabela3[[Responsáveis ]], 0)), "Não encontrado") -> 5 | L93: Daniel | M93: BIOTA
A94: =IFERROR(INDEX(Tabela2[ID_Area], MATCH(B94,Tabela2[Area], 0)), "Não encontrado") -> 1000 | B94: Meio Ambiente - Gerencial | C94: Estudos Ambientais | D94: =ROW(D94) +98 -> 192 | E94: Apoiar Elaboração Book ambiental dos teste DIEP(Heap Leaching) | F94: =IF(G94=1,"Concluído", IF(TODAY()>I94,"Atrasado", IF(AND(G94=0,TODAY()<I94),"Não iniciado", "Em Andamento"))) -> Concluído | G94: {=SUMPRODUCT( (Atividades!$E$2:$E$598=Metas!E94) * (Atividades!$O$2:$O$598=Metas!L94), Atividades!$I$2:$I$598, Atividades!$J$2:$J$598 ) / SUMPRODUCT( (Atividades!$E$2:$E$598=Metas!E94) * (Atividades!$O$2:$O$598=Metas!L94), Atividades!$J$2:$J$598 )} -> 1 | H94: 45659 | I94: 45994 | J94: =I94-H94 -> 335 | K94: =IFERROR(INDEX(Tabela3[ID_Responsavel], MATCH(L94,Tabela3[[Responsáveis ]], 0)), "Não encontrado") -> 5 | L94: Daniel | M94: BIOTA
A95: =IFERROR(INDEX(Tabela2[ID_Area], MATCH(B95,Tabela2[Area], 0)), "Não encontrado") -> 1000 | B95: Meio Ambiente - Gerencial | C95: Estudos Ambientais | D95: =ROW(D95) +98 -> 193 | E95: Acompanhamento In Loco da operaçáo da Planta Piloto de Tratabilidade de Efluente Salino | F95: =IF(G95=1,"Concluído", IF(TODAY()>I95,"Atrasado", IF(AND(G95=0,TODAY()<I95),"Não iniciado", "Em Andamento"))) -> Concluído | G95: {=SUMPRODUCT( (Atividades!$E$2:$E$598=Metas!E95) * (Atividades!$O$2:$O$598=Metas!L95), Atividades!$I$2:$I$598, Atividades!$J$2:$J$598 ) / SUMPRODUCT( (Atividades!$E$2:$E$598=Metas!E95) * (Atividades!$O$2:$O$598=Metas!L95), Atividades!$J$2:$J$598 )} -> 1 | H95: 45659 | I95: 45994 | J95: =I95-H95 -> 335 | K95: =IFERROR(INDEX(Tabela3[ID_Responsavel], MATCH(L95,Tabela3[[Responsáveis ]], 0)), "Não encontrado") -> 5 | L95: Daniel | M95: BIOTA
A96: =IFERROR(INDEX(Tabela2[ID_Area], MATCH(B96,Tabela2[Area], 0)), "Não encontrado") -> 1001 | B96: Meio Ambiente - Operação | C96: P&D | D96: =ROW(D96) +98 -> 194 | E96: Propor nova metodologia para controle de material particulado em vias não pavimentadas_GuilhermeMonteiro | F96: =IF(G96=1,"Concluído", IF(TODAY()>I96,"Atrasado", IF(AND(G96=0,TODAY()<I96),"Não iniciado", "Em Andamento"))) -> Concluído | G96: {=SUMPRODUCT( (Atividades!$E$2:$E$598=Metas!E96) * (Atividades!$O$2:$O$598=Metas!L96), Atividades!$I$2:$I$598, Atividades!$J$2:$J$598 ) / SUMPRODUCT( (Atividades!$E$2:$E$598=Metas!E96) * (Atividades!$O$2:$O$598=Metas!L96), Atividades!$J$2:$J$598 )} -> 1 | H96: 45719 | I96: 45847 | J96: =I96-H96 -> 128 | K96: =IFERROR(INDEX(Tabela3[ID_Responsavel], MATCH(L96,Tabela3[[Responsáveis ]], 0)), "Não encontrado") -> 10 | L96: Guilherme Monteiro | M96: BIOTA | O96: Sim
A97: =IFERROR(INDEX(Tabela2[ID_Area], MATCH(B97,Tabela2[Area], 0)), "Não encontrado") -> 1004 | B97: Licenciamento & Regulatório | C97: Gestão Ambiental de Fornecedores | D97: =ROW(D97) +98 -> 195 | E97: Implementar, executar e gerir processo de gestão ambiental documental e de desempenho operacional de empresas envolvidas nas obras de Complementação de Projeto | F97: =IF(G97=1,"Concluído", IF(TODAY()>I97,"Atrasado", IF(AND(G97=0,TODAY()<I97),"Não iniciado", "Em Andamento"))) -> Concluído | G97: {=SUMPRODUCT( (Atividades!$E$2:$E$598=Metas!E97) * (Atividades!$O$2:$O$598=Metas!L97), Atividades!$I$2:$I$598, Atividades!$J$2:$J$598 ) / SUMPRODUCT( (Atividades!$E$2:$E$598=Metas!E97) * (Atividades!$O$2:$O$598=Metas!L97), Atividades!$J$2:$J$598 )} -> 1 | H97: 45769 | I97: 46022 | J97: =I97-H97 -> 253 | K97: =IFERROR(INDEX(Tabela3[ID_Responsavel], MATCH(L97,Tabela3[[Responsáveis ]], 0)), "Não encontrado") -> 27 | L97: Ana Clara | M97: SESI | O97: Sim
A98: =IFERROR(INDEX(Tabela2[ID_Area], MATCH(B98,Tabela2[Area], 0)), "Não encontrado") -> 1004 | B98: Licenciamento & Regulatório | C98: Treinamentos Ambientais | D98: =ROW(D98) +98 -> 196 | E98: Desenvolver matriz de treinamentos ambientais aplicáveis por cargo e função SVPM, implementar e ministrar os treinamentos para capacitação | F98: =IF(G98=1,"Concluído", IF(TODAY()>I98,"Atrasado", IF(AND(G98=0,TODAY()<I98),"Não iniciado", "Em Andamento"))) -> Atrasado | G98: {=SUMPRODUCT( (Atividades!$E$2:$E$598=Metas!E98) * (Atividades!$O$2:$O$598=Metas!L98), Atividades!$I$2:$I$598, Atividades!$J$2:$J$598 ) / SUMPRODUCT( (Atividades!$E$2:$E$598=Metas!E98) * (Atividades!$O$2:$O$598=Metas!L98), Atividades!$J$2:$J$598 )} -> 0.90827068 | H98: 45778 | I98: 46022 | J98: =I98-H98 -> 244 | K98: =IFERROR(INDEX(Tabela3[ID_Responsavel], MATCH(L98,Tabela3[[Responsáveis ]], 0)), "Não encontrado") -> 27 | L98: Ana Clara | M98: SESI | N98: Dar continuidade aos treinamentos ambientais para as equipes SVPM em 2026, seguindo o ciclo de treinamento. | O98: Sim
A99: =IFERROR(INDEX(Tabela2[ID_Area], MATCH(B99,Tabela2[Area], 0)), "Não encontrado") -> 1004 | B99: Licenciamento & Regulatório | C99: Relatório de Desempenho Ambiental | D99: =ROW(D99) +98 -> 197 | E99: Executar e consolidar sistemática de atualização e consolidação das informações para elaboração RDA 2026/2025_Ana Clara | F99: =IF(G99=1,"Concluído", IF(TODAY()>I99,"Atrasado", IF(AND(G99=0,TODAY()<I99),"Não iniciado", "Em Andamento"))) -> Concluído | G99: {=SUMPRODUCT( (Atividades!$E$2:$E$598=Metas!E99) * (Atividades!$O$2:$O$598=Metas!L99), Atividades!$I$2:$I$598, Atividades!$J$2:$J$598 ) / SUMPRODUCT( (Atividades!$E$2:$E$598=Metas!E99) * (Atividades!$O$2:$O$598=Metas!L99), Atividades!$J$2:$J$598 )} -> 1 | H99: 45748 | I99: 46013 | J99: =I99-H99 -> 265 | K99: =IFERROR(INDEX(Tabela3[ID_Responsavel], MATCH(L99,Tabela3[[Responsáveis ]], 0)), "Não encontrado") -> 27 | L99: Ana Clara | M99: SESI | O99: Sim
A100: =IFERROR(INDEX(Tabela2[ID_Area], MATCH(B100,Tabela2[Area], 0)), "Não encontrado") -> 1004 | B100: Licenciamento & Regulatório | C100: SGA | D100: =ROW(D100) +98 -> 198 | E100: Desenvolver Guideline/Documento de Referência Interna de Gestão Ambiental conforme requisitos IFC, ISO e outros aplicáveis. | F100: =IF(G100=1,"Concluído", IF(TODAY()>I100,"Atrasado", IF(AND(G100=0,TODAY()<I100),"Não iniciado", "Em Andamento"))) -> Atrasado | G100: {=SUMPRODUCT( (Atividades!$E$2:$E$598=Metas!E100) * (Atividades!$O$2:$O$598=Metas!L100), Atividades!$I$2:$I$598, Atividades!$J$2:$J$598 ) / SUMPRODUCT( (Atividades!$E$2:$E$598=Metas!E100) * (Atividades!$O$2:$O$598=Metas!L100), Atividades!$J$2:$J$598 )} -> 0.79896907 | H100: 45911 | I100: 46013 | J100: =I100-H100 -> 102 | K100: =IFERROR(INDEX(Tabela3[ID_Responsavel], MATCH(L100,Tabela3[[Responsáveis ]], 0)), "Não encontrado") -> 27 | L100: Ana Clara | M100: SESI | N100: Elaboração do Documento sua revisão e publicaçãoserão executados em 2026. | O100: Não
...

Sheet Atividades
A1: ID_Area | B1: Área | C1: Tema | D1: ID_Meta | E1: Descrição da Meta | F1: Atividade | G1: Status da Atividade | H1: Data de Conclusão | I1: % Concluído | J1: Peso da tarefa | K1: Data Inicio | L1: Data Fim | M1: Duração | N1: ID_Responsavel | O1: Responsável | P1: Empresa | Q1: Observação de Acompanhamento
A2: =IFERROR(INDEX(Tabela2[ID_Area], MATCH(B2,Tabela2[Area], 0)), "Não encontrado") -> 1000 | B2: Meio Ambiente - Gerencial | C2: Regulatório | D2: =IFERROR(INDEX(Metas!$D$2:$D$104, MATCH(E2,Metas!$E$2:$E$104, 0)), "Não encontrado") -> 125 | E2: Atualizar base de APP (Vereda, Nascente e cursos hídricos) das propriedades. | F2: Diagnóstico de recursos e planejamento de prioridades | G2: =IF(I2=1,"Concluído", IF(TODAY()>L2,"Atrasado", IF(AND(I2=0,TODAY()<K2),"Não iniciado", "Em Andamento"))) -> Concluído | H2: 45660 | I2: 1 | J2: =IFERROR( M2 / SUMIFS($M:$M, $E:$E, $E2, $O:$O, $O2) * 120, 0 ) -> 0.30795552 | K2: 45660 | L2: 45662 | M2: =L2 - K2 + 1 -> 3 | N2: =IFERROR(INDEX(Tabela3[ID_Responsavel], MATCH(O2,Tabela3[[Responsáveis ]], 0)), "Não encontrado") -> 7 | O2: Edimar Dias | P2: SESI | Q2: Organizado banco de dados
A3: =IFERROR(INDEX(Tabela2[ID_Area], MATCH(B3,Tabela2[Area], 0)), "Não encontrado") -> 1000 | B3: Meio Ambiente - Gerencial | C3: Regulatório | D3: =IFERROR(INDEX(Metas!$D$2:$D$104, MATCH(E3,Metas!$E$2:$E$104, 0)), "Não encontrado") -> 125 | E3: Atualizar base de APP (Vereda, Nascente e cursos hídricos) das propriedades. | F3: Elaboração de escopo para contratação | G3: =IF(I3=1,"Concluído", IF(TODAY()>L3,"Atrasado", IF(AND(I3=0,TODAY()<K3),"Não iniciado", "Em Andamento"))) -> Concluído | H3: 45671 | I3: 1 | J3: =IFERROR( M3 / SUMIFS($M:$M, $E:$E, $E3, $O:$O, $O3) * 120, 0 ) -> 1.7450813 | K3: 45664 | L3: 45680 | M3: =L3 - K3 + 1 -> 17 | N3: =IFERROR(INDEX(Tabela3[ID_Responsavel], MATCH(O3,Tabela3[[Responsáveis ]], 0)), "Não encontrado") -> 7 | O3: Edimar Dias | P3: SESI | Q3: Escopo elaborado
A4: =IFERROR(INDEX(Tabela2[ID_Area], MATCH(B4,Tabela2[Area], 0)), "Não encontrado") -> 1000 | B4: Meio Ambiente - Gerencial | C4: Regulatório | D4: =IFERROR(INDEX(Metas!$D$2:$D$104, MATCH(E4,Metas!$E$2:$E$104, 0)), "Não encontrado") -> 125 | E4: Atualizar base de APP (Vereda, Nascente e cursos hídricos) das propriedades. | F4: Contratação de empresa para levantamento de dados em campo | G4: =IF(I4=1,"Concluído", IF(TODAY()>L4,"Atrasado", IF(AND(I4=0,TODAY()<K4),"Não iniciado", "Em Andamento"))) -> Concluído | I4: 1 | J4: =IFERROR( M4 / SUMIFS($M:$M, $E:$E, $E4, $O:$O, $O4) * 120, 0 ) -> 22.378101 | K4: 45703 | L4: 45920 | M4: =L4 - K4 + 1 -> 218 | N4: =IFERROR(INDEX(Tabela3[ID_Responsavel], MATCH(O4,Tabela3[[Responsáveis ]], 0)), "Não encontrado") -> 7 | O4: Edimar Dias | P4: SESI
A5: =IFERROR(INDEX(Tabela2[ID_Area], MATCH(B5,Tabela2[Area], 0)), "Não encontrado") -> 1000 | B5: Meio Ambiente - Gerencial | C5: Regulatório | D5: =IFERROR(INDEX(Metas!$D$2:$D$104, MATCH(E5,Metas!$E$2:$E$104, 0)), "Não encontrado") -> 125 | E5: Atualizar base de APP (Vereda, Nascente e cursos hídricos) das propriedades. | F5: Reunião de kick off com empresa | G5: =IF(I5=1,"Concluído", IF(TODAY()>L5,"Atrasado", IF(AND(I5=0,TODAY()<K5),"Não iniciado", "Em Andamento"))) -> Concluído | I5: 1 | J5: =IFERROR( M5 / SUMIFS($M:$M, $E:$E, $E5, $O:$O, $O5) * 120, 0 ) -> 19.811805 | K5: 45736 | L5: 45928 | M5: =L5 - K5 + 1 -> 193 | N5: =IFERROR(INDEX(Tabela3[ID_Responsavel], MATCH(O5,Tabela3[[Responsáveis ]], 0)), "Não encontrado") -> 7 | O5: Edimar Dias | P5: SESI
A6: =IFERROR(INDEX(Tabela2[ID_Area], MATCH(B6,Tabela2[Area], 0)), "Não encontrado") -> 1000 | B6: Meio Ambiente - Gerencial | C6: Regulatório | D6: =IFERROR(INDEX(Metas!$D$2:$D$104, MATCH(E6,Metas!$E$2:$E$104, 0)), "Não encontrado") -> 125 | E6: Atualizar base de APP (Vereda, Nascente e cursos hídricos) das propriedades. | F6: Mobilização da empresa | G6: =IF(I6=1,"Concluído", IF(TODAY()>L6,"Atrasado", IF(AND(I6=0,TODAY()<K6),"Não iniciado", "Em Andamento"))) -> Concluído | I6: 1 | J6: =IFERROR( M6 / SUMIFS($M:$M, $E:$E, $E6, $O:$O, $O6) * 120, 0 ) -> 19.606501 | K6: 45740 | L6: 45930 | M6: =L6 - K6 + 1 -> 191 | N6: =IFERROR(INDEX(Tabela3[ID_Responsavel], MATCH(O6,Tabela3[[Responsáveis ]], 0)), "Não encontrado") -> 7 | O6: Edimar Dias | P6: SESI
A7: =IFERROR(INDEX(Tabela2[ID_Area], MATCH(B7,Tabela2[Area], 0)), "Não encontrado") -> 1000 | B7: Meio Ambiente - Gerencial | C7: Regulatório | D7: =IFERROR(INDEX(Metas!$D$2:$D$104, MATCH(E7,Metas!$E$2:$E$104, 0)), "Não encontrado") -> 125 | E7: Atualizar base de APP (Vereda, Nascente e cursos hídricos) das propriedades. | F7: Realização do trabalho de campo | G7: =IF(I7=1,"Concluído", IF(TODAY()>L7,"Atrasado", IF(AND(I7=0,TODAY()<K7),"Não iniciado", "Em Andamento"))) -> Concluído | I7: 1 | J7: =IFERROR( M7 / SUMIFS($M:$M, $E:$E, $E7, $O:$O, $O7) * 120, 0 ) -> 16.73225 | K7: 45778 | L7: 45940 | M7: =L7 - K7 + 1 -> 163 | N7: =IFERROR(INDEX(Tabela3[ID_Responsavel], MATCH(O7,Tabela3[[Responsáveis ]], 0)), "Não encontrado") -> 7 | O7: Edimar Dias | P7: SESI
A8: =IFERROR(INDEX(Tabela2[ID_Area], MATCH(B8,Tabela2[Area], 0)), "Não encontrado") -> 1000 | B8: Meio Ambiente - Gerencial | C8: Regulatório | D8: =IFERROR(INDEX(Metas!$D$2:$D$104, MATCH(E8,Metas!$E$2:$E$104, 0)), "Não encontrado") -> 125 | E8: Atualizar base de APP (Vereda, Nascente e cursos hídricos) das propriedades. | F8: Entrega preliminar | G8: =IF(I8=1,"Concluído", IF(TODAY()>L8,"Atrasado", IF(AND(I8=0,TODAY()<K8),"Não iniciado", "Em Andamento"))) -> Concluído | I8: 1 | J8: =IFERROR( M8 / SUMIFS($M:$M, $E:$E, $E8, $O:$O, $O8) * 120, 0 ) -> 13.96065 | K8: 45846 | L8: 45981 | M8: =L8 - K8 + 1 -> 136 | N8: =IFERROR(INDEX(Tabela3[ID_Responsavel], MATCH(O8,Tabela3[[Responsáveis ]], 0)), "Não encontrado") -> 7 | O8: Edimar Dias | P8: SESI
A9: =IFERROR(INDEX(Tabela2[ID_Area], MATCH(B9,Tabela2[Area], 0)), "Não encontrado") -> 1000 | B9: Meio Ambiente - Gerencial | C9: Regulatório | D9: =IFERROR(INDEX(Metas!$D$2:$D$104, MATCH(E9,Metas!$E$2:$E$104, 0)), "Não encontrado") -> 125 | E9: Atualizar base de APP (Vereda, Nascente e cursos hídricos) das propriedades. | F9: Revisão da entrega | G9: =IF(I9=1,"Concluído", IF(TODAY()>L9,"Atrasado", IF(AND(I9=0,TODAY()<K9),"Não iniciado", "Em Andamento"))) -> Concluído | I9: 1 | J9: =IFERROR( M9 / SUMIFS($M:$M, $E:$E, $E9, $O:$O, $O9) * 120, 0 ) -> 12.934132 | K9: 45860 | L9: 45985 | M9: =L9 - K9 + 1 -> 126 | N9: =IFERROR(INDEX(Tabela3[ID_Responsavel], MATCH(O9,Tabela3[[Responsáveis ]], 0)), "Não encontrado") -> 7 | O9: Edimar Dias | P9: SESI
A10: =IFERROR(INDEX(Tabela2[ID_Area], MATCH(B10,Tabela2[Area], 0)), "Não encontrado") -> 1000 | B10: Meio Ambiente - Gerencial | C10: Regulatório | D10: =IFERROR(INDEX(Metas!$D$2:$D$104, MATCH(E10,Metas!$E$2:$E$104, 0)), "Não encontrado") -> 125 | E10: Atualizar base de APP (Vereda, Nascente e cursos hídricos) das propriedades. | F10: Entrega final da base atualizada | G10: =IF(I10=1,"Concluído", IF(TODAY()>L10,"Atrasado", IF(AND(I10=0,TODAY()<K10),"Não iniciado", "Em Andamento"))) -> Concluído | I10: 1 | J10: =IFERROR( M10 / SUMIFS($M:$M, $E:$E, $E10, $O:$O, $O10) * 120, 0 ) -> 12.523524 | K10: 45868 | L10: 45989 | M10: =L10 - K10 + 1 -> 122 | N10: =IFERROR(INDEX(Tabela3[ID_Responsavel], MATCH(O10,Tabela3[[Responsáveis ]], 0)), "Não encontrado") -> 7 | O10: Edimar Dias | P10: SESI
A11: =IFERROR(INDEX(Tabela2[ID_Area], MATCH(B11,Tabela2[Area], 0)), "Não encontrado") -> 1000 | B11: Meio Ambiente - Gerencial | C11: Regulatório | D11: =IFERROR(INDEX(Metas!$D$2:$D$104, MATCH(E11,Metas!$E$2:$E$104, 0)), "Não encontrado") -> 123 | E11: REGULARIZAÇÃO CAR - Atualização das informações e adequação das bases das propriedades inseridas na ADA SVPM conforme prioridade e disponibilidade de recurso. | F11: Diagnóstico das bases das propriedades incluindo atualização das APPs | G11: =IF(I11=1,"Concluído", IF(TODAY()>L11,"Atrasado", IF(AND(I11=0,TODAY()<K11),"Não iniciado", "Em Andamento"))) -> Concluído | I11: 1 | J11: =IFERROR( M11 / SUMIFS($M:$M, $E:$E, $E11, $O:$O, $O11) * 120, 0 ) -> 39.466667 | K11: 45847 | L11: 45994 | M11: =L11 - K11 + 1 -> 148 | N11: =IFERROR(INDEX(Tabela3[ID_Responsavel], MATCH(O11,Tabela3[[Responsáveis ]], 0)), "Não encontrado") -> 7 | O11: Edimar Dias | P11: SESI
A12: =IFERROR(INDEX(Tabela2[ID_Area], MATCH(B12,Tabela2[Area], 0)), "Não encontrado") -> 1000 | B12: Meio Ambiente - Gerencial | C12: Regulatório | D12: =IFERROR(INDEX(Metas!$D$2:$D$104, MATCH(E12,Metas!$E$2:$E$104, 0)), "Não encontrado") -> 123 | E12: REGULARIZAÇÃO CAR - Atualização das informações e adequação das bases das propriedades inseridas na ADA SVPM conforme prioridade e disponibilidade de recurso. | F12: Atualização da base | G12: =IF(I12=1,"Concluído", IF(TODAY()>L12,"Atrasado", IF(AND(I12=0,TODAY()<K12),"Não iniciado", "Em Andamento"))) -> Concluído | I12: 1 | J12: =IFERROR( M12 / SUMIFS($M:$M, $E:$E, $E12, $O:$O, $O12) * 120, 0 ) -> 26.133333 | K12: 45899 | L12: 45996 | M12: =L12 - K12 + 1 -> 98 | N12: =IFERROR(INDEX(Tabela3[ID_Responsavel], MATCH(O12,Tabela3[[Responsáveis ]], 0)), "Não encontrado") -> 7 | O12: Edimar Dias | P12: SESI
A13: =IFERROR(INDEX(Tabela2[ID_Area], MATCH(B13,Tabela2[Area], 0)), "Não encontrado") -> 1000 | B13: Meio Ambiente - Gerencial | C13: Regulatório | D13: =IFERROR(INDEX(Metas!$D$2:$D$104, MATCH(E13,Metas!$E$2:$E$104, 0)), "Não encontrado") -> 123 | E13: REGULARIZAÇÃO CAR - Atualização das informações e adequação das bases das propriedades inseridas na ADA SVPM conforme prioridade e disponibilidade de recurso. | F13: Reunião para apresentação da base atualizada para Gerencia de MA | G13: =IF(I13=1,"Concluído", IF(TODAY()>L13,"Atrasado", IF(AND(I13=0,TODAY()<K13),"Não iniciado", "Em Andamento"))) -> Concluído | I13: 1 | J13: =IFERROR( M13 / SUMIFS($M:$M, $E:$E, $E13, $O:$O, $O13) * 120, 0 ) -> 18.933333 | K13: 45931 | L13: 46001 | M13: =L13 - K13 + 1 -> 71 | N13: =IFERROR(INDEX(Tabela3[ID_Responsavel], MATCH(O13,Tabela3[[Responsáveis ]], 0)), "Não encontrado") -> 7 | O13: Edimar Dias | P13: SESI
A14: =IFERROR(INDEX(Tabela2[ID_Area], MATCH(B14,Tabela2[Area], 0)), "Não encontrado") -> 1000 | B14: Meio Ambiente - Gerencial | C14: Regulatório | D14: =IFERROR(INDEX(Metas!$D$2:$D$104, MATCH(E14,Metas!$E$2:$E$104, 0)), "Não encontrado") -> 123 | E14: REGULARIZAÇÃO CAR - Atualização das informações e adequação das bases das propriedades inseridas na ADA SVPM conforme prioridade e disponibilidade de recurso. | F14: Aprovação do jurídico | G14: =IF(I14=1,"Concluído", IF(TODAY()>L14,"Atrasado", IF(AND(I14=0,TODAY()<K14),"Não iniciado", "Em Andamento"))) -> Concluído | I14: 1 | J14: =IFERROR( M14 / SUMIFS($M:$M, $E:$E, $E14, $O:$O, $O14) * 120, 0 ) -> 16.533333 | K14: 45943 | L14: 46004 | M14: =L14 - K14 + 1 -> 62 | N14: =IFERROR(INDEX(Tabela3[ID_Responsavel], MATCH(O14,Tabela3[[Responsáveis ]], 0)), "Não encontrado") -> 7 | O14: Edimar Dias | P14: SESI
A15: =IFERROR(INDEX(Tabela2[ID_Area], MATCH(B15,Tabela2[Area], 0)), "Não encontrado") -> 1000 | B15: Meio Ambiente - Gerencial | C15: Regulatório | D15: =IFERROR(INDEX(Metas!$D$2:$D$104, MATCH(E15,Metas!$E$2:$E$104, 0)), "Não encontrado") -> 123 | E15: REGULARIZAÇÃO CAR - Atualização das informações e adequação das bases das propriedades inseridas na ADA SVPM conforme prioridade e disponibilidade de recurso. | F15: Atualização do CAR no SISCAR | G15: =IF(I15=1,"Concluído", IF(TODAY()>L15,"Atrasado", IF(AND(I15=0,TODAY()<K15),"Não iniciado", "Em Andamento"))) -> Concluído | I15: 1 | J15: =IFERROR( M15 / SUMIFS($M:$M, $E:$E, $E15, $O:$O, $O15) * 120, 0 ) -> 18.933333 | K15: 45951 | L15: 46021 | M15: =L15 - K15 + 1 -> 71 | N15: =IFERROR(INDEX(Tabela3[ID_Responsavel], MATCH(O15,Tabela3[[Responsáveis ]], 0)), "Não encontrado") -> 7 | O15: Edimar Dias | P15: SESI
... A23: =IFERROR(INDEX(Tabela2[ID_Area], MATCH(B23,Tabela2[Area], 0)), "Não encontrado") -> 1000 | B23: Meio Ambiente - Gerencial | C23: SGA | D23: =IFERROR(INDEX(Metas!$D$2:$D$104, MATCH(E23,Metas!$E$2:$E$104, 0)), "Não encontrado") -> 124 | E23: Desenvolver e Implementar do Indice de Maturidade e regras socioambientais | F23: Startar o IMA para as áreas | G23: =IF(I23=1,"Concluído", IF(TODAY()>L23,"Atrasado", IF(AND(I23=0,TODAY()<K23),"Não iniciado", "Em Andamento"))) -> Concluído | I23: 1 | J23: =IFERROR( M23 / SUMIFS($M:$M, $E:$E, $E23, $O:$O, $O23) * 120, 0 ) -> 21.311806 | K23: 45814 | L23: 45989 | M23: =L23 - K23 + 1 -> 176 | N23: =IFERROR(INDEX(Tabela3[ID_Responsavel], MATCH(O23,Tabela3[[Responsáveis ]], 0)), "Não encontrado") -> 7 | O23: Edimar Dias | P23: SESI
A24: =IFERROR(INDEX(Tabela2[ID_Area], MATCH(B24,Tabela2[Area], 0)), "Não encontrado") -> 1000 | B24: Meio Ambiente - Gerencial | C24: Projeto | D24: =IFERROR(INDEX(Metas!$D$2:$D$104, MATCH(E24,Metas!$E$2:$E$104, 0)), "Não encontrado") -> 126 | E24: Rehabilitation Projects Phase II | F24: Elaborar cronograma de acompanhamento do Rehabilitation projects phase II | G24: =IF(I24=1,"Concluído", IF(TODAY()>L24,"Atrasado", IF(AND(I24=0,TODAY()<K24),"Não iniciado", "Em Andamento"))) -> Concluído | I24: 1 | J24: =IFERROR( M24 / SUMIFS($M:$M, $E:$E, $E24, $O:$O, $O24) * 120, 0 ) -> 35.134228 | K24: 45663 | L24: 46011 | M24: =L24 - K24 + 1 -> 349 | N24: =IFERROR(INDEX(Tabela3[ID_Responsavel], MATCH(O24,Tabela3[[Responsáveis ]], 0)), "Não encontrado") -> 7 | O24: Edimar Dias | P24: SESI | Q24: Foi elaborado e apresentado a gerência de MA o levantamento sobre todos os projetos Rehabilitation projects phase II
A25: =IFERROR(INDEX(Tabela2[ID_Area], MATCH(B25,Tabela2[Area], 0)), "Não encontrado") -> 1000 | B25: Meio Ambiente - Gerencial | C25: Projeto | D25: =IFERROR(INDEX(Metas!$D$2:$D$104, MATCH(E25,Metas!$E$2:$E$104, 0)), "Não encontrado") -> 126 | E25: Rehabilitation Projects Phase II | F25: Realizar reunião com equipe aplicando Ciclo PDCA para avaliação das oportunidades de 2025 frente ao acompanhamento 2024 | G25: =IF(I25=1,"Concluído", IF(TODAY()>L25,"Atrasado", IF(AND(I25=0,TODAY()<K25),"Não iniciado", "Em Andamento"))) -> Concluído | I25: 1 | J25: =IFERROR( M25 / SUMIFS($M:$M, $E:$E, $E25, $O:$O, $O25) * 120, 0 ) -> 31.409396 | K25: 45708 | L25: 46019 | M25: =L25 - K25 + 1 -> 312 | N25: =IFERROR(INDEX(Tabela3[ID_Responsavel], MATCH(O25,Tabela3[[Responsáveis ]], 0)), "Não encontrado") -> 7 | O25: Edimar Dias | P25: SESI
A26: =IFERROR(INDEX(Tabela2[ID_Area], MATCH(B26,Tabela2[Area], 0)), "Não encontrado") -> 1000 | B26: Meio Ambiente - Gerencial | C26: Projeto | D26: =IFERROR(INDEX(Metas!$D$2:$D$104, MATCH(E26,Metas!$E$2:$E$104, 0)), "Não encontrado") -> 126 | E26: Rehabilitation Projects Phase II | F26: Elaborar modelo de acompanhamento do desenvolvimento do trabalho ao longo de 2025, de forma a integrar dados de turbidez, controles, reabilitação, pluviometria e consolida-los em informações para tomadas de decisão | G26: =IF(I26=1,"Concluído", IF(TODAY()>L26,"Atrasado", IF(AND(I26=0,TODAY()<K26),"Não iniciado", "Em Andamento"))) -> Concluído | I26: 1 | J26: =IFERROR( M26 / SUMIFS($M:$M, $E:$E, $E26, $O:$O, $O26) * 120, 0 ) -> 30.503356 | K26: 45717 | L26: 46019 | M26: =L26 - K26 + 1 -> 303 | N26: =IFERROR(INDEX(Tabela3[ID_Responsavel], MATCH(O26,Tabela3[[Responsáveis ]], 0)), "Não encontrado") -> 7 | O26: Edimar Dias | P26: SESI
A27: =IFERROR(INDEX(Tabela2[ID_Area], MATCH(B27,Tabela2[Area], 0)), "Não encontrado") -> 1000 | B27: Meio Ambiente - Gerencial | C27: Projeto | D27: =IFERROR(INDEX(Metas!$D$2:$D$104, MATCH(E27,Metas!$E$2:$E$104, 0)), "Não encontrado") -> 126 | E27: Rehabilitation Projects Phase II | F27: Elaborar mensalmente relatório estratégico com informações dos resultados do trabalho | G27: =IF(I27=1,"Concluído", IF(TODAY()>L27,"Atrasado", IF(AND(I27=0,TODAY()<K27),"Não iniciado", "Em Andamento"))) -> Concluído | I27: 1 | J27: =IFERROR( M27 / SUMIFS($M:$M, $E:$E, $E27, $O:$O, $O27) * 120, 0 ) -> 19.127517 | K27: 45741 | L27: 45930 | M27: =L27 - K27 + 1 -> 190 | N27: =IFERROR(INDEX(Tabela3[ID_Responsavel], MATCH(O27,Tabela3[[Responsáveis ]], 0)), "Não encontrado") -> 7 | O27: Edimar Dias | P27: SESI
A28: =IFERROR(INDEX(Tabela2[ID_Area], MATCH(B28,Tabela2[Area], 0)), "Não encontrado") -> 1000 | B28: Meio Ambiente - Gerencial | C28: Projeto | D28: =IFERROR(INDEX(Metas!$D$2:$D$104, MATCH(E28,Metas!$E$2:$E$104, 0)), "Não encontrado") -> 126 | E28: Rehabilitation Projects Phase II | F28: Apresentar resultados preliminares do trabalho realizado | G28: =IF(I28=1,"Concluído", IF(TODAY()>L28,"Atrasado", IF(AND(I28=0,TODAY()<K28),"Não iniciado", "Em Andamento"))) -> Concluído | I28: 1 | J28: =IFERROR( M28 / SUMIFS($M:$M, $E:$E, $E28, $O:$O, $O28) * 120, 0 ) -> 1.9127517 | K28: 45936 | L28: 45954 | M28: =L28 - K28 + 1 -> 19 | N28: =IFERROR(INDEX(Tabela3[ID_Responsavel], MATCH(O28,Tabela3[[Responsáveis ]], 0)), "Não encontrado") -> 7 | O28: Edimar Dias | P28: SESI
A29: =IFERROR(INDEX(Tabela2[ID_Area], MATCH(B29,Tabela2[Area], 0)), "Não encontrado") -> 1000 | B29: Meio Ambiente - Gerencial | C29: Projeto | D29: =IFERROR(INDEX(Metas!$D$2:$D$104, MATCH(E29,Metas!$E$2:$E$104, 0)), "Não encontrado") -> 126 | E29: Rehabilitation Projects Phase II | F29: Realizar reunião técnica com equipe envolvida nos trabalhos apresentando os resultados e lições aprendidas de 2025 e oportunidades 2026 | G29: =IF(I29=1,"Concluído", IF(TODAY()>L29,"Atrasado", IF(AND(I29=0,TODAY()<K29),"Não iniciado", "Em Andamento"))) -> Concluído | I29: 1 | J29: =IFERROR( M29 / SUMIFS($M:$M, $E:$E, $E29, $O:$O, $O29) * 120, 0 ) -> 1.9127517 | K29: 45992 | L29: 46010 | M29: =L29 - K29 + 1 -> 19 | N29: =IFERROR(INDEX(Tabela3[ID_Responsavel], MATCH(O29,Tabela3[[Responsáveis ]], 0)), "Não encontrado") -> 7 | O29: Edimar Dias | P29: SESI
A30: =IFERROR(INDEX(Tabela2[ID_Area], MATCH(B30,Tabela2[Area], 0)), "Não encontrado") -> 1000 | B30: Meio Ambiente - Gerencial | C30: Projeto | D30: =IFERROR(INDEX(Metas!$D$2:$D$104, MATCH(E30,Metas!$E$2:$E$104, 0)), "Não encontrado") -> 127 | E30: Elaborar Book ambiental dos projetos Flow Sheat | F30: Elaborar descrição dos itens que irão compor o Book Ambiental para acompanhamento e registro do desenvolvimento do Flow Sheat | G30: =IF(I30=1,"Concluído", IF(TODAY()>L30,"Atrasado", IF(AND(I30=0,TODAY()<K30),"Não iniciado", "Em Andamento"))) -> Atrasado | I30: 0.01 | J30: =IFERROR( M30 / SUMIFS($M:$M, $E:$E, $E30, $O:$O, $O30) * 120, 0 ) -> 54.086728 | K30: 45677 | L30: 46019 | M30: =L30 - K30 + 1 -> 343 | N30: =IFERROR(INDEX(Tabela3[ID_Responsavel], MATCH(O30,Tabela3[[Responsáveis ]], 0)), "Não encontrado") -> 7 | O30: Edimar Dias | P30: SESI
A31: =IFERROR(INDEX(Tabela2[ID_Area], MATCH(B31,Tabela2[Area], 0)), "Não encontrado") -> 1000 | B31: Meio Ambiente - Gerencial | C31: Projeto | D31: =IFERROR(INDEX(Metas!$D$2:$D$104, MATCH(E31,Metas!$E$2:$E$104, 0)), "Não encontrado") -> 127 | E31: Elaborar Book ambiental dos projetos Flow Sheat | F31: Elaborar cronograma em conjunto com Gerência e Estratégia para acompanhamento de projeto da parte estratégica e operacional | G31: =IF(I31=1,"Concluído", IF(TODAY()>L31,"Atrasado", IF(AND(I31=0,TODAY()<K31),"Não iniciado", "Em Andamento"))) -> Atrasado | I31: 0 | J31: =IFERROR( M31 / SUMIFS($M:$M, $E:$E, $E31, $O:$O, $O31) * 120, 0 ) -> 50.775296 | K31: 45698 | L31: 46019 | M31: =L31 - K31 + 1 -> 322 | N31: =IFERROR(INDEX(Tabela3[ID_Responsavel], MATCH(O31,Tabela3[[Responsáveis ]], 0)), "Não encontrado") -> 7 | O31: Edimar Dias | P31: SESI
A32: =IFERROR(INDEX(Tabela2[ID_Area], MATCH(B32,Tabela2[Area], 0)), "Não encontrado") -> 1000 | B32: Meio Ambiente - Gerencial | C32: Projeto | D32: =IFERROR(INDEX(Metas!$D$2:$D$104, MATCH(E32,Metas!$E$2:$E$104, 0)), "Não encontrado") -> 127 | E32: Elaborar Book ambiental dos projetos Flow Sheat | F32: Apresentar relatório final consolidando as informações referente ao acompanhamento Flow Sheat | G32: =IF(I32=1,"Concluído", IF(TODAY()>L32,"Atrasado", IF(AND(I32=0,TODAY()<K32),"Não iniciado", "Em Andamento"))) -> Atrasado | I32: 0 | J32: =IFERROR( M32 / SUMIFS($M:$M, $E:$E, $E32, $O:$O, $O32) * 120, 0 ) -> 7.7266754 | K32: 45964 | L32: 46012 | M32: =L32 - K32 + 1 -> 49 | N32: =IFERROR(INDEX(Tabela3[ID_Responsavel], MATCH(O32,Tabela3[[Responsáveis ]], 0)), "Não encontrado") -> 7 | O32: Edimar Dias | P32: SESI
A33: =IFERROR(INDEX(Tabela2[ID_Area], MATCH(B33,Tabela2[Area], 0)), "Não encontrado") -> 1000 | B33: Meio Ambiente - Gerencial | C33: Projeto | D33: =IFERROR(INDEX(Metas!$D$2:$D$104, MATCH(E33,Metas!$E$2:$E$104, 0)), "Não encontrado") -> 127 | E33: Elaborar Book ambiental dos projetos Flow Sheat | F33: Realizar Work Shopp técnico com equipe envolvida no projeto para apresentação e discussões abertas sobre as lições aprendidas | G33: =IF(I33=1,"Concluído", IF(TODAY()>L33,"Atrasado", IF(AND(I33=0,TODAY()<K33),"Não iniciado", "Em Andamento"))) -> Atrasado | I33: 0 | J33: =IFERROR( M33 / SUMIFS($M:$M, $E:$E, $E33, $O:$O, $O33) * 120, 0 ) -> 7.4113009 | K33: 45964 | L33: 46010 | M33: =L33 - K33 + 1 -> 47 | N33: =IFERROR(INDEX(Tabela3[ID_Responsavel], MATCH(O33,Tabela3[[Responsáveis ]], 0)), "Não encontrado") -> 7 | O33: Edimar Dias | P33: SESI
A34: =IFERROR(INDEX(Tabela2[ID_Area], MATCH(B34,Tabela2[Area], 0)), "Não encontrado") -> 1000 | B34: Meio Ambiente - Gerencial | C34: Projeto | D34: =IFERROR(INDEX(Metas!$D$2:$D$104, MATCH(E34,Metas!$E$2:$E$104, 0)), "Não encontrado") -> 128 | E34: Elaborar Book ambiental do Heap Laeth | F34: Elaborar descrição dos itens que irão compor o Book Ambiental para acompanhamento e registro do desenvolvimento do Flow Sheat | G34: =IF(I34=1,"Concluído", IF(TODAY()>L34,"Atrasado", IF(AND(I34=0,TODAY()<K34),"Não iniciado", "Em Andamento"))) -> Concluído | I34: 1 | J34: =IFERROR( M34 / SUMIFS($M:$M, $E:$E, $E34, $O:$O, $O34) * 120, 0 ) -> 56.30643 | K34: 45677 | L34: 46019 | M34: =L34 - K34 + 1 -> 343 | N34: =IFERROR(INDEX(Tabela3[ID_Responsavel], MATCH(O34,Tabela3[[Responsáveis ]], 0)), "Não encontrado") -> 7 | O34: Edimar Dias | P34: SESI
A35: =IFERROR(INDEX(Tabela2[ID_Area], MATCH(B35,Tabela2[Area], 0)), "Não encontrado") -> 1000 | B35: Meio Ambiente - Gerencial | C35: Projeto | D35: =IFERROR(INDEX(Metas!$D$2:$D$104, MATCH(E35,Metas!$E$2:$E$104, 0)), "Não encontrado") -> 128 | E35: Elaborar Book ambiental do Heap Laeth | F35: Elaborar cronograma em conjunto com Gerência e Estratégia para acompanhamento de projeto da parte estratégica e operacional | G35: =IF(I35=1,"Concluído", IF(TODAY()>L35,"Atrasado", IF(AND(I35=0,TODAY()<K35),"Não iniciado", "Em Andamento"))) -> Atrasado | I35: 0.5 | J35: =IFERROR( M35 / SUMIFS($M:$M, $E:$E, $E35, $O:$O, $O35) * 120, 0 ) -> 52.859097 | K35: 45698 | L35: 46019 | M35: =L35 - K35 + 1 -> 322 | N35: =IFERROR(INDEX(Tabela3[ID_Responsavel], MATCH(O35,Tabela3[[Responsáveis ]], 0)), "Não encontrado") -> 7 | O35: Edimar Dias | P35: SESI
A36: =IFERROR(INDEX(Tabela2[ID_Area], MATCH(B36,Tabela2[Area], 0)), "Não encontrado") -> 1000 | B36: Meio Ambiente - Gerencial | C36: Projeto | D36: =IFERROR(INDEX(Metas!$D$2:$D$104, MATCH(E36,Metas!$E$2:$E$104, 0)), "Não encontrado") -> 128 | E36: Elaborar Book ambiental do Heap Laeth | F36: Apresentar relatório final consolidando as informações referente ao acompanhamento Flow Sheat | G36: =IF(I36=1,"Concluído", IF(TODAY()>L36,"Atrasado", IF(AND(I36=0,TODAY()<K36),"Não iniciado", "Em Andamento"))) -> Atrasado | I36: 0 | J36: =IFERROR( M36 / SUMIFS($M:$M, $E:$E, $E36, $O:$O, $O36) * 120, 0 ) -> 3.119015 | K36: 45964 | L36: 45982 | M36: =L36 - K36 + 1 -> 19 | N36: =IFERROR(INDEX(Tabela3[ID_Responsavel], MATCH(O36,Tabela3[[Responsáveis ]], 0)), "Não encontrado") -> 7 | O36: Edimar Dias | P36: SESI
A37: =IFERROR(INDEX(Tabela2[ID_Area], MATCH(B37,Tabela2[Area], 0)), "Não encontrado") -> 1000 | B37: Meio Ambiente - Gerencial | C37: Projeto | D37: =IFERROR(INDEX(Metas!$D$2:$D$104, MATCH(E37,Metas!$E$2:$E$104, 0)), "Não encontrado") -> 128 | E37: Elaborar Book ambiental do Heap Laeth | F37: Realizar Work Shopp técnico com equipe envolvida no projeto para apresentação e discussões abertas sobre as lições aprendidas | G37: =IF(I37=1,"Concluído", IF(TODAY()>L37,"Atrasado", IF(AND(I37=0,TODAY()<K37),"Não iniciado", "Em Andamento"))) -> Atrasado | I37: 0 | J37: =IFERROR( M37 / SUMIFS($M:$M, $E:$E, $E37, $O:$O, $O37) * 120, 0 ) -> 7.7154583 | K37: 45964 | L37: 46010 | M37: =L37 - K37 + 1 -> 47 | N37: =IFERROR(INDEX(Tabela3[ID_Responsavel], MATCH(O37,Tabela3[[Responsáveis ]], 0)), "Não encontrado") -> 7 | O37: Edimar Dias | P37: SESI
A38: =IFERROR(INDEX(Tabela2[ID_Area], MATCH(B38,Tabela2[Area], 0)), "Não encontrado") -> 1000 | B38: Meio Ambiente - Gerencial | C38: P&D | D38: =IFERROR(INDEX(Metas!$D$2:$D$104, MATCH(E38,Metas!$E$2:$E$104, 0)), "Não encontrado") -> 121 | E38: SULFATO DE AMÔNIO - Continuidade dos Estudos de Avaliação de Impactos e Ganhos Potenciais com inclusão do reagente S.A. | F38: Elaboração de escopo com envio para suprimentos | G38: =IF(I38=1,"Concluído", IF(TODAY()>L38,"Atrasado", IF(AND(I38=0,TODAY()<K38),"Não iniciado", "Em Andamento"))) -> Concluído | H38: 45695 | I38: 1 | J38: =IFERROR( M38 / SUMIFS($M:$M, $E:$E, $E38, $O:$O, $O38) * 120, 0 ) -> 1.4302191 | K38: 45658 | L38: 45688 | M38: =L38 - K38 + 1 -> 31 | N38: =IFERROR(INDEX(Tabela3[ID_Responsavel], MATCH(O38,Tabela3[[Responsáveis ]], 0)), "Não encontrado") -> 7 | O38: Edimar Dias | P38: SVPM | Q38: E-mail enviado para equipe técnica contribuir e na sequência enviado para validação de contrato.
A39: =IFERROR(INDEX(Tabela2[ID_Area], MATCH(B39,Tabela2[Area], 0)), "Não encontrado") -> 1000 | B39: Meio Ambiente - Gerencial | C39: P&D | D39: =IFERROR(INDEX(Metas!$D$2:$D$104, MATCH(E39,Metas!$E$2:$E$104, 0)), "Não encontrado") -> 121 | E39: SULFATO DE AMÔNIO - Continuidade dos Estudos de Avaliação de Impactos e Ganhos Potenciais com inclusão do reagente S.A. | F39: Contratar Consultoria | G39: =IF(I39=1,"Concluído", IF(TODAY()>L39,"Atrasado", IF(AND(I39=0,TODAY()<K39),"Não iniciado", "Em Andamento"))) -> Concluído | I39: 1 | J39: =IFERROR( M39 / SUMIFS($M:$M, $E:$E, $E39, $O:$O, $O39) * 120, 0 ) -> 15.27105 | K39: 45689 | L39: 46019 | M39: =L39 - K39 + 1 -> 331 | N39: =IFERROR(INDEX(Tabela3[ID_Responsavel], MATCH(O39,Tabela3[[Responsáveis ]], 0)), "Não encontrado") -> 7 | O39: Edimar Dias | P39: SVPM
A40: =IFERROR(INDEX(Tabela2[ID_Area], MATCH(B40,Tabela2[Area], 0)), "Não encontrado") -> 1000 | B40: Meio Ambiente - Gerencial | C40: P&D | D40: =IFERROR(INDEX(Metas!$D$2:$D$104, MATCH(E40,Metas!$E$2:$E$104, 0)), "Não encontrado") -> 121 | E40: SULFATO DE AMÔNIO - Continuidade dos Estudos de Avaliação de Impactos e Ganhos Potenciais com inclusão do reagente S.A. | F40: Reunião de Kick off com empresa | G40: =IF(I40=1,"Concluído", IF(TODAY()>L40,"Atrasado", IF(AND(I40=0,TODAY()<K40),"Não iniciado", "Em Andamento"))) -> Concluído | I40: 1 | J40: =IFERROR( M40 / SUMIFS($M:$M, $E:$E, $E40, $O:$O, $O40) * 120, 0 ) -> 13.979239 | K40: 45717 | L40: 46019 | M40: =L40 - K40 + 1 -> 303 | N40: =IFERROR(INDEX(Tabela3[ID_Responsavel], MATCH(O40,Tabela3[[Responsáveis ]], 0)), "Não encontrado") -> 7 | O40: Edimar Dias | P40: SVPM
A41: =IFERROR(INDEX(Tabela2[ID_Area], MATCH(B41,Tabela2[Area], 0)), "Não encontrado") -> 1000 | B41: Meio Ambiente - Gerencial | C41: P&D | D41: =IFERROR(INDEX(Metas!$D$2:$D$104, MATCH(E41,Metas!$E$2:$E$104, 0)), "Não encontrado") -> 121 | E41: SULFATO DE AMÔNIO - Continuidade dos Estudos de Avaliação de Impactos e Ganhos Potenciais com inclusão do reagente S.A. | F41: Desenvolver estudos conforme etapas e cronograma do projeto | G41: =IF(I41=1,"Concluído", IF(TODAY()>L41,"Atrasado", IF(AND(I41=0,TODAY()<K41),"Não iniciado", "Em Andamento"))) -> Concluído | I41: 1 | J41: =IFERROR( M41 / SUMIFS($M:$M, $E:$E, $E41, $O:$O, $O41) * 120, 0 ) -> 28.8812 | K41: 45731 | L41: 46356 | M41: =L41 - K41 + 1 -> 626 | N41: =IFERROR(INDEX(Tabela3[ID_Responsavel], MATCH(O41,Tabela3[[Responsáveis ]], 0)), "Não encontrado") -> 7 | O41: Edimar Dias | P41: SVPM
A42: =IFERROR(INDEX(Tabela2[ID_Area], MATCH(B42,Tabela2[Area], 0)), "Não encontrado") -> 1000 | B42: Meio Ambiente - Gerencial | C42: P&D | D42: =IFERROR(INDEX(Metas!$D$2:$D$104, MATCH(E42,Metas!$E$2:$E$104, 0)), "Não encontrado") -> 121 | E42: SULFATO DE AMÔNIO - Continuidade dos Estudos de Avaliação de Impactos e Ganhos Potenciais com inclusão do reagente S.A. | F42: Entrega da primeira versão do Relatório Preliminar | G42: =IF(I42=1,"Concluído", IF(TODAY()>L42,"Atrasado", IF(AND(I42=0,TODAY()<K42),"Não iniciado", "Em Andamento"))) -> Concluído | I42: 1 | J42: =IFERROR( M42 / SUMIFS($M:$M, $E:$E, $E42, $O:$O, $O42) * 120, 0 ) -> 20.346021 | K42: 45931 | L42: 46371 | M42: =L42 - K42 + 1 -> 441 | N42: =IFERROR(INDEX(Tabela3[ID_Responsavel], MATCH(O42,Tabela3[[Responsáveis ]], 0)), "Não encontrado") -> 7 | O42: Edimar Dias | P42: SVPM
A43: =IFERROR(INDEX(Tabela2[ID_Area], MATCH(B43,Tabela2[Area], 0)), "Não encontrado") -> 1000 | B43: Meio Ambiente - Gerencial | C43: P&D | D43: =IFERROR(INDEX(Metas!$D$2:$D$104, MATCH(E43,Metas!$E$2:$E$104, 0)), "Não encontrado") -> 121 | E43: SULFATO DE AMÔNIO - Continuidade dos Estudos de Avaliação de Impactos e Ganhos Potenciais com inclusão do reagente S.A. | F43: Revisar Relatório | G43: =IF(I43=1,"Concluído", IF(TODAY()>L43,"Atrasado", IF(AND(I43=0,TODAY()<K43),"Não iniciado", "Em Andamento"))) -> Concluído | I43: 1 | J43: =IFERROR( M43 / SUMIFS($M:$M, $E:$E, $E43, $O:$O, $O43) * 120, 0 ) -> 20.161476 | K43: 45937 | L43: 46373 | M43: =L43 - K43 + 1 -> 437 | N43: =IFERROR(INDEX(Tabela3[ID_Responsavel], MATCH(O43,Tabela3[[Responsáveis ]], 0)), "Não encontrado") -> 7 | O43: Edimar Dias | P43: SVPM
A44: =IFERROR(INDEX(Tabela2[ID_Area], MATCH(B44,Tabela2[Area], 0)), "Não encontrado") -> 1000 | B44: Meio Ambiente - Gerencial | C44: P&D | D44: =IFERROR(INDEX(Metas!$D$2:$D$104, MATCH(E44,Metas!$E$2:$E$104, 0)), "Não encontrado") -> 121 | E44: SULFATO DE AMÔNIO - Continuidade dos Estudos de Avaliação de Impactos e Ganhos Potenciais com inclusão do reagente S.A. | F44: Apresentação Resultados Preliminares | G44: =IF(I44=1,"Concluído", IF(TODAY()>L44,"Atrasado", IF(AND(I44=0,TODAY()<K44),"Não iniciado", "Em Andamento"))) -> Concluído | I44: 1 | J44: =IFERROR( M44 / SUMIFS($M:$M, $E:$E, $E44, $O:$O, $O44) * 120, 0 ) -> 19.930796 | K44: 45945 | L44: 46376 | M44: =L44 - K44 + 1 -> 432 | N44: =IFERROR(INDEX(Tabela3[ID_Responsavel], MATCH(O44,Tabela3[[Responsáveis ]], 0)), "Não encontrado") -> 7 | O44: Edimar Dias | P44: SVPM
A45: =IFERROR(INDEX(Tabela2[ID_Area], MATCH(B45,Tabela2[Area], 0)), "Não encontrado") -> 1000 | B45: Meio Ambiente - Gerencial | C45: P&D | D45: =IFERROR(INDEX(Metas!$D$2:$D$104, MATCH(E45,Metas!$E$2:$E$104, 0)), "Não encontrado") -> 122 | E45: TRATABILIDADE EFLUENTES E REJEITOS - Continuidade dos Estudos de Tratabilidade de Efluentes (Salinidade ). | F45: Elaboração de escopo com envio para suprimentos | G45: =IF(I45=1,"Concluído", IF(TODAY()>L45,"Atrasado", IF(AND(I45=0,TODAY()<K45),"Não iniciado", "Em Andamento"))) -> Concluído | I45: 1 | J45: =IFERROR( M45 / SUMIFS($M:$M, $E:$E, $E45, $O:$O, $O45) * 120, 0 ) -> 15.978261 | K45: 45658 | L45: 45853 | M45: =L45 - K45 + 1 -> 196 | N45: =IFERROR(INDEX(Tabela3[ID_Responsavel], MATCH(O45,Tabela3[[Responsáveis ]], 0)), "Não encontrado") -> 7 | O45: Edimar Dias | P45: SVPM | Q45: Escopo em fase de revisão/conclusão. Ajuste para novo modelo MD enviado pela Gerência de Contratos
A46: =IFERROR(INDEX(Tabela2[ID_Area], MATCH(B46,Tabela2[Area], 0)), "Não encontrado") -> 1000 | B46: Meio Ambiente - Gerencial | C46: P&D | D46: =IFERROR(INDEX(Metas!$D$2:$D$104, MATCH(E46,Metas!$E$2:$E$104, 0)), "Não encontrado") -> 122 | E46: TRATABILIDADE EFLUENTES E REJEITOS - Continuidade dos Estudos de Tratabilidade de Efluentes (Salinidade ). | F46: Contratar Consultoria | G46: =IF(I46=1,"Concluído", IF(TODAY()>L46,"Atrasado", IF(AND(I46=0,TODAY()<K46),"Não iniciado", "Em Andamento"))) -> Concluído | I46: 1 | J46: =IFERROR( M46 / SUMIFS($M:$M, $E:$E, $E46, $O:$O, $O46) * 120, 0 ) -> 26.983696 | K46: 45689 | L46: 46019 | M46: =L46 - K46 + 1 -> 331 | N46: =IFERROR(INDEX(Tabela3[ID_Responsavel], MATCH(O46,Tabela3[[Responsáveis ]], 0)), "Não encontrado") -> 7 | O46: Edimar Dias | P46: SVPM
A47: =IFERROR(INDEX(Tabela2[ID_Area], MATCH(B47,Tabela2[Area], 0)), "Não encontrado") -> 1000 | B47: Meio Ambiente - Gerencial | C47: P&D | D47: =IFERROR(INDEX(Metas!$D$2:$D$104, MATCH(E47,Metas!$E$2:$E$104, 0)), "Não encontrado") -> 122 | E47: TRATABILIDADE EFLUENTES E REJEITOS - Continuidade dos Estudos de Tratabilidade de Efluentes (Salinidade ). | F47: Reunião de Kick off com empresa | G47: =IF(I47=1,"Concluído", IF(TODAY()>L47,"Atrasado", IF(AND(I47=0,TODAY()<K47),"Não iniciado", "Em Andamento"))) -> Concluído | I47: 1 | J47: =IFERROR( M47 / SUMIFS($M:$M, $E:$E, $E47, $O:$O, $O47) * 120, 0 ) -> 24.701087 | K47: 45717 | L47: 46019 | M47: =L47 - K47 + 1 -> 303 | N47: =IFERROR(INDEX(Tabela3[ID_Responsavel], MATCH(O47,Tabela3[[Responsáveis ]], 0)), "Não encontrado") -> 7 | O47: Edimar Dias | P47: SVPM
A48: =IFERROR(INDEX(Tabela2[ID_Area], MATCH(B48,Tabela2[Area], 0)), "Não encontrado") -> 1000 | B48: Meio Ambiente - Gerencial | C48: P&D | D48: =IFERROR(INDEX(Metas!$D$2:$D$104, MATCH(E48,Metas!$E$2:$E$104, 0)), "Não encontrado") -> 122 | E48: TRATABILIDADE EFLUENTES E REJEITOS - Continuidade dos Estudos de Tratabilidade de Efluentes (Salinidade ). | F48: Desenvolver estudos conforme etapas e cronograma do projeto | G48: =IF(I48=1,"Concluído", IF(TODAY()>L48,"Atrasado", IF(AND(I48=0,TODAY()<K48),"Não iniciado", "Em Andamento"))) -> Concluído | I48: 1 | J48: =IFERROR( M48 / SUMIFS($M:$M, $E:$E, $E48, $O:$O, $O48) * 120, 0 ) -> 26.413043 | K48: 45731 | L48: 46054 | M48: =L48 - K48 + 1 -> 324 | N48: =IFERROR(INDEX(Tabela3[ID_Responsavel], MATCH(O48,Tabela3[[Responsáveis ]], 0)), "Não encontrado") -> 7 | O48: Edimar Dias | P48: SVPM
A49: =IFERROR(INDEX(Tabela2[ID_Area], MATCH(B49,Tabela2[Area], 0)), "Não encontrado") -> 1000 | B49: Meio Ambiente - Gerencial | C49: P&D | D49: =IFERROR(INDEX(Metas!$D$2:$D$104, MATCH(E49,Metas!$E$2:$E$104, 0)), "Não encontrado") -> 122 | E49: TRATABILIDADE EFLUENTES E REJEITOS - Continuidade dos Estudos de Tratabilidade de Efluentes (Salinidade ). | F49: Entrega da primeira versão do Relatório Preliminar | G49: =IF(I49=1,"Concluído", IF(TODAY()>L49,"Atrasado", IF(AND(I49=0,TODAY()<K49),"Não iniciado", "Em Andamento"))) -> Concluído | I49: 1 | J49: =IFERROR( M49 / SUMIFS($M:$M, $E:$E, $E49, $O:$O, $O49) * 120, 0 ) -> 10.923913 | K49: 45940 | L49: 46073 | M49: =L49 - K49 + 1 -> 134 | N49: =IFERROR(INDEX(Tabela3[ID_Responsavel], MATCH(O49,Tabela3[[Responsáveis ]], 0)), "Não encontrado") -> 7 | O49: Edimar Dias | P49: SVPM
A50: =IFERROR(INDEX(Tabela2[ID_Area], MATCH(B50,Tabela2[Area], 0)), "Não encontrado") -> 1000 | B50: Meio Ambiente - Gerencial | C50: P&D | D50: =IFERROR(INDEX(Metas!$D$2:$D$104, MATCH(E50,Metas!$E$2:$E$104, 0)), "Não encontrado") -> 122 | E50: TRATABILIDADE EFLUENTES E REJEITOS - Continuidade dos Estudos de Tratabilidade de Efluentes (Salinidade ). | F50: Revisar Relatório Final | G50: =IF(I50=1,"Concluído", IF(TODAY()>L50,"Atrasado", IF(AND(I50=0,TODAY()<K50),"Não iniciado", "Em Andamento"))) -> Concluído | I50: 1 | J50: =IFERROR( M50 / SUMIFS($M:$M, $E:$E, $E50, $O:$O, $O50) * 120, 0 ) -> 4.4021739 | K50: 45950 | L50: 46003 | M50: =L50 - K50 + 1 -> 54 | N50: =IFERROR(INDEX(Tabela3[ID_Responsavel], MATCH(O50,Tabela3[[Responsáveis ]], 0)), "Não encontrado") -> 7 | O50: Edimar Dias | P50: SVPM
A51: =IFERROR(INDEX(Tabela2[ID_Area], MATCH(B51,Tabela2[Area], 0)), "Não encontrado") -> 1000 | B51: Meio Ambiente - Gerencial | C51: P&D | D51: =IFERROR(INDEX(Metas!$D$2:$D$104, MATCH(E51,Metas!$E$2:$E$104, 0)), "Não encontrado") -> 122 | E51: TRATABILIDADE EFLUENTES E REJEITOS - Continuidade dos Estudos de Tratabilidade de Efluentes (Salinidade ). | F51: Apresentação Resultados Preliminares | G51: =IF(I51=1,"Concluído", IF(TODAY()>L51,"Atrasado", IF(AND(I51=0,TODAY()<K51),"Não iniciado", "Em Andamento"))) -> Concluído | I51: 1 | J51: =IFERROR( M51 / SUMIFS($M:$M, $E:$E, $E51, $O:$O, $O51) * 120, 0 ) -> 10.597826 | K51: 45962 | L51: 46091 | M51: =L51 - K51 + 1 -> 130 | N51: =IFERROR(INDEX(Tabela3[ID_Responsavel], MATCH(O51,Tabela3[[Responsáveis ]], 0)), "Não encontrado") -> 7 | O51: Edimar Dias | P51: SVPM
A52: =IFERROR(INDEX(Tabela2[ID_Area], MATCH(B52,Tabela2[Area], 0)), "Não encontrado") -> 1001 | B52: Meio Ambiente - Operação | C52: Controle Ambiental | D52: =IFERROR(INDEX(Metas!$D$2:$D$104, MATCH(E52,Metas!$E$2:$E$104, 0)), "Não encontrado") -> 129 | E52: Elaborar o Plano Diretor de PRAD do empreendimento, estabelecendo diretrizes e ações para o gerenciamento de águas superficiais, controle de processos erosivos, aplicação de técnicas de bioengenharia e revegetação de taludes nas áreas da SVPM. | F52: Definir as diretrizes para a recuperação das áreas degradadas no contexto do empreendimento da Serra Verde Pesquisa e Mineração. | G52: =IF(I52=1,"Concluído", IF(TODAY()>L52,"Atrasado", IF(AND(I52=0,TODAY()<K52),"Não iniciado", "Em Andamento"))) -> Concluído | H52: 45782 | I52: 1 | J52: =IFERROR( M52 / SUMIFS($M:$M, $E:$E, $E52, $O:$O, $O52) * 120, 0 ) -> 25.217391 | K52: 45659 | L52: 45716 | M52: =L52 - K52 + 1 -> 58 | N52: =IFERROR(INDEX(Tabela3[ID_Responsavel], MATCH(O52,Tabela3[[Responsáveis ]], 0)), "Não encontrado") -> 1 | O52: Alan Boni | P52: SVPM | Q52: Plano diretor PD-PRAD aprovado e concluido.
A53: =IFERROR(INDEX(Tabela2[ID_Area], MATCH(B53,Tabela2[Area], 0)), "Não encontrado") -> 1001 | B53: Meio Ambiente - Operação | C53: Controle Ambiental | D53: =IFERROR(INDEX(Metas!$D$2:$D$104, MATCH(E53,Metas!$E$2:$E$104, 0)), "Não encontrado") -> 129 | E53: Elaborar o Plano Diretor de PRAD do empreendimento, estabelecendo diretrizes e ações para o gerenciamento de águas superficiais, controle de processos erosivos, aplicação de técnicas de bioengenharia e revegetação de taludes nas áreas da SVPM. | F53: Entrega do Plano Diretor de PRAD | G53: =IF(I53=1,"Concluído", IF(TODAY()>L53,"Atrasado", IF(AND(I53=0,TODAY()<K53),"Não iniciado", "Em Andamento"))) -> Concluído | H53: 45930 | I53: 1 | J53: =IFERROR( M53 / SUMIFS($M:$M, $E:$E, $E53, $O:$O, $O53) * 120, 0 ) -> 66.956522 | K53: 45716 | L53: 45869 | M53: =L53 - K53 + 1 -> 154 | N53: =IFERROR(INDEX(Tabela3[ID_Responsavel], MATCH(O53,Tabela3[[Responsáveis ]], 0)), "Não encontrado") -> 1 | O53: Alan Boni | P53: SVPM | Q53: Plano diretor PD-PRAD aprovado e concluido.
A54: =IFERROR(INDEX(Tabela2[ID_Area], MATCH(B54,Tabela2[Area], 0)), "Não encontrado") -> 1001 | B54: Meio Ambiente - Operação | C54: Controle Ambiental | D54: =IFERROR(INDEX(Metas!$D$2:$D$104, MATCH(E54,Metas!$E$2:$E$104, 0)), "Não encontrado") -> 129 | E54: Elaborar o Plano Diretor de PRAD do empreendimento, estabelecendo diretrizes e ações para o gerenciamento de águas superficiais, controle de processos erosivos, aplicação de técnicas de bioengenharia e revegetação de taludes nas áreas da SVPM. | F54: Realização do Workshop | G54: =IF(I54=1,"Concluído", IF(TODAY()>L54,"Atrasado", IF(AND(I54=0,TODAY()<K54),"Não iniciado", "Em Andamento"))) -> Atrasado | H54: 45937 | I54: 0.9 | J54: =IFERROR( M54 / SUMIFS($M:$M, $E:$E, $E54, $O:$O, $O54) * 120, 0 ) -> 13.913043 | K54: 45930 | L54: 45961 | M54: =L54 - K54 + 1 -> 32 | N54: =IFERROR(INDEX(Tabela3[ID_Responsavel], MATCH(O54,Tabela3[[Responsáveis ]], 0)), "Não encontrado") -> 1 | O54: Alan Boni | P54: SVPM | Q54: Workshop pronto,material apresentado a gerencia e diretoria. Contudo foi cancelado por estratégia da Gerência.
A55: =IFERROR(INDEX(Tabela2[ID_Area], MATCH(B55,Tabela2[Area], 0)), "Não encontrado") -> 1001 | B55: Meio Ambiente - Operação | C55: Controle Ambiental | D55: =IFERROR(INDEX(Metas!$D$2:$D$104, MATCH(E55,Metas!$E$2:$E$104, 0)), "Não encontrado") -> 129 | E55: Elaborar o Plano Diretor de PRAD do empreendimento, estabelecendo diretrizes e ações para o gerenciamento de águas superficiais, controle de processos erosivos, aplicação de técnicas de bioengenharia e revegetação de taludes nas áreas da SVPM. | F55: Realizar a entrega dos procedimentos derivados do Plano Diretor de PRAD | G55: =IF(I55=1,"Concluído", IF(TODAY()>L55,"Atrasado", IF(AND(I55=0,TODAY()<K55),"Não iniciado", "Em Andamento"))) -> Atrasado | I55: 0.5 | J55: =IFERROR( M55 / SUMIFS($M:$M, $E:$E, $E55, $O:$O, $O55) * 120, 0 ) -> 13.913043 | K55: 45930 | L55: 45961 | M55: =L55 - K55 + 1 -> 32 | N55: =IFERROR(INDEX(Tabela3[ID_Responsavel], MATCH(O55,Tabela3[[Responsáveis ]], 0)), "Não encontrado") -> 1 | O55: Alan Boni | P55: SVPM | Q55: Publicado PM Driver: Plantio de Mudas Nativas para Recuperação de Áreas Degradadas , Hidrossemeadura e Bioengenharia para Recuperação de Áreas Degradadas. Elaborado Procedimento Uso e controle de espécies vegetais exóticas em projetos da SVPM e Controle Químico de Plantas Daninhas a ser aprovado no PM Driver.
A56: =IFERROR(INDEX(Tabela2[ID_Area], MATCH(B56,Tabela2[Area], 0)), "Não encontrado") -> 1001 | B56: Meio Ambiente - Operação | C56: Controle Ambiental | D56: =IFERROR(INDEX(Metas!$D$2:$D$104, MATCH(E56,Metas!$E$2:$E$104, 0)), "Não encontrado") -> 130 | E56: Desenvolvimento de protocolo de monitoramento para conclusão de áreas de PRAD da Serra Verde | F56: Levantar dados de campo e levantamento Bibliográfico | G56: =IF(I56=1,"Concluído", IF(TODAY()>L56,"Atrasado", IF(AND(I56=0,TODAY()<K56),"Não iniciado", "Em Andamento"))) -> Concluído | H56: 45791 | I56: 1 | J56: =IFERROR( M56 / SUMIFS($M:$M, $E:$E, $E56, $O:$O, $O56) * 120, 0 ) -> 27.256098 | K56: 45659 | L56: 45807 | M56: =L56 - K56 + 1 -> 149 | N56: =IFERROR(INDEX(Tabela3[ID_Responsavel], MATCH(O56,Tabela3[[Responsáveis ]], 0)), "Não encontrado") -> 1 | O56: Alan Boni | P56: SVPM | Q56: Realizado levantamento bibliográfico e orientação para coleta de dados de campo do PRAD Piloto
A57: =IFERROR(INDEX(Tabela2[ID_Area], MATCH(B57,Tabela2[Area], 0)), "Não encontrado") -> 1001 | B57: Meio Ambiente - Operação | C57: Controle Ambiental | D57: =IFERROR(INDEX(Metas!$D$2:$D$104, MATCH(E57,Metas!$E$2:$E$104, 0)), "Não encontrado") -> 130 | E57: Desenvolvimento de protocolo de monitoramento para conclusão de áreas de PRAD da Serra Verde | F57: Realizar a entrega do documento inicial do protocolo de monitoramento | G57: =IF(I57=1,"Concluído", IF(TODAY()>L57,"Atrasado", IF(AND(I57=0,TODAY()<K57),"Não iniciado", "Em Andamento"))) -> Concluído | H57: 45798 | I57: 1 | J57: =IFERROR( M57 / SUMIFS($M:$M, $E:$E, $E57, $O:$O, $O57) * 120, 0 ) -> 16.829268 | K57: 45716 | L57: 45807 | M57: =L57 - K57 + 1 -> 92 | N57: =IFERROR(INDEX(Tabela3[ID_Responsavel], MATCH(O57,Tabela3[[Responsáveis ]], 0)), "Não encontrado") -> 1 | O57: Alan Boni | P57: SVPM
A58: =IFERROR(INDEX(Tabela2[ID_Area], MATCH(B58,Tabela2[Area], 0)), "Não encontrado") -> 1001 | B58: Meio Ambiente - Operação | C58: Controle Ambiental | D58: =IFERROR(INDEX(Metas!$D$2:$D$104, MATCH(E58,Metas!$E$2:$E$104, 0)), "Não encontrado") -> 130 | E58: Desenvolvimento de protocolo de monitoramento para conclusão de áreas de PRAD da Serra Verde | F58: Realizar capacitação técnica da equipe executora das atividades de PRAD | G58: =IF(I58=1,"Concluído", IF(TODAY()>L58,"Atrasado", IF(AND(I58=0,TODAY()<K58),"Não iniciado", "Em Andamento"))) -> Concluído | H58: 45818 | I58: 1 | J58: =IFERROR( M58 / SUMIFS($M:$M, $E:$E, $E58, $O:$O, $O58) * 120, 0 ) -> 39.329268 | K58: 45777 | L58: 45991 | M58: =L58 - K58 + 1 -> 215 | N58: =IFERROR(INDEX(Tabela3[ID_Responsavel], MATCH(O58,Tabela3[[Responsáveis ]], 0)), "Não encontrado") -> 1 | O58: Alan Boni | P58: SVPM
A59: =IFERROR(INDEX(Tabela2[ID_Area], MATCH(B59,Tabela2[Area], 0)), "Não encontrado") -> 1001 | B59: Meio Ambiente - Operação | C59: Controle Ambiental | D59: =IFERROR(INDEX(Metas!$D$2:$D$104, MATCH(E59,Metas!$E$2:$E$104, 0)), "Não encontrado") -> 130 | E59: Desenvolvimento de protocolo de monitoramento para conclusão de áreas de PRAD da Serra Verde | F59: Entrega Final do Protocolo de Monitoramento | G59: =IF(I59=1,"Concluído", IF(TODAY()>L59,"Atrasado", IF(AND(I59=0,TODAY()<K59),"Não iniciado", "Em Andamento"))) -> Concluído | H59: 45964 | I59: 1 | J59: =IFERROR( M59 / SUMIFS($M:$M, $E:$E, $E59, $O:$O, $O59) * 120, 0 ) -> 36.585366 | K59: 45792 | L59: 45991 | M59: =L59 - K59 + 1 -> 200 | N59: =IFERROR(INDEX(Tabela3[ID_Responsavel], MATCH(O59,Tabela3[[Responsáveis ]], 0)), "Não encontrado") -> 1 | O59: Alan Boni | P59: SVPM
A60: =IFERROR(INDEX(Tabela2[ID_Area], MATCH(B60,Tabela2[Area], 0)), "Não encontrado") -> 1001 | B60: Meio Ambiente - Operação | C60: Controle Ambiental | D60: =IFERROR(INDEX(Metas!$D$2:$D$104, MATCH(E60,Metas!$E$2:$E$104, 0)), "Não encontrado") -> 131 | E60: Elaborar o Plano Diretor de Controles Ambientais do empreendimento | F60: Definir as diretrizes para Plano Diretor de Controles Ambientais no contexto do empreendimento da Serra Verde Pesquisa e Mineração. | G60: =IF(I60=1,"Concluído", IF(TODAY()>L60,"Atrasado", IF(AND(I60=0,TODAY()<K60),"Não iniciado", "Em Andamento"))) -> Concluído | H60: 45930 | I60: 1 | J60: =IFERROR( M60 / SUMIFS($M:$M, $E:$E, $E60, $O:$O, $O60) * 120, 0 ) -> 71.523179 | K60: 45659 | L60: 45838 | M60: =L60 - K60 + 1 -> 180 | N60: =IFERROR(INDEX(Tabela3[ID_Responsavel], MATCH(O60,Tabela3[[Responsáveis ]], 0)), "Não encontrado") -> 1 | O60: Alan Boni | P60: SVPM | Q60: Diretrizes do Plano Diretor Elaboradas.
A61: =IFERROR(INDEX(Tabela2[ID_Area], MATCH(B61,Tabela2[Area], 0)), "Não encontrado") -> 1001 | B61: Meio Ambiente - Operação | C61: Controle Ambiental | D61: =IFERROR(INDEX(Metas!$D$2:$D$104, MATCH(E61,Metas!$E$2:$E$104, 0)), "Não encontrado") -> 131 | E61: Elaborar o Plano Diretor de Controles Ambientais do empreendimento | F61: Realizar a entrega dos procedimentos derivados do Plano Diretor de Controles Ambientais | G61: =IF(I61=1,"Concluído", IF(TODAY()>L61,"Atrasado", IF(AND(I61=0,TODAY()<K61),"Não iniciado", "Em Andamento"))) -> Atrasado | I61: 0.5 | J61: =IFERROR( M61 / SUMIFS($M:$M, $E:$E, $E61, $O:$O, $O61) * 120, 0 ) -> 12.317881 | K61: 45838 | L61: 45868 | M61: =L61 - K61 + 1 -> 31 | N61: =IFERROR(INDEX(Tabela3[ID_Responsavel], MATCH(O61,Tabela3[[Responsáveis ]], 0)), "Não encontrado") -> 1 | O61: Alan Boni | P61: SVPM | Q61: Entrega adiada para atender a finalização de revisão do documento mestre.
A62: =IFERROR(INDEX(Tabela2[ID_Area], MATCH(B62,Tabela2[Area], 0)), "Não encontrado") -> 1001 | B62: Meio Ambiente - Operação | C62: Controle Ambiental | D62: =IFERROR(INDEX(Metas!$D$2:$D$104, MATCH(E62,Metas!$E$2:$E$104, 0)), "Não encontrado") -> 131 | E62: Elaborar o Plano Diretor de Controles Ambientais do empreendimento | F62: Elaborar cronograma de treinamento das equipes de interface | G62: =IF(I62=1,"Concluído", IF(TODAY()>L62,"Atrasado", IF(AND(I62=0,TODAY()<K62),"Não iniciado", "Em Andamento"))) -> Atrasado | I62: 0 | J62: =IFERROR( M62 / SUMIFS($M:$M, $E:$E, $E62, $O:$O, $O62) * 120, 0 ) -> 11.92053 | K62: 45870 | L62: 45899 | M62: =L62 - K62 + 1 -> 30 | N62: =IFERROR(INDEX(Tabela3[ID_Responsavel], MATCH(O62,Tabela3[[Responsáveis ]], 0)), "Não encontrado") -> 1 | O62: Alan Boni | P62: SVPM | Q62: Devido ao adiamento estratégico do Workshop as equipes de interface não foram mobilizadas para treinamento.
A63: =IFERROR(INDEX(Tabela2[ID_Area], MATCH(B63,Tabela2[Area], 0)), "Não encontrado") -> 1001 | B63: Meio Ambiente - Operação | C63: Controle Ambiental | D63: =IFERROR(INDEX(Metas!$D$2:$D$104, MATCH(E63,Metas!$E$2:$E$104, 0)), "Não encontrado") -> 131 | E63: Elaborar o Plano Diretor de Controles Ambientais do empreendimento | F63: Entrega do Plano Diretor de Plano Diretor de Controles Ambientais e Realização do Workshop | G63: =IF(I63=1,"Concluído", IF(TODAY()>L63,"Atrasado", IF(AND(I63=0,TODAY()<K63),"Não iniciado", "Em Andamento"))) -> Atrasado | I63: 0.9 | J63: =IFERROR( M63 / SUMIFS($M:$M, $E:$E, $E63, $O:$O, $O63) * 120, 0 ) -> 24.238411 | K63: 45931 | L63: 45991 | M63: =L63 - K63 + 1 -> 61 | N63: =IFERROR(INDEX(Tabela3[ID_Responsavel], MATCH(O63,Tabela3[[Responsáveis ]], 0)), "Não encontrado") -> 1 | O63: Alan Boni | P63: SVPM | Q63: Plano Diretor Aprovado e concluído. Workshop pronto,material apresentado a gerencia e diretoria. Contudo foi cancelado por estratégia da Gerência.
A64: =IFERROR(INDEX(Tabela2[ID_Area], MATCH(B64,Tabela2[Area], 0)), "Não encontrado") -> 1001 | B64: Meio Ambiente - Operação | C64: SGA | D64: =IFERROR(INDEX(Metas!$D$2:$D$104, MATCH(E64,Metas!$E$2:$E$104, 0)), "Não encontrado") -> 132 | E64: Desenvolver e Implementar do Indice de Maturidade e regras socioambientais. | F64: Alinhar toda equipe sobre o conceito do Indice de Maturidade Ambiental colher percepções e apresentar produto final esperado | G64: =IF(I64=1,"Concluído", IF(TODAY()>L64,"Atrasado", IF(AND(I64=0,TODAY()<K64),"Não iniciado", "Em Andamento"))) -> Concluído | I64: 1 | J64: =IFERROR( M64 / SUMIFS($M:$M, $E:$E, $E64, $O:$O, $O64) * 120, 0 ) -> 1.9354839 | K64: 45674 | L64: 45688 | M64: =L64 - K64 + 1 -> 15 | N64: =IFERROR(INDEX(Tabela3[ID_Responsavel], MATCH(O64,Tabela3[[Responsáveis ]], 0)), "Não encontrado") -> 1 | O64: Alan Boni | P64: SVPM
A65: =IFERROR(INDEX(Tabela2[ID_Area], MATCH(B65,Tabela2[Area], 0)), "Não encontrado") -> 1001 | B65: Meio Ambiente - Operação | C65: SGA | D65: =IFERROR(INDEX(Metas!$D$2:$D$104, MATCH(E65,Metas!$E$2:$E$104, 0)), "Não encontrado") -> 132 | E65: Desenvolver e Implementar do Indice de Maturidade e regras socioambientais. | F65: Elaborar racional sobre as métricas de avaliação de cada temática do IMA | G65: =IF(I65=1,"Concluído", IF(TODAY()>L65,"Atrasado", IF(AND(I65=0,TODAY()<K65),"Não iniciado", "Em Andamento"))) -> Concluído | I65: 1 | J65: =IFERROR( M65 / SUMIFS($M:$M, $E:$E, $E65, $O:$O, $O65) * 120, 0 ) -> 3.3548387 | K65: 45691 | L65: 45716 | M65: =L65 - K65 + 1 -> 26 | N65: =IFERROR(INDEX(Tabela3[ID_Responsavel], MATCH(O65,Tabela3[[Responsáveis ]], 0)), "Não encontrado") -> 1 | O65: Alan Boni | P65: SVPM
A66: =IFERROR(INDEX(Tabela2[ID_Area], MATCH(B66,Tabela2[Area], 0)), "Não encontrado") -> 1001 | B66: Meio Ambiente - Operação | C66: SGA | D66: =IFERROR(INDEX(Metas!$D$2:$D$104, MATCH(E66,Metas!$E$2:$E$104, 0)), "Não encontrado") -> 132 | E66: Desenvolver e Implementar do Indice de Maturidade e regras socioambientais. | F66: Realizar reuniões e validar com focais dos temas Não conformidade, Requisitos Legais, Recursos Hídricos, Resíduos, Biodiversidade, PAE, Emissões e Recuperação de áreas degradadas | G66: =IF(I66=1,"Concluído", IF(TODAY()>L66,"Atrasado", IF(AND(I66=0,TODAY()<K66),"Não iniciado", "Em Andamento"))) -> Concluído | I66: 1 | J66: =IFERROR( M66 / SUMIFS($M:$M, $E:$E, $E66, $O:$O, $O66) * 120, 0 ) -> 2.1935484 | K66: 45717 | L66: 45733 | M66: =L66 - K66 + 1 -> 17 | N66: =IFERROR(INDEX(Tabela3[ID_Responsavel], MATCH(O66,Tabela3[[Responsáveis ]], 0)), "Não encontrado") -> 1 | O66: Alan Boni | P66: SVPM
A67: =IFERROR(INDEX(Tabela2[ID_Area], MATCH(B67,Tabela2[Area], 0)), "Não encontrado") -> 1001 | B67: Meio Ambiente - Operação | C67: SGA | D67: =IFERROR(INDEX(Metas!$D$2:$D$104, MATCH(E67,Metas!$E$2:$E$104, 0)), "Não encontrado") -> 132 | E67: Desenvolver e Implementar do Indice de Maturidade e regras socioambientais. | F67: Elaborar ferramentas de controle e divulgação do IMA | G67: =IF(I67=1,"Concluído", IF(TODAY()>L67,"Atrasado", IF(AND(I67=0,TODAY()<K67),"Não iniciado", "Em Andamento"))) -> Atrasado | I67: 0.9 | J67: =IFERROR( M67 / SUMIFS($M:$M, $E:$E, $E67, $O:$O, $O67) * 120, 0 ) -> 23.354839 | K67: 45734 | L67: 45914 | M67: =L67 - K67 + 1 -> 181 | N67: =IFERROR(INDEX(Tabela3[ID_Responsavel], MATCH(O67,Tabela3[[Responsáveis ]], 0)), "Não encontrado") -> 1 | O67: Alan Boni | P67: SVPM
A68: =IFERROR(INDEX(Tabela2[ID_Area], MATCH(B68,Tabela2[Area], 0)), "Não encontrado") -> 1001 | B68: Meio Ambiente - Operação | C68: SGA | D68: =IFERROR(INDEX(Metas!$D$2:$D$104, MATCH(E68,Metas!$E$2:$E$104, 0)), "Não encontrado") -> 132 | E68: Desenvolver e Implementar do Indice de Maturidade e regras socioambientais. | F68: Elaborar procedimento para gestão do IMA | G68: =IF(I68=1,"Concluído", IF(TODAY()>L68,"Atrasado", IF(AND(I68=0,TODAY()<K68),"Não iniciado", "Em Andamento"))) -> Atrasado | I68: 0.8 | J68: =IFERROR( M68 / SUMIFS($M:$M, $E:$E, $E68, $O:$O, $O68) * 120, 0 ) -> 23.354839 | K68: 45734 | L68: 45914 | M68: =L68 - K68 + 1 -> 181 | N68: =IFERROR(INDEX(Tabela3[ID_Responsavel], MATCH(O68,Tabela3[[Responsáveis ]], 0)), "Não encontrado") -> 1 | O68: Alan Boni | P68: SVPM
A69: =IFERROR(INDEX(Tabela2[ID_Area], MATCH(B69,Tabela2[Area], 0)), "Não encontrado") -> 1001 | B69: Meio Ambiente - Operação | C69: SGA | D69: =IFERROR(INDEX(Metas!$D$2:$D$104, MATCH(E69,Metas!$E$2:$E$104, 0)), "Não encontrado") -> 132 | E69: Desenvolver e Implementar do Indice de Maturidade e regras socioambientais. | F69: Apresentar para GMA procedimentos e ferramentas de gestão | G69: =IF(I69=1,"Concluído", IF(TODAY()>L69,"Atrasado", IF(AND(I69=0,TODAY()<K69),"Não iniciado", "Em Andamento"))) -> Atrasado | I69: 0 | J69: =IFERROR( M69 / SUMIFS($M:$M, $E:$E, $E69, $O:$O, $O69) * 120, 0 ) -> 21.935484 | K69: 45761 | L69: 45930 | M69: =L69 - K69 + 1 -> 170 | N69: =IFERROR(INDEX(Tabela3[ID_Responsavel], MATCH(O69,Tabela3[[Responsáveis ]], 0)), "Não encontrado") -> 1 | O69: Alan Boni | P69: SVPM
A70: =IFERROR(INDEX(Tabela2[ID_Area], MATCH(B70,Tabela2[Area], 0)), "Não encontrado") -> 1001 | B70: Meio Ambiente - Operação | C70: SGA | D70: =IFERROR(INDEX(Metas!$D$2:$D$104, MATCH(E70,Metas!$E$2:$E$104, 0)), "Não encontrado") -> 132 | E70: Desenvolver e Implementar do Indice de Maturidade e regras socioambientais. | F70: Realizar reuniões com as áreas operacionais para apresentação IMA e regras socioambientais | G70: =IF(I70=1,"Concluído", IF(TODAY()>L70,"Atrasado", IF(AND(I70=0,TODAY()<K70),"Não iniciado", "Em Andamento"))) -> Atrasado | I70: 0 | J70: =IFERROR( M70 / SUMIFS($M:$M, $E:$E, $E70, $O:$O, $O70) * 120, 0 ) -> 21.16129 | K70: 45782 | L70: 45945 | M70: =L70 - K70 + 1 -> 164 | N70: =IFERROR(INDEX(Tabela3[ID_Responsavel], MATCH(O70,Tabela3[[Responsáveis ]], 0)), "Não encontrado") -> 1 | O70: Alan Boni | P70: SVPM
A71: =IFERROR(INDEX(Tabela2[ID_Area], MATCH(B71,Tabela2[Area], 0)), "Não encontrado") -> 1001 | B71: Meio Ambiente - Operação | C71: SGA | D71: =IFERROR(INDEX(Metas!$D$2:$D$104, MATCH(E71,Metas!$E$2:$E$104, 0)), "Não encontrado") -> 132 | E71: Desenvolver e Implementar do Indice de Maturidade e regras socioambientais. | F71: Startar o IMA para as áreas | G71: =IF(I71=1,"Concluído", IF(TODAY()>L71,"Atrasado", IF(AND(I71=0,TODAY()<K71),"Não iniciado", "Em Andamento"))) -> Atrasado | I71: 0 | J71: =IFERROR( M71 / SUMIFS($M:$M, $E:$E, $E71, $O:$O, $O71) * 120, 0 ) -> 22.709677 | K71: 45814 | L71: 45989 | M71: =L71 - K71 + 1 -> 176 | N71: =IFERROR(INDEX(Tabela3[ID_Responsavel], MATCH(O71,Tabela3[[Responsáveis ]], 0)), "Não encontrado") -> 1 | O71: Alan Boni | P71: SVPM
A72: =IFERROR(INDEX(Tabela2[ID_Area], MATCH(B72,Tabela2[Area], 0)), "Não encontrado") -> 1001 | B72: Meio Ambiente - Operação | C72: Planos Diretores | D72: =IFERROR(INDEX(Metas!$D$2:$D$104, MATCH(E72,Metas!$E$2:$E$104, 0)), "Não encontrado") -> 137 | E72: Implementar o Plano Diretor de Controles Ambientais (PDCA) do empreendimento. | F72: Realizar a entrega do documento mestre Plano Diretor de Controles Ambientais | G72: =IF(I72=1,"Concluído", IF(TODAY()>L72,"Atrasado", IF(AND(I72=0,TODAY()<K72),"Não iniciado", "Em Andamento"))) -> Concluído | H72: 45838 | I72: 1 | J72: =IFERROR( M72 / SUMIFS($M:$M, $E:$E, $E72, $O:$O, $O72) * 120, 0 ) -> 71.760797 | K72: 45659 | L72: 45838 | M72: =L72 - K72 + 1 -> 180 | N72: =IFERROR(INDEX(Tabela3[ID_Responsavel], MATCH(O72,Tabela3[[Responsáveis ]], 0)), "Não encontrado") -> 22 | O72: Pedro Duque | P72: SVPM | Q72: Realizada entrega do documento com caracterização do empreendimento e início de definições das diretrizes. Entrega parcial da segunda revisão do documento Entrega dos mapas, indicadores e governança Realizada entrega do Plano Diretor de Controles Ambientais e Documentos auxiliares
A73: =IFERROR(INDEX(Tabela2[ID_Area], MATCH(B73,Tabela2[Area], 0)), "Não encontrado") -> 1001 | B73: Meio Ambiente - Operação | C73: Planos Diretores | D73: =IFERROR(INDEX(Metas!$D$2:$D$104, MATCH(E73,Metas!$E$2:$E$104, 0)), "Não encontrado") -> 137 | E73: Implementar o Plano Diretor de Controles Ambientais (PDCA) do empreendimento. | F73: Realizar a entrega dos procedimentos derivados do Plano Diretor de Controles Ambientais | G73: =IF(I73=1,"Concluído", IF(TODAY()>L73,"Atrasado", IF(AND(I73=0,TODAY()<K73),"Não iniciado", "Em Andamento"))) -> Atrasado | I73: 0.5 | J73: =IFERROR( M73 / SUMIFS($M:$M, $E:$E, $E73, $O:$O, $O73) * 120, 0 ) -> 12.358804 | K73: 45838 | L73: 45868 | M73: =L73 - K73 + 1 -> 31 | N73: =IFERROR(INDEX(Tabela3[ID_Responsavel], MATCH(O73,Tabela3[[Responsáveis ]], 0)), "Não encontrado") -> 22 | O73: Pedro Duque | P73: SVPM | Q73: Entrega adiada para atender a finalização de revisão do documento mestre
A74: =IFERROR(INDEX(Tabela2[ID_Area], MATCH(B74,Tabela2[Area], 0)), "Não encontrado") -> 1001 | B74: Meio Ambiente - Operação | C74: Planos Diretores | D74: =IFERROR(INDEX(Metas!$D$2:$D$104, MATCH(E74,Metas!$E$2:$E$104, 0)), "Não encontrado") -> 137 | E74: Implementar o Plano Diretor de Controles Ambientais (PDCA) do empreendimento. | F74: Elaborar cronograma de treinamento das equipes operacionais nos procedimentos | G74: =IF(I74=1,"Concluído", IF(TODAY()>L74,"Atrasado", IF(AND(I74=0,TODAY()<K74),"Não iniciado", "Em Andamento"))) -> Atrasado | I74: 0 | J74: =IFERROR( M74 / SUMIFS($M:$M, $E:$E, $E74, $O:$O, $O74) * 120, 0 ) -> 11.960133 | K74: 45870 | L74: 45899 | M74: =L74 - K74 + 1 -> 30 | N74: =IFERROR(INDEX(Tabela3[ID_Responsavel], MATCH(O74,Tabela3[[Responsáveis ]], 0)), "Não encontrado") -> 22 | O74: Pedro Duque | P74: SVPM | Q74: Equipes não foram mobilizadas
A75: =IFERROR(INDEX(Tabela2[ID_Area], MATCH(B75,Tabela2[Area], 0)), "Não encontrado") -> 1001 | B75: Meio Ambiente - Operação | C75: Planos Diretores | D75: =IFERROR(INDEX(Metas!$D$2:$D$104, MATCH(E75,Metas!$E$2:$E$104, 0)), "Não encontrado") -> 137 | E75: Implementar o Plano Diretor de Controles Ambientais (PDCA) do empreendimento. | F75: Realizar capacitação técnica da equipe executora das atividades de controle ambiental | G75: =IF(I75=1,"Concluído", IF(TODAY()>L75,"Atrasado", IF(AND(I75=0,TODAY()<K75),"Não iniciado", "Em Andamento"))) -> Atrasado | I75: 0 | J75: =IFERROR( M75 / SUMIFS($M:$M, $E:$E, $E75, $O:$O, $O75) * 120, 0 ) -> 23.920266 | K75: 45901 | L75: 45960 | M75: =L75 - K75 + 1 -> 60 | N75: =IFERROR(INDEX(Tabela3[ID_Responsavel], MATCH(O75,Tabela3[[Responsáveis ]], 0)), "Não encontrado") -> 22 | O75: Pedro Duque | P75: SVPM | Q75: Equipes não foram mobilizadas
A76: =IFERROR(INDEX(Tabela2[ID_Area], MATCH(B76,Tabela2[Area], 0)), "Não encontrado") -> 1001 | B76: Meio Ambiente - Operação | C76: Controle Ambiental | D76: =IFERROR(INDEX(Metas!$D$2:$D$104, MATCH(E76,Metas!$E$2:$E$104, 0)), "Não encontrado") -> 138 | E76: Determinar as principais bacias de drenagem natural da ADA SVPM e suas contribuições pluviais, para determinar a origem dos impactos de turbidez das bacias. | F76: Realizar levantamento topográfico detalhado das drenagens para definir os pontos de contribuição | G76: =IF(I76=1,"Concluído", IF(TODAY()>L76,"Atrasado", IF(AND(I76=0,TODAY()<K76),"Não iniciado", "Em Andamento"))) -> Concluído | H76: 45705 | I76: 1 | J76: =IFERROR( M76 / SUMIFS($M:$M, $E:$E, $E76, $O:$O, $O76) * 120, 0 ) -> 28.732394 | K76: 45659 | L76: 45709 | M76: =L76 - K76 + 1 -> 51 | N76: =IFERROR(INDEX(Tabela3[ID_Responsavel], MATCH(O76,Tabela3[[Responsáveis ]], 0)), "Não encontrado") -> 22 | O76: Pedro Duque | P76: SVPM | Q76: Recebida informações da equipe de topografia para modelagem
A77: =IFERROR(INDEX(Tabela2[ID_Area], MATCH(B77,Tabela2[Area], 0)), "Não encontrado") -> 1001 | B77: Meio Ambiente - Operação | C77: Controle Ambiental | D77: =IFERROR(INDEX(Metas!$D$2:$D$104, MATCH(E77,Metas!$E$2:$E$104, 0)), "Não encontrado") -> 138 | E77: Determinar as principais bacias de drenagem natural da ADA SVPM e suas contribuições pluviais, para determinar a origem dos impactos de turbidez das bacias. | F77: Criar modelo de elevação e definir estratégia de investigação | G77: =IF(I77=1,"Concluído", IF(TODAY()>L77,"Atrasado", IF(AND(I77=0,TODAY()<K77),"Não iniciado", "Em Andamento"))) -> Concluído | H77: 45722 | I77: 1 | J77: =IFERROR( M77 / SUMIFS($M:$M, $E:$E, $E77, $O:$O, $O77) * 120, 0 ) -> 11.830986 | K77: 45709 | L77: 45729 | M77: =L77 - K77 + 1 -> 21 | N77: =IFERROR(INDEX(Tabela3[ID_Responsavel], MATCH(O77,Tabela3[[Responsáveis ]], 0)), "Não encontrado") -> 22 | O77: Pedro Duque | P77: SVPM | Q77: Criado o Modelo Digital de Elevação e canais de drenagem
A78: =IFERROR(INDEX(Tabela2[ID_Area], MATCH(B78,Tabela2[Area], 0)), "Não encontrado") -> 1001 | B78: Meio Ambiente - Operação | C78: Controle Ambiental | D78: =IFERROR(INDEX(Metas!$D$2:$D$104, MATCH(E78,Metas!$E$2:$E$104, 0)), "Não encontrado") -> 138 | E78: Determinar as principais bacias de drenagem natural da ADA SVPM e suas contribuições pluviais, para determinar a origem dos impactos de turbidez das bacias. | F78: Realizar levatamento de campo das drenagens e pontos de contribuição de turbidez | G78: =IF(I78=1,"Concluído", IF(TODAY()>L78,"Atrasado", IF(AND(I78=0,TODAY()<K78),"Não iniciado", "Em Andamento"))) -> Concluído | H78: 45800 | I78: 1 | J78: =IFERROR( M78 / SUMIFS($M:$M, $E:$E, $E78, $O:$O, $O78) * 120, 0 ) -> 42.816901 | K78: 45729 | L78: 45804 | M78: =L78 - K78 + 1 -> 76 | N78: =IFERROR(INDEX(Tabela3[ID_Responsavel], MATCH(O78,Tabela3[[Responsáveis ]], 0)), "Não encontrado") -> 22 | O78: Pedro Duque | P78: SVPM
A79: =IFERROR(INDEX(Tabela2[ID_Area], MATCH(B79,Tabela2[Area], 0)), "Não encontrado") -> 1001 | B79: Meio Ambiente - Operação | C79: Controle Ambiental | D79: =IFERROR(INDEX(Metas!$D$2:$D$104, MATCH(E79,Metas!$E$2:$E$104, 0)), "Não encontrado") -> 138 | E79: Determinar as principais bacias de drenagem natural da ADA SVPM e suas contribuições pluviais, para determinar a origem dos impactos de turbidez das bacias. | F79: Criar fluxograma e mapa das contribuições de turbidez nas drenagens | G79: =IF(I79=1,"Concluído", IF(TODAY()>L79,"Atrasado", IF(AND(I79=0,TODAY()<K79),"Não iniciado", "Em Andamento"))) -> Concluído | H79: 45833 | I79: 1 | J79: =IFERROR( M79 / SUMIFS($M:$M, $E:$E, $E79, $O:$O, $O79) * 120, 0 ) -> 36.619718 | K79: 45804 | L79: 45868 | M79: =L79 - K79 + 1 -> 65 | N79: =IFERROR(INDEX(Tabela3[ID_Responsavel], MATCH(O79,Tabela3[[Responsáveis ]], 0)), "Não encontrado") -> 22 | O79: Pedro Duque | P79: SVPM
A80: =IFERROR(INDEX(Tabela2[ID_Area], MATCH(B80,Tabela2[Area], 0)), "Não encontrado") -> 1001 | B80: Meio Ambiente - Operação | C80: P&D | D80: =IFERROR(INDEX(Metas!$D$2:$D$104, MATCH(E80,Metas!$E$2:$E$104, 0)), "Não encontrado") -> 139 | E80: Apresentar e testar novas soluções para proteção de taludes a erosão | F80: Levantar de tecnologias disponíveis | G80: =IF(I80=1,"Concluído", IF(TODAY()>L80,"Atrasado", IF(AND(I80=0,TODAY()<K80),"Não iniciado", "Em Andamento"))) -> Concluído | H80: 45659 | I80: 1 | J80: =IFERROR( M80 / SUMIFS($M:$M, $E:$E, $E80, $O:$O, $O80) * 120, 0 ) -> 35.907591 | K80: 45659 | L80: 45930 | M80: =L80 - K80 + 1 -> 272 | N80: =IFERROR(INDEX(Tabela3[ID_Responsavel], MATCH(O80,Tabela3[[Responsáveis ]], 0)), "Não encontrado") -> 22 | O80: Pedro Duque | P80: SVPM | Q80: Iniciadas pesquisas bibliográficas e benchmarking
A81: =IFERROR(INDEX(Tabela2[ID_Area], MATCH(B81,Tabela2[Area], 0)), "Não encontrado") -> 1001 | B81: Meio Ambiente - Operação | C81: P&D | D81: =IFERROR(INDEX(Metas!$D$2:$D$104, MATCH(E81,Metas!$E$2:$E$104, 0)), "Não encontrado") -> 139 | E81: Apresentar e testar novas soluções para proteção de taludes a erosão | F81: Realizar benchmarking | G81: =IF(I81=1,"Concluído", IF(TODAY()>L81,"Atrasado", IF(AND(I81=0,TODAY()<K81),"Não iniciado", "Em Andamento"))) -> Concluído | H81: 45681 | I81: 1 | J81: =IFERROR( M81 / SUMIFS($M:$M, $E:$E, $E81, $O:$O, $O81) * 120, 0 ) -> 35.907591 | K81: 45659 | L81: 45930 | M81: =L81 - K81 + 1 -> 272 | N81: =IFERROR(INDEX(Tabela3[ID_Responsavel], MATCH(O81,Tabela3[[Responsáveis ]], 0)), "Não encontrado") -> 22 | O81: Pedro Duque | P81: SVPM
A82: =IFERROR(INDEX(Tabela2[ID_Area], MATCH(B82,Tabela2[Area], 0)), "Não encontrado") -> 1001 | B82: Meio Ambiente - Operação | C82: P&D | D82: =IFERROR(INDEX(Metas!$D$2:$D$104, MATCH(E82,Metas!$E$2:$E$104, 0)), "Não encontrado") -> 139 | E82: Apresentar e testar novas soluções para proteção de taludes a erosão | F82: Apresentar tecnologias para controle de erosão | G82: =IF(I82=1,"Concluído", IF(TODAY()>L82,"Atrasado", IF(AND(I82=0,TODAY()<K82),"Não iniciado", "Em Andamento"))) -> Concluído | H82: 45841 | I82: 1 | J82: =IFERROR( M82 / SUMIFS($M:$M, $E:$E, $E82, $O:$O, $O82) * 120, 0 ) -> 28.118812 | K82: 45749 | L82: 45961 | M82: =L82 - K82 + 1 -> 213 | N82: =IFERROR(INDEX(Tabela3[ID_Responsavel], MATCH(O82,Tabela3[[Responsáveis ]], 0)), "Não encontrado") -> 22 | O82: Pedro Duque | P82: SVPM
A83: =IFERROR(INDEX(Tabela2[ID_Area], MATCH(B83,Tabela2[Area], 0)), "Não encontrado") -> 1001 | B83: Meio Ambiente - Operação | C83: P&D | D83: =IFERROR(INDEX(Metas!$D$2:$D$104, MATCH(E83,Metas!$E$2:$E$104, 0)), "Não encontrado") -> 139 | E83: Apresentar e testar novas soluções para proteção de taludes a erosão | F83: Testar nova tecnologia de controle de erosão | G83: =IF(I83=1,"Concluído", IF(TODAY()>L83,"Atrasado", IF(AND(I83=0,TODAY()<K83),"Não iniciado", "Em Andamento"))) -> Concluído | H83: 45966 | I83: 1 | J83: =IFERROR( M83 / SUMIFS($M:$M, $E:$E, $E83, $O:$O, $O83) * 120, 0 ) -> 20.066007 | K83: 45870 | L83: 46021 | M83: =L83 - K83 + 1 -> 152 | N83: =IFERROR(INDEX(Tabela3[ID_Responsavel], MATCH(O83,Tabela3[[Responsáveis ]], 0)), "Não encontrado") -> 22 | O83: Pedro Duque | P83: SVPM
A84: =IFERROR(INDEX(Tabela2[ID_Area], MATCH(B84,Tabela2[Area], 0)), "Não encontrado") -> 1001 | B84: Meio Ambiente - Operação | C84: P&D | D84: =IFERROR(INDEX(Metas!$D$2:$D$104, MATCH(E84,Metas!$E$2:$E$104, 0)), "Não encontrado") -> 140 | E84: Propor nova metodologia para controle de material particulado em vias não pavimentadas | F84: Levantar de tecnologias disponíveis | G84: =IF(I84=1,"Concluído", IF(TODAY()>L84,"Atrasado", IF(AND(I84=0,TODAY()<K84),"Não iniciado", "Em Andamento"))) -> Concluído | H84: 45761 | I84: 1 | J84: =IFERROR( M84 / SUMIFS($M:$M, $E:$E, $E84, $O:$O, $O84) * 120, 0 ) -> 34.723404 | K84: 45659 | L84: 45930 | M84: =L84 - K84 + 1 -> 272 | N84: =IFERROR(INDEX(Tabela3[ID_Responsavel], MATCH(O84,Tabela3[[Responsáveis ]], 0)), "Não encontrado") -> 22 | O84: Pedro Duque | P84: SVPM | Q84: Iniciadas pesquisas bibliográficas e benchmarking Novos benchmarking e reunião planejada com geotecnia
A85: =IFERROR(INDEX(Tabela2[ID_Area], MATCH(B85,Tabela2[Area], 0)), "Não encontrado") -> 1001 | B85: Meio Ambiente - Operação | C85: P&D | D85: =IFERROR(INDEX(Metas!$D$2:$D$104, MATCH(E85,Metas!$E$2:$E$104, 0)), "Não encontrado") -> 140 | E85: Propor nova metodologia para controle de material particulado em vias não pavimentadas | F85: Realizar benchmarking | G85: =IF(I85=1,"Concluído", IF(TODAY()>L85,"Atrasado", IF(AND(I85=0,TODAY()<K85),"Não iniciado", "Em Andamento"))) -> Concluído | H85: 45761 | I85: 1 | J85: =IFERROR( M85 / SUMIFS($M:$M, $E:$E, $E85, $O:$O, $O85) * 120, 0 ) -> 34.723404 | K85: 45659 | L85: 45930 | M85: =L85 - K85 + 1 -> 272 | N85: =IFERROR(INDEX(Tabela3[ID_Responsavel], MATCH(O85,Tabela3[[Responsáveis ]], 0)), "Não encontrado") -> 22 | O85: Pedro Duque | P85: SVPM
A86: =IFERROR(INDEX(Tabela2[ID_Area], MATCH(B86,Tabela2[Area], 0)), "Não encontrado") -> 1001 | B86: Meio Ambiente - Operação | C86: P&D | D86: =IFERROR(INDEX(Metas!$D$2:$D$104, MATCH(E86,Metas!$E$2:$E$104, 0)), "Não encontrado") -> 140 | E86: Propor nova metodologia para controle de material particulado em vias não pavimentadas | F86: Apresentar tecnologias para controle de poeira em vias | G86: =IF(I86=1,"Concluído", IF(TODAY()>L86,"Atrasado", IF(AND(I86=0,TODAY()<K86),"Não iniciado", "Em Andamento"))) -> Concluído | H86: 45874 | I86: 1 | J86: =IFERROR( M86 / SUMIFS($M:$M, $E:$E, $E86, $O:$O, $O86) * 120, 0 ) -> 27.191489 | K86: 45749 | L86: 45961 | M86: =L86 - K86 + 1 -> 213 | N86: =IFERROR(INDEX(Tabela3[ID_Responsavel], MATCH(O86,Tabela3[[Responsáveis ]], 0)), "Não encontrado") -> 22 | O86: Pedro Duque | P86: SVPM
A87: =IFERROR(INDEX(Tabela2[ID_Area], MATCH(B87,Tabela2[Area], 0)), "Não encontrado") -> 1001 | B87: Meio Ambiente - Operação | C87: P&D | D87: =IFERROR(INDEX(Metas!$D$2:$D$104, MATCH(E87,Metas!$E$2:$E$104, 0)), "Não encontrado") -> 140 | E87: Propor nova metodologia para controle de material particulado em vias não pavimentadas | F87: Testar novo método para controle de poeira em vias | G87: =IF(I87=1,"Concluído", IF(TODAY()>L87,"Atrasado", IF(AND(I87=0,TODAY()<K87),"Não iniciado", "Em Andamento"))) -> Concluído | H87: 45791 | I87: 1 | J87: =IFERROR( M87 / SUMIFS($M:$M, $E:$E, $E87, $O:$O, $O87) * 120, 0 ) -> 23.361702 | K87: 45839 | L87: 46021 | M87: =L87 - K87 + 1 -> 183 | N87: =IFERROR(INDEX(Tabela3[ID_Responsavel], MATCH(O87,Tabela3[[Responsáveis ]], 0)), "Não encontrado") -> 22 | O87: Pedro Duque | P87: SVPM
A88: =IFERROR(INDEX(Tabela2[ID_Area], MATCH(B88,Tabela2[Area], 0)), "Não encontrado") -> 1001 | B88: Meio Ambiente - Operação | C88: Plano de Atendimento a Emergência | D88: =IFERROR(INDEX(Metas!$D$2:$D$104, MATCH(E88,Metas!$E$2:$E$104, 0)), "Não encontrado") -> 146 | E88: Revisão do PAE, PGR e PAE Rodoviário integrando atualizando e revisão riscos e atividades do empreendimento. | F88: Solicitar a empresa responsável pela elaboração dos documentos a entrega dos documentos. | G88: =IF(I88=1,"Concluído", IF(TODAY()>L88,"Atrasado", IF(AND(I88=0,TODAY()<K88),"Não iniciado", "Em Andamento"))) -> Concluído | H88: 45713 | I88: 1 | J88: =IFERROR( M88 / SUMIFS($M:$M, $E:$E, $E88, $O:$O, $O88) * 120, 0 ) -> 11.601208 | K88: 45663 | L88: 45694 | M88: =L88 - K88 + 1 -> 32 | N88: =IFERROR(INDEX(Tabela3[ID_Responsavel], MATCH(O88,Tabela3[[Responsáveis ]], 0)), "Não encontrado") -> 26 | O88: Thulio Souza | P88: Biota
A89: =IFERROR(INDEX(Tabela2[ID_Area], MATCH(B89,Tabela2[Area], 0)), "Não encontrado") -> 1001 | B89: Meio Ambiente - Operação | C89: Plano de Atendimento a Emergência | D89: =IFERROR(INDEX(Metas!$D$2:$D$104, MATCH(E89,Metas!$E$2:$E$104, 0)), "Não encontrado") -> 146 | E89: Revisão do PAE, PGR e PAE Rodoviário integrando atualizando e revisão riscos e atividades do empreendimento. | F89: Avaliar o conteúdo e revisar os riscos (Se condiz com a nossa realidade). | G89: =IF(I89=1,"Concluído", IF(TODAY()>L89,"Atrasado", IF(AND(I89=0,TODAY()<K89),"Não iniciado", "Em Andamento"))) -> Concluído | H89: 45961 | I89: 1 | J89: =IFERROR( M89 / SUMIFS($M:$M, $E:$E, $E89, $O:$O, $O89) * 120, 0 ) -> 108.39879 | K89: 45663 | L89: 45961 | M89: =L89 - K89 + 1 -> 299 | N89: =IFERROR(INDEX(Tabela3[ID_Responsavel], MATCH(O89,Tabela3[[Responsáveis ]], 0)), "Não encontrado") -> 26 | O89: Thulio Souza | P89: Biota | Q89: Um dos itens previstos no novo contrato de emergências é a revisão de tais documentos, onde após finalizado o processo de contratação no início de 2026, os documentos passaram por nova revisão de empresa especializada.
A90: =IFERROR(INDEX(Tabela2[ID_Area], MATCH(B90,Tabela2[Area], 0)), "Não encontrado") -> 1001 | B90: Meio Ambiente - Operação | C90: Plano de Atendimento a Emergência | D90: =IFERROR(INDEX(Metas!$D$2:$D$104, MATCH(E90,Metas!$E$2:$E$104, 0)), "Não encontrado") -> 147 | E90: Criar Procedimento do PAE e PGR (Unificado Ambiente e Segurança). | F90: Solicitar a segurança a revisão no PAE da segurança. | G90: =IF(I90=1,"Concluído", IF(TODAY()>L90,"Atrasado", IF(AND(I90=0,TODAY()<K90),"Não iniciado", "Em Andamento"))) -> Concluído | H90: 45764 | I90: 1 | J90: =IFERROR( M90 / SUMIFS($M:$M, $E:$E, $E90, $O:$O, $O90) * 120, 0 ) -> 10 | K90: 45663 | L90: 45694 | M90: =L90 - K90 + 1 -> 32 | N90: =IFERROR(INDEX(Tabela3[ID_Responsavel], MATCH(O90,Tabela3[[Responsáveis ]], 0)), "Não encontrado") -> 26 | O90: Thulio Souza | P90: Biota
A91: =IFERROR(INDEX(Tabela2[ID_Area], MATCH(B91,Tabela2[Area], 0)), "Não encontrado") -> 1001 | B91: Meio Ambiente - Operação | C91: Plano de Atendimento a Emergência | D91: =IFERROR(INDEX(Metas!$D$2:$D$104, MATCH(E91,Metas!$E$2:$E$104, 0)), "Não encontrado") -> 147 | E91: Criar Procedimento do PAE e PGR (Unificado Ambiente e Segurança). | F91: Entrega do PAE unificado | G91: =IF(I91=1,"Concluído", IF(TODAY()>L91,"Atrasado", IF(AND(I91=0,TODAY()<K91),"Não iniciado", "Em Andamento"))) -> Concluído | H91: 45931 | I91: 1 | J91: =IFERROR( M91 / SUMIFS($M:$M, $E:$E, $E91, $O:$O, $O91) * 120, 0 ) -> 110 | K91: 45670 | L91: 46021 | M91: =L91 - K91 + 1 -> 352 | N91: =IFERROR(INDEX(Tabela3[ID_Responsavel], MATCH(O91,Tabela3[[Responsáveis ]], 0)), "Não encontrado") -> 26 | O91: Thulio Souza | P91: Biota
A92: =IFERROR(INDEX(Tabela2[ID_Area], MATCH(B92,Tabela2[Area], 0)), "Não encontrado") -> 1001 | B92: Meio Ambiente - Operação | C92: SGA | D92: =IFERROR(INDEX(Metas!$D$2:$D$104, MATCH(E92,Metas!$E$2:$E$104, 0)), "Não encontrado") -> 148 | E92: Aperfeiçoar sistema de gestão ambiental da área de Meio Ambiente Operação. | F92: Redefinir termos e conceitos da área de controles e criar os fluxos de informações e decisão da área de controles ambientais. | G92: =IF(I92=1,"Concluído", IF(TODAY()>L92,"Atrasado", IF(AND(I92=0,TODAY()<K92),"Não iniciado", "Em Andamento"))) -> Concluído | H92: 45734 | I92: 1 | J92: =IFERROR( M92 / SUMIFS($M:$M, $E:$E, $E92, $O:$O, $O92) * 120, 0 ) -> 33.247706 | K92: 45292 | L92: 45442 | M92: =L92 - K92 + 1 -> 151 | N92: =IFERROR(INDEX(Tabela3[ID_Responsavel], MATCH(O92,Tabela3[[Responsáveis ]], 0)), "Não encontrado") -> 26 | O92: Thulio Souza | P92: Biota
A93: =IFERROR(INDEX(Tabela2[ID_Area], MATCH(B93,Tabela2[Area], 0)), "Não encontrado") -> 1001 | B93: Meio Ambiente - Operação | C93: SGA | D93: =IFERROR(INDEX(Metas!$D$2:$D$104, MATCH(E93,Metas!$E$2:$E$104, 0)), "Não encontrado") -> 148 | E93: Aperfeiçoar sistema de gestão ambiental da área de Meio Ambiente Operação. | F93: Revisar todos os procedimentos, ferramentas(PM Driver) e check list. | G93: =IF(I93=1,"Concluído", IF(TODAY()>L93,"Atrasado", IF(AND(I93=0,TODAY()<K93),"Não iniciado", "Em Andamento"))) -> Concluído | H93: 45734 | I93: 1 | J93: =IFERROR( M93 / SUMIFS($M:$M, $E:$E, $E93, $O:$O, $O93) * 120, 0 ) -> 33.247706 | K93: 45292 | L93: 45442 | M93: =L93 - K93 + 1 -> 151 | N93: =IFERROR(INDEX(Tabela3[ID_Responsavel], MATCH(O93,Tabela3[[Responsáveis ]], 0)), "Não encontrado") -> 26 | O93: Thulio Souza | P93: Biota
A94: =IFERROR(INDEX(Tabela2[ID_Area], MATCH(B94,Tabela2[Area], 0)), "Não encontrado") -> 1001 | B94: Meio Ambiente - Operação | C94: SGA | D94: =IFERROR(INDEX(Metas!$D$2:$D$104, MATCH(E94,Metas!$E$2:$E$104, 0)), "Não encontrado") -> 148 | E94: Aperfeiçoar sistema de gestão ambiental da área de Meio Ambiente Operação. | F94: Definir de KPI’ s da área de controle. | G94: =IF(I94=1,"Concluído", IF(TODAY()>L94,"Atrasado", IF(AND(I94=0,TODAY()<K94),"Não iniciado", "Em Andamento"))) -> Concluído | H94: 45734 | I94: 1 | J94: =IFERROR( M94 / SUMIFS($M:$M, $E:$E, $E94, $O:$O, $O94) * 120, 0 ) -> 20.036697 | K94: 45352 | L94: 45442 | M94: =L94 - K94 + 1 -> 91 | N94: =IFERROR(INDEX(Tabela3[ID_Responsavel], MATCH(O94,Tabela3[[Responsáveis ]], 0)), "Não encontrado") -> 26 | O94: Thulio Souza | P94: Biota | Q94: Os KPIs foram definidos, o procedimento interno foi revisado e aprovado gerencialmente. Vale ressaltar, que a classificação de gravidade de AA será revisado no início de 2026, com frente a equipe de SGI, com apoio das equipes de M.A operação e licenciamento, para alteração no procedimento normativo. Outro ponto que foi discutido é a exclusão do Ver e agir de Meio Ambiente, onde após decisão gerencial, o procedimento será revisado novamente e o KPI removido. Para 2025, o que foi proposto atendeu a equipe de operação e as pontuações citadas acima serão realizadas no início de 2026, conforme alinhamentos e decisões entre equipes.
A95: =IFERROR(INDEX(Tabela2[ID_Area], MATCH(B95,Tabela2[Area], 0)), "Não encontrado") -> 1001 | B95: Meio Ambiente - Operação | C95: SGA | D95: =IFERROR(INDEX(Metas!$D$2:$D$104, MATCH(E95,Metas!$E$2:$E$104, 0)), "Não encontrado") -> 148 | E95: Aperfeiçoar sistema de gestão ambiental da área de Meio Ambiente Operação. | F95: Disponibilizar para consulta os dados de maneira rápida, clara, objetiva e com confiabilidade, através de um dashboard e realizar workshop | G95: =IF(I95=1,"Concluído", IF(TODAY()>L95,"Atrasado", IF(AND(I95=0,TODAY()<K95),"Não iniciado", "Em Andamento"))) -> Concluído | H95: 45960 | I95: 1 | J95: =IFERROR( M95 / SUMIFS($M:$M, $E:$E, $E95, $O:$O, $O95) * 120, 0 ) -> 33.46789 | K95: 45809 | L95: 45960 | M95: =L95 - K95 + 1 -> 152 | N95: =IFERROR(INDEX(Tabela3[ID_Responsavel], MATCH(O95,Tabela3[[Responsáveis ]], 0)), "Não encontrado") -> 26 | O95: Thulio Souza | P95: Biota
A96: =IFERROR(INDEX(Tabela2[ID_Area], MATCH(B96,Tabela2[Area], 0)), "Não encontrado") -> 1001 | B96: Meio Ambiente - Operação | C96: P&D | D96: =IFERROR(INDEX(Metas!$D$2:$D$104, MATCH(E96,Metas!$E$2:$E$104, 0)), "Não encontrado") -> 157 | E96: Apresentar e testar novas soluções para proteção de taludes a erosão_GuilhermeMonteiro | F96: Levantar de tecnologias disponíveis | G96: =IF(I96=1,"Concluído", IF(TODAY()>L96,"Atrasado", IF(AND(I96=0,TODAY()<K96),"Não iniciado", "Em Andamento"))) -> Concluído | H96: 45800 | I96: 1 | J96: =IFERROR( M96 / SUMIFS($M:$M, $E:$E, $E96, $O:$O, $O96) * 120, 0 ) -> 35.907591 | K96: 45659 | L96: 45930 | M96: =L96 - K96 + 1 -> 272 | N96: =IFERROR(INDEX(Tabela3[ID_Responsavel], MATCH(O96,Tabela3[[Responsáveis ]], 0)), "Não encontrado") -> 10 | O96: Guilherme Monteiro | P96: Biota | Q96: Iniciadas pesquisas bibliográficas e benchmarking
A97: =IFERROR(INDEX(Tabela2[ID_Area], MATCH(B97,Tabela2[Area], 0)), "Não encontrado") -> 1001 | B97: Meio Ambiente - Operação | C97: P&D | D97: =IFERROR(INDEX(Metas!$D$2:$D$104, MATCH(E97,Metas!$E$2:$E$104, 0)), "Não encontrado") -> 157 | E97: Apresentar e testar novas soluções para proteção de taludes a erosão_GuilhermeMonteiro | F97: Realizar benchmarking | G97: =IF(I97=1,"Concluído", IF(TODAY()>L97,"Atrasado", IF(AND(I97=0,TODAY()<K97),"Não iniciado", "Em Andamento"))) -> Concluído | H97: 45681 | I97: 1 | J97: =IFERROR( M97 / SUMIFS($M:$M, $E:$E, $E97, $O:$O, $O97) * 120, 0 ) -> 35.907591 | K97: 45659 | L97: 45930 | M97: =L97 - K97 + 1 -> 272 | N97: =IFERROR(INDEX(Tabela3[ID_Responsavel], MATCH(O97,Tabela3[[Responsáveis ]], 0)), "Não encontrado") -> 10 | O97: Guilherme Monteiro | P97: Biota | Q97: Realizado benchmarking com fornecedores
A98: =IFERROR(INDEX(Tabela2[ID_Area], MATCH(B98,Tabela2[Area], 0)), "Não encontrado") -> 1001 | B98: Meio Ambiente - Operação | C98: P&D | D98: =IFERROR(INDEX(Metas!$D$2:$D$104, MATCH(E98,Metas!$E$2:$E$104, 0)), "Não encontrado") -> 157 | E98: Apresentar e testar novas soluções para proteção de taludes a erosão_GuilhermeMonteiro | F98: Apresentar tecnologias para controle de erosão | G98: =IF(I98=1,"Concluído", IF(TODAY()>L98,"Atrasado", IF(AND(I98=0,TODAY()<K98),"Não iniciado", "Em Andamento"))) -> Concluído | I98: 1 | J98: =IFERROR( M98 / SUMIFS($M:$M, $E:$E, $E98, $O:$O, $O98) * 120, 0 ) -> 28.118812 | K98: 45749 | L98: 45961 | M98: =L98 - K98 + 1 -> 213 | N98: =IFERROR(INDEX(Tabela3[ID_Responsavel], MATCH(O98,Tabela3[[Responsáveis ]], 0)), "Não encontrado") -> 10 | O98: Guilherme Monteiro | P98: Biota | Q98: Realizado aplicação da tela de mosquiteiro e tela de sombrete no talude na área da mina. / Comclusão para 19/12/2025
A99: =IFERROR(INDEX(Tabela2[ID_Area], MATCH(B99,Tabela2[Area], 0)), "Não encontrado") -> 1001 | B99: Meio Ambiente - Operação | C99: P&D | D99: =IFERROR(INDEX(Metas!$D$2:$D$104, MATCH(E99,Metas!$E$2:$E$104, 0)), "Não encontrado") -> 157 | E99: Apresentar e testar novas soluções para proteção de taludes a erosão_GuilhermeMonteiro | F99: Testar nova tecnologia de controle de erosão | G99: =IF(I99=1,"Concluído", IF(TODAY()>L99,"Atrasado", IF(AND(I99=0,TODAY()<K99),"Não iniciado", "Em Andamento"))) -> Concluído | I99: 1 | J99: =IFERROR( M99 / SUMIFS($M:$M, $E:$E, $E99, $O:$O, $O99) * 120, 0 ) -> 20.066007 | K99: 45870 | L99: 46021 | M99: =L99 - K99 + 1 -> 152 | N99: =IFERROR(INDEX(Tabela3[ID_Responsavel], MATCH(O99,Tabela3[[Responsáveis ]], 0)), "Não encontrado") -> 10 | O99: Guilherme Monteiro | P99: Biota | Q99: Definido os taludes de corte e aterro para teste
A100: =IFERROR(INDEX(Tabela2[ID_Area], MATCH(B100,Tabela2[Area], 0)), "Não encontrado") -> 1001 | B100: Meio Ambiente - Operação | C100: P&D | D100: =IFERROR(INDEX(Metas!$D$2:$D$104, MATCH(E100,Metas!$E$2:$E$104, 0)), "Não encontrado") -> 156 | E100: Implantar soluções técnicas para controles controle da vazamento de óleo na planta e na mina.. | F100: Realizar levantamento de áreas de alto risco de vazamento | G100: =IF(I100=1,"Concluído", IF(TODAY()>L100,"Atrasado", IF(AND(I100=0,TODAY()<K100),"Não iniciado", "Em Andamento"))) -> Concluído | I100: 1 | J100: =IFERROR( M100 / SUMIFS($M:$M, $E:$E, $E100, $O:$O, $O100) * 120, 0 ) -> 51.240188 | K100: 45659 | L100: 45930 | M100: =L100 - K100 + 1 -> 272 | N100: =IFERROR(INDEX(Tabela3[ID_Responsavel], MATCH(O100,Tabela3[[Responsáveis ]], 0)), "Não encontrado") -> 10 | O100: Guilherme Monteiro | P100: Biota | Q100: A atividade foi finalizada devido à conclusão do levantamento e entrega das áreas classificadas como de alto risco de vazamento de óleo, contemplando tanto a planta quanto a mina
A101: =IFERROR(INDEX(Tabela2[ID_Area], MATCH(B101,Tabela2[Area], 0)), "Não encontrado") -> 1001 | B101: Meio Ambiente - Operação | C101: P&D | D101: =IFERROR(INDEX(Metas!$D$2:$D$104, MATCH(E101,Metas!$E$2:$E$104, 0)), "Não encontrado") -> 156 | E101: Implantar soluções técnicas para controles controle da vazamento de óleo na planta e na mina.. | F101: Apresentar novos modelos de kits de emergencia ambiental | G101: =IF(I101=1,"Concluído", IF(TODAY()>L101,"Atrasado", IF(AND(I101=0,TODAY()<K101),"Não iniciado", "Em Andamento"))) -> Concluído | I101: 1 | J101: =IFERROR( M101 / SUMIFS($M:$M, $E:$E, $E101, $O:$O, $O101) * 120, 0 ) -> 40.125589 | K101: 45749 | L101: 45961 | M101: =L101 - K101 + 1 -> 213 | N101: =IFERROR(INDEX(Tabela3[ID_Responsavel], MATCH(O101,Tabela3[[Responsáveis ]], 0)), "Não encontrado") -> 10 | O101: Guilherme Monteiro | P101: Biota | Q101: Foi marcado um benchmarking técnico com a empresa Toalim para o dia 10/11, com o objetivo de conhecer e avaliar soluções aplicáveis ao controle e tratamento de vazamentos de óleo em áreas operacionais da planta e da mina.
A102: =IFERROR(INDEX(Tabela2[ID_Area], MATCH(B102,Tabela2[Area], 0)), "Não encontrado") -> 1001 | B102: Meio Ambiente - Operação | C102: P&D | D102: =IFERROR(INDEX(Metas!$D$2:$D$104, MATCH(E102,Metas!$E$2:$E$104, 0)), "Não encontrado") -> 156 | E102: Implantar soluções técnicas para controles controle da vazamento de óleo na planta e na mina.. | F102: Testar nova tecnologia de tratamento de controle da vazamento de óleo na planta e na mina. | G102: =IF(I102=1,"Concluído", IF(TODAY()>L102,"Atrasado", IF(AND(I102=0,TODAY()<K102),"Não iniciado", "Em Andamento"))) -> Atrasado | I102: 0 | J102: =IFERROR( M102 / SUMIFS($M:$M, $E:$E, $E102, $O:$O, $O102) * 120, 0 ) -> 28.634223 | K102: 45870 | L102: 46021 | M102: =L102 - K102 + 1 -> 152 | N102: =IFERROR(INDEX(Tabela3[ID_Responsavel], MATCH(O102,Tabela3[[Responsáveis ]], 0)), "Não encontrado") -> 10 | O102: Guilherme Monteiro | P102: Biota | Q102: Realizado benchmarking com a empresa DISOL ECO BRASIL para testar um produto que quebra as particulas de hidrocarboneto/ Fornecedor enviou uma amostra do produto para teste, assim que chegar o produto no site SVPM iremos realizar uma teste operacional.
A103: =IFERROR(INDEX(Tabela2[ID_Area], MATCH(B103,Tabela2[Area], 0)), "Não encontrado") -> 1001 | B103: Meio Ambiente - Operação | C103: P&D | D103: =IFERROR(INDEX(Metas!$D$2:$D$104, MATCH(E103,Metas!$E$2:$E$104, 0)), "Não encontrado") -> 154 | E103: Implantar soluções técnicas para controles controle da vazamento de óleo na planta e na mina. | F103: Realizar levantamento de áreas de alto risco de vazamento | G103: =IF(I103=1,"Concluído", IF(TODAY()>L103,"Atrasado", IF(AND(I103=0,TODAY()<K103),"Não iniciado", "Em Andamento"))) -> Concluído | H103: 45964 | I103: 1 | J103: =IFERROR( M103 / SUMIFS($M:$M, $E:$E, $E103, $O:$O, $O103) * 120, 0 ) -> 55.209125 | K103: 45659 | L103: 46021 | M103: =L103 - K103 + 1 -> 363 | N103: =IFERROR(INDEX(Tabela3[ID_Responsavel], MATCH(O103,Tabela3[[Responsáveis ]], 0)), "Não encontrado") -> 17 | O103: Matheus | P103: Biota | Q103: A atividade foi finalizada devido à conclusão do levantamento e entrega das áreas classificadas como de alto risco de vazamento de óleo, contemplando tanto a planta quanto a mina.
A104: =IFERROR(INDEX(Tabela2[ID_Area], MATCH(B104,Tabela2[Area], 0)), "Não encontrado") -> 1001 | B104: Meio Ambiente - Operação | C104: P&D | D104: =IFERROR(INDEX(Metas!$D$2:$D$104, MATCH(E104,Metas!$E$2:$E$104, 0)), "Não encontrado") -> 154 | E104: Implantar soluções técnicas para controles controle da vazamento de óleo na planta e na mina. | F104: Apresentar novos modelos de kits de emergencia ambiental | G104: =IF(I104=1,"Concluído", IF(TODAY()>L104,"Atrasado", IF(AND(I104=0,TODAY()<K104),"Não iniciado", "Em Andamento"))) -> Concluído | I104: 1 | J104: =IFERROR( M104 / SUMIFS($M:$M, $E:$E, $E104, $O:$O, $O104) * 120, 0 ) -> 41.673004 | K104: 45749 | L104: 46022 | M104: =L104 - K104 + 1 -> 274 | N104: =IFERROR(INDEX(Tabela3[ID_Responsavel], MATCH(O104,Tabela3[[Responsáveis ]], 0)), "Não encontrado") -> 17 | O104: Matheus | P104: Biota | Q104: Benchmarking técnico com Toalim realizado em 10/11 para avaliação de soluções de controle e tratamento de óleo nas áreas operacionais da planta e da mina.
A105: =IFERROR(INDEX(Tabela2[ID_Area], MATCH(B105,Tabela2[Area], 0)), "Não encontrado") -> 1001 | B105: Meio Ambiente - Operação | C105: P&D | D105: =IFERROR(INDEX(Metas!$D$2:$D$104, MATCH(E105,Metas!$E$2:$E$104, 0)), "Não encontrado") -> 154 | E105: Implantar soluções técnicas para controles controle da vazamento de óleo na planta e na mina. | F105: Testar nova tecnologia de tratamento de controle da vazamento de óleo na planta e na mina. | G105: =IF(I105=1,"Concluído", IF(TODAY()>L105,"Atrasado", IF(AND(I105=0,TODAY()<K105),"Não iniciado", "Em Andamento"))) -> Concluído | I105: 1 | J105: =IFERROR( M105 / SUMIFS($M:$M, $E:$E, $E105, $O:$O, $O105) * 120, 0 ) -> 23.117871 | K105: 45870 | L105: 46021 | M105: =L105 - K105 + 1 -> 152 | N105: =IFERROR(INDEX(Tabela3[ID_Responsavel], MATCH(O105,Tabela3[[Responsáveis ]], 0)), "Não encontrado") -> 17 | O105: Matheus | P105: Biota | Q105: Recebido os materiais da empresa Toalim. Está programada para o dia 15/12/25 a realização dos testes com os materiais, em conjunto com a equipe de manutenção da usina.
A106: =IFERROR(INDEX(Tabela2[ID_Area], MATCH(B106,Tabela2[Area], 0)), "Não encontrado") -> 1001 | B106: Meio Ambiente - Operação | C106: Controle Ambiental | D106: =IFERROR(INDEX(Metas!$D$2:$D$104, MATCH(E106,Metas!$E$2:$E$104, 0)), "Não encontrado") -> 155 | E106: Determinar as principais bacias de drenagem natural da ADA SVPM e suas contribuições pluviais, para determinar a origem dos impactos de turbidez das bacias_Matheus | F106: Realizar levantamento topográfico detalhado das drenagens para definir os pontos de contribuição | G106: =IF(I106=1,"Concluído", IF(TODAY()>L106,"Atrasado", IF(AND(I106=0,TODAY()<K106),"Não iniciado", "Em Andamento"))) -> Concluído | H106: 45742 | I106: 1 | J106: =IFERROR( M106 / SUMIFS($M:$M, $E:$E, $E106, $O:$O, $O106) * 120, 0 ) -> 28.732394 | K106: 45659 | L106: 45709 | M106: =L106 - K106 + 1 -> 51 | N106: =IFERROR(INDEX(Tabela3[ID_Responsavel], MATCH(O106,Tabela3[[Responsáveis ]], 0)), "Não encontrado") -> 17 | O106: Matheus | P106: Biota | Q106: Realizado planejamento das atividades junto equipe de Meio Ambiente Operação, pois é uma meta compartilhada.
A107: =IFERROR(INDEX(Tabela2[ID_Area], MATCH(B107,Tabela2[Area], 0)), "Não encontrado") -> 1001 | B107: Meio Ambiente - Operação | C107: Controle Ambiental | D107: =IFERROR(INDEX(Metas!$D$2:$D$104, MATCH(E107,Metas!$E$2:$E$104, 0)), "Não encontrado") -> 155 | E107: Determinar as principais bacias de drenagem natural da ADA SVPM e suas contribuições pluviais, para determinar a origem dos impactos de turbidez das bacias_Matheus | F107: Criar modelo de elevação e definir estratégia de investigação | G107: =IF(I107=1,"Concluído", IF(TODAY()>L107,"Atrasado", IF(AND(I107=0,TODAY()<K107),"Não iniciado", "Em Andamento"))) -> Concluído | H107: 45723 | I107: 1 | J107: =IFERROR( M107 / SUMIFS($M:$M, $E:$E, $E107, $O:$O, $O107) * 120, 0 ) -> 11.830986 | K107: 45709 | L107: 45729 | M107: =L107 - K107 + 1 -> 21 | N107: =IFERROR(INDEX(Tabela3[ID_Responsavel], MATCH(O107,Tabela3[[Responsáveis ]], 0)), "Não encontrado") -> 17 | O107: Matheus | P107: Biota | Q107: Realizado todo o levantamento e estruturação para continuidade da montagem do diagrama
...

Sheet Dim_Responsaveis
A1: ID_Responsavel | B1: Responsáveis
A2: 1 | B2: Alan Boni
A3: 2 | B3: Allikison
A4: 3 | B4: Anna Laura
A5: 4 | B5: Cyro
A6: 5 | B6: Daniel
A7: 6 | B7: Dyse
A8: 7 | B8: Edimar Dias
A9: 8 | B9: Geovanna Freitas
A10: 9 | B10: Gilmar
A11: 10 | B11: Guilherme Monteiro
A12: 11 | B12: Jansley Rodart
A13: 12 | B13: Leonardo de Paula
... A28: 28 | B28: Mirelly Martins

Sheet Dim_Areas
A1: ID_Area | B1: Area
A2: 1000 | B2: Meio Ambiente - Gerencial
A3: 1001 | B3: Meio Ambiente - Operação
A4: 1002 | B4: Meio Biótico
A5: 1003 | B5: Meio Físico
A6: 1004 | B6: Licenciamento & Regulatório
